Workbook

Sheet Matriz
B2: DAIPUNTOS — Reglas de evaluación
B3: Las celdas en azul son las únicas editables. Todo lo demás son fórmulas.
B5: 1. PUNTOS BASE = IMPACTO × ALCANCE
B6: Impacto \ Alcance | C6: 1 Estación | D6: 2 Línea / Área | E6: 3 Multi-línea / planta
B7: 1 Orden / Visual | C7: 50 | D7: 100 | E7: 150
B8: 2 Tiempo / Retrabajo | C8: 100 | D8: 200 | E8: 300
B9: 3 Calidad / Seguridad | C9: 150 | D9: 300 | E9: 450
B11: 2. AHORRO — NO da puntos en DaiPuntos
B12: Ahorro anual MXN (desde) | C12: Puntos
B13: 0 | C13: 300
B14: 10000 | C14: 500
B15: 50000 | C15: 700
B16: 150000 | C16: 1000
B17: Los Kaizen con ahorro validado se reconocen en el SALÓN DEL AHORRO (hoja aparte), no con puntos.
B19: 3. BONOS
B20: Impacto en seguridad (automático si el indicador incluye 'Seguridad') | C20: 100
B21: Idea de operador — requiere campo nuevo en el Forms | C21: 50
B22: Ya replicada en otra área — requiere campo nuevo en el Forms | C22: 50
B23: Usó herramienta de mejora — requiere campo nuevo en el Forms | C23: 50
B24: Tope de bonos | C24: 200
B26: 4. SUPUESTOS
B27: Tipo de cambio (MXN por USD) — solo para convertir a mano un Kaizen capturado en USD | C27: 17
B28: La columna 'Ahorro MXN/año' de la hoja Evaluación se captura YA EN PESOS. Si el formato del Kaizen viene en USD, multiplícalo por este tipo de cambio antes de capturarlo.
B29: Meta: 420 Kaizen/año (35/mes) — ritmo real jun-ago fue 29/mes
B30: Niveles anuales: Bronce <600 · Plata 600-1,499 · Oro 1,500-2,499 · Platino 2,500+

Sheet Evaluación
A1: EVALUACIÓN DE KAIZEN — DaiPuntos
A2: DaiPuntos = matriz + bonos. El ahorro NO da puntos aquí: los proyectos con ahorro van al Salón del Ahorro (hoja aparte).
A4: ID | B4: Fecha impl. | C4: Mes | D4: Líder (persona que cuenta) | E4: Planta | F4: Departamento | G4: Categoría (principal) | H4: IMPACTO | I4: ALCANCE | J4: Ahorro MXN/año | K4: Pts matriz | L4: Pts ahorro (informativo) | M4: Bono seg. | N4: TOTAL | O4: Revisar | P4: Problema | Q4: Mejora | R4: Registró en el Form | S4: Indicadores marcados en el Form | T4: Archivo fuente | U4: Nómina
A5: 1 | B5: 2026-05-06 | C5: 2026-05 | D5: Genet Campos (registro de prueba) | E5: Planta 1 | F5: (inválido) | G5: Seguridad | H5: 3 | I5: 2 | K5: =INDEX(Matriz!$C$7:$E$9,H5,I5) -> 300 | L5: =IF(J5="",0,IF(J5<Matriz!$B$14,Matriz!$C$13,IF(J5<Matriz!$B$15,Matriz!$C$14,IF(J5<Matriz!$B$16,Matriz!$C$15,Matriz!$C$16)))) -> 0 | M5: =IF(ISNUMBER(SEARCH("Seguridad",S5)),Matriz!$C$20,0) -> 100 | N5: =K5+MIN(M5,Matriz!$C$24) -> 400 | O5: Registro de prueba del administrador — no cuenta. | P5: sd | Q5: df | R5: Genet Campos | S5: Seguridad
A6: 2 | B6: 2026-04-01 | C6: 2026-04 | D6: Karina Guadalupe Flores González | E6: Parras | F6: Compras | G6: Ahorro | H6: 3 | I6: 3 | K6: =INDEX(Matriz!$C$7:$E$9,H6,I6) -> 450 | L6: =IF(J6="",0,IF(J6<Matriz!$B$14,Matriz!$C$13,IF(J6<Matriz!$B$15,Matriz!$C$14,IF(J6<Matriz!$B$16,Matriz!$C$15,Matriz!$C$16)))) -> 0 | M6: =IF(ISNUMBER(SEARCH("Seguridad",S6)),Matriz!$C$20,0) -> 0 | N6: =K6+MIN(M6,Matriz!$C$24) -> 450 | O6: Descripción de la mejora vacía ('.') | P6: Negociación en costo por recoleccion | Q6: . | R6: Karina Guadalupe Flores Gonzalez | S6: Ahorro $ | T6: FM-MOP-0023-DR Formato de Kaizen -R3_Karina Guadalupe Flo.xlsx | U6: 3061818
A7: 3 | B7: 2026-05-20 | C7: 2026-05 | D7: Idalia Recio | E7: Planta 3/4 | F7: Calidad | G7: Medio Ambiente | H7: 1 | I7: 3 | K7: =INDEX(Matriz!$C$7:$E$9,H7,I7) -> 150 | L7: =IF(J7="",0,IF(J7<Matriz!$B$14,Matriz!$C$13,IF(J7<Matriz!$B$15,Matriz!$C$14,IF(J7<Matriz!$B$16,Matriz!$C$15,Matriz!$C$16)))) -> 0 | M7: =IF(ISNUMBER(SEARCH("Seguridad",S7)),Matriz!$C$20,0) -> 0 | N7: =K7+MIN(M7,Matriz!$C$24) -> 150 | O7: Indicador dice 'Medio Ambiente' pero la mejora es de método/eficiencia | P7: Auditores de LPAs realizan su auditoria de proceso con un formato incorrecto. El cual se les rechaza, ya que no cumple con el programa a auditar correcto y nivel o capa correcto y se tiene que volver a realizar en el formato correcto. | Q7: Incluir en el correo de comunicación de LPAs el link del formato correcto a utilizar para descargarlo con un solo clic | R7: Idalia Recio | S7: Medio Ambiente | T7: Kaizen Mayo Calidad_Idalia Recio.xlsx | U7: 3051929
A8: 4 | B8: 2026-04-29 | C8: 2026-04 | D8: Tania Alejandra Lira Villarreal | E8: Planta 3/4 | F8: Logística | G8: Ahorro | H8: 3 | I8: 3 | J8: 474000 | K8: =INDEX(Matriz!$C$7:$E$9,H8,I8) -> 450 | L8: =IF(J8="",0,IF(J8<Matriz!$B$14,Matriz!$C$13,IF(J8<Matriz!$B$15,Matriz!$C$14,IF(J8<Matriz!$B$16,Matriz!$C$15,Matriz!$C$16)))) -> 1000 | M8: =IF(ISNUMBER(SEARCH("Seguridad",S8)),Matriz!$C$20,0) -> 0 | N8: =K8+MIN(M8,Matriz!$C$24) -> 450 | P8: VOLATILIDAD EN COSTOS DE RUTA | Q8: COSTOS FIJOS POR PERIODOS DE 3 MESES | R8: Tania Alejandra Lira Villarreal | S8: Ahorro $ | T8: FM-MOP-0023-DR Formato de Kaizen -R3 1 LOGIST_Tania Alejandra Lira.xlsx | U8: 3047688
A9: 5 | B9: 2026-05-24 | C9: 2026-05 | D9: Federico Alberto Obispo Florencio | E9: Planta 2 | F9: Calidad | G9: Calidad | H9: 3 | I9: 1 | J9: 438000 | K9: =INDEX(Matriz!$C$7:$E$9,H9,I9) -> 150 | L9: =IF(J9="",0,IF(J9<Matriz!$B$14,Matriz!$C$13,IF(J9<Matriz!$B$15,Matriz!$C$14,IF(J9<Matriz!$B$16,Matriz!$C$15,Matriz!$C$16)))) -> 1000 | M9: =IF(ISNUMBER(SEARCH("Seguridad",S9)),Matriz!$C$20,0) -> 0 | N9: =K9+MIN(M9,Matriz!$C$24) -> 150 | P9: No se contaba con un metodo para la inspeccion de la parte interna del cargador de rivian | Q9: Se implementa una lampara para la inspeccion visual y deteccion de presencia de componentes del cargador | R9: Jose Emmanuel Alejo Wong | S9: FTQ;Eficiencia;Tiempo Muerto | T9: FM-MOP-0023-DR Formato de Kaizen -R2 Calidad-_Jose Emmanuel Alejo.xlsx | U9: 3039850
A10: 6 | B10: 2026-05-28 | C10: 2026-05 | D10: Citlalli Ozuna | E10: Planta 3/4 | F10: Lanzamientos | G10: Seguridad | H10: 3 | I10: 1 | K10: =INDEX(Matriz!$C$7:$E$9,H10,I10) -> 150 | L10: =IF(J10="",0,IF(J10<Matriz!$B$14,Matriz!$C$13,IF(J10<Matriz!$B$15,Matriz!$C$14,IF(J10<Matriz!$B$16,Matriz!$C$15,Matriz!$C$16)))) -> 0 | M10: =IF(ISNUMBER(SEARCH("Seguridad",S10)),Matriz!$C$20,0) -> 100 | N10: =K10+MIN(M10,Matriz!$C$24) -> 250 | P10: Kaizen para evitar quemaduras en area de pegado de foam | Q10: Colocar un porta pistola para evitar quemaduras | R10: Citlalli Ozuna | S10: Seguridad | U10: 3039635
A11: 7 | B11: 2026-06-01 | C11: 2026-06 | D11: Maria Fernanda Tovanche | E11: Planta 1 | F11: Materiales | G11: Ahorro | H11: 3 | I11: 3 | K11: =INDEX(Matriz!$C$7:$E$9,H11,I11) -> 450 | L11: =IF(J11="",0,IF(J11<Matriz!$B$14,Matriz!$C$13,IF(J11<Matriz!$B$15,Matriz!$C$14,IF(J11<Matriz!$B$16,Matriz!$C$15,Matriz!$C$16)))) -> 0 | M11: =IF(ISNUMBER(SEARCH("Seguridad",S11)),Matriz!$C$20,0) -> 0 | N11: =K11+MIN(M11,Matriz!$C$24) -> 450 | P11: Se estaba solicitando material al proveedor HURRBARD el cual generaba un costo mensual de 5,514USD considerando el costo de la piezas y el flete logistico de forma semanal. | Q11: Cambio de proveedor a Daimay Yindai con entrega en destino, sin costo logistico. | R11: Luis Gustavo Garcia Fuentes | S11: Ahorro $ | T11: FM-MOP-0023-DR Formato de Kaizen -R3 2_Luis Gustavo Garcia.xlsx | U11: 3049161
A12: 8 | B12: 2026-07-03 | C12: 2026-07 | D12: Francisco Hernandez Ramirez | E12: Planta 2 | F12: Lanzamientos | G12: Productividad | H12: 2 | I12: 2 | K12: =INDEX(Matriz!$C$7:$E$9,H12,I12) -> 200 | L12: =IF(J12="",0,IF(J12<Matriz!$B$14,Matriz!$C$13,IF(J12<Matriz!$B$15,Matriz!$C$14,IF(J12<Matriz!$B$16,Matriz!$C$15,Matriz!$C$16)))) -> 0 | M12: =IF(ISNUMBER(SEARCH("Seguridad",S12)),Matriz!$C$20,0) -> 0 | N12: =K12+MIN(M12,Matriz!$C$24) -> 200 | P12: mal flujo de la materia prima y material terminado | Q12: creacion de un flujo de material para evitar retrazos y pedida de este | R12: Francisco Hernandez | S12: Eficiencia;5S's | T12: Kaizen_LAUNCH_JUNIO_2026_Francisco Hernandez.xlsx | U12: 3055346
A13: 9 | B13: 2026-05-18 | C13: 2026-05 | D13: Brandon Durán | E13: Planta 1 | F13: Logística | G13: Productividad | H13: 3 | I13: 3 | K13: =INDEX(Matriz!$C$7:$E$9,H13,I13) -> 450 | L13: =IF(J13="",0,IF(J13<Matriz!$B$14,Matriz!$C$13,IF(J13<Matriz!$B$15,Matriz!$C$14,IF(J13<Matriz!$B$16,Matriz!$C$15,Matriz!$C$16)))) -> 0 | M13: =IF(ISNUMBER(SEARCH("Seguridad",S13)),Matriz!$C$20,0) -> 0 | N13: =K13+MIN(M13,Matriz!$C$24) -> 450 | P13: Costos elevados de tiempo extra en aduana | Q13: Conseguir otro agente aduanal para obtener una mejor tarifa | R13: Brandon Alejandro Duran Rios | S13: Eficiencia;Ahorro $ | T13: FM-MOP-0023-DR Formato de Kaizen -R3 1 JUNIO_Brandon Alejandro Du.xlsx | U13: 3059699
A14: 10 | B14: 2026-07-02 | C14: 2026-07 | D14: Juan Carlos Guerrero Lozano | E14: Planta 2 | F14: Manufactura | G14: Seguridad | H14: 3 | I14: 2 | K14: =INDEX(Matriz!$C$7:$E$9,H14,I14) -> 300 | L14: =IF(J14="",0,IF(J14<Matriz!$B$14,Matriz!$C$13,IF(J14<Matriz!$B$15,Matriz!$C$14,IF(J14<Matriz!$B$16,Matriz!$C$15,Matriz!$C$16)))) -> 0 | M14: =IF(ISNUMBER(SEARCH("Seguridad",S14)),Matriz!$C$20,0) -> 0 | N14: =K14+MIN(M14,Matriz!$C$24) -> 300 | P14: Lineas de produccion deficientes | Q14: Colocacion de cabinas para Esprayado | R14: Carlos Lozano | S14: Eficiencia;FTQ;5S's;Ergonomía | T14: Kaizen_MFG_JUNIO_2026_Carlos Lozano.xlsx | U14: 3038990
A15: 11 | B15: 2026-07-02 | C15: 2026-07 | D15: Monica Sifuentes Ortiz | E15: Planta 2 | F15: Recursos Humanos | G15: Productividad | H15: 2 | I15: 3 | K15: =INDEX(Matriz!$C$7:$E$9,H15,I15) -> 300 | L15: =IF(J15="",0,IF(J15<Matriz!$B$14,Matriz!$C$13,IF(J15<Matriz!$B$15,Matriz!$C$14,IF(J15<Matriz!$B$16,Matriz!$C$15,Matriz!$C$16)))) -> 0 | M15: =IF(ISNUMBER(SEARCH("Seguridad",S15)),Matriz!$C$20,0) -> 0 | N15: =K15+MIN(M15,Matriz!$C$24) -> 300 | P15: Anteriormente, el reporte de transportes se llevaba en formato impreso, lo que generaba demoras en la revisión y respuesta de la información por DM. Este proceso manual incrementaba los tiempos de atención y dificultaba el acceso oportuno a los datos necesarios para la toma de decisiones. | Q15: Se implementará un código QR enlazado al correo electrónico, con el objetivo de facilitar la comunicación con el usuario y obtener su retroalimentación de manera ágil, permitiendo brindar respuestas más oportunas y mejorar el seguimiento de las solicitudes. | R15: Monica Arcelia Sifuentes Ortiz | S15: Eficiencia;Tiempo Muerto | T15: FM-MOP-0023-DR Formato de Kaizen -R3 (003)_Monica Arcelia Sifue.xlsx | U15: 3065185
A16: 12 | B16: 2026-05-25 | C16: 2026-05 | D16: Ricardo Valdivia Leyva | E16: Planta 3/4 | F16: Calidad | G16: Calidad | H16: 3 | I16: 1 | K16: =INDEX(Matriz!$C$7:$E$9,H16,I16) -> 150 | L16: =IF(J16="",0,IF(J16<Matriz!$B$14,Matriz!$C$13,IF(J16<Matriz!$B$15,Matriz!$C$14,IF(J16<Matriz!$B$16,Matriz!$C$15,Matriz!$C$16)))) -> 0 | M16: =IF(ISNUMBER(SEARCH("Seguridad",S16)),Matriz!$C$20,0) -> 0 | N16: =K16+MIN(M16,Matriz!$C$24) -> 150 | P16: Piezas fuera de especificacion | Q16: Instalacion de poka yoke mecanico | R16: Ricardo Valdivia Leyva | S16: FTQ | T16: Kaizen Calidad P3-4-Junio_Ricardo Valdivia Ley.xlsx | U16: 3029443
A17: 13 | B17: 2026-06-05 | C17: 2026-06 | D17: Ricardo Mendoza Hernandez | E17: Planta 2 | F17: Materiales | G17: Seguridad | H17: 3 | I17: 2 | K17: =INDEX(Matriz!$C$7:$E$9,H17,I17) -> 300 | L17: =IF(J17="",0,IF(J17<Matriz!$B$14,Matriz!$C$13,IF(J17<Matriz!$B$15,Matriz!$C$14,IF(J17<Matriz!$B$16,Matriz!$C$15,Matriz!$C$16)))) -> 0 | M17: =IF(ISNUMBER(SEARCH("Seguridad",S17)),Matriz!$C$20,0) -> 100 | N17: =K17+MIN(M17,Matriz!$C$24) -> 400 | P17: Racks dañados en area de empaque | Q17: Cambiar racks dañados y habilidar 16 espacios adicionales | R17: Ricardo Mendoza Hernandez | S17: Seguridad;5S's | T17: FM-MOP-0023-DR Formato de Kaizen -R3 Reemplaz_Ricardo Mendoza Hern.xlsx | U17: 3035680
A18: 14 | B18: 2026-07-17 | C18: 2026-07 | D18: (líder no identificado) | E18: Planta 6/7 | F18: Calidad | G18: Seguridad | H18: 2 | I18: 1 | K18: =INDEX(Matriz!$C$7:$E$9,H18,I18) -> 100 | L18: =IF(J18="",0,IF(J18<Matriz!$B$14,Matriz!$C$13,IF(J18<Matriz!$B$15,Matriz!$C$14,IF(J18<Matriz!$B$16,Matriz!$C$15,Matriz!$C$16)))) -> 0 | M18: =IF(ISNUMBER(SEARCH("Seguridad",S18)),Matriz!$C$20,0) -> 0 | N18: =K18+MIN(M18,Matriz!$C$24) -> 100 | O18: El campo "Nombre de líder" trae texto no válido ("Optimización del area de trabajo"). Nómina 3062914. Confirmar con quien lo registró. | P18: érdida de tiempo buscando materiales. * Riesgo de contaminación o daño del producto. * Mayor probabilidad de accidentes. * Mala imagen del área de trabajo. | Q18: instalar, asignar, retirar, ordenar, delimitar | R18: Fernanda Monserrath Vielma Zavala | S18: Ergonomía;Eficiencia;Tiempo Muerto;5S's | T18: Kaizen Mesas de inspección Cuarentena -Antoni_Fernanda Monserrath.xlsx | U18: 3062914
A19: 15 | B19: 2026-06-22 | C19: 2026-06 | D19: Felipe Angel Guerrero Herrera | E19: Planta 2 | F19: Mantenimiento | G19: Seguridad | H19: 3 | I19: 1 | K19: =INDEX(Matriz!$C$7:$E$9,H19,I19) -> 150 | L19: =IF(J19="",0,IF(J19<Matriz!$B$14,Matriz!$C$13,IF(J19<Matriz!$B$15,Matriz!$C$14,IF(J19<Matriz!$B$16,Matriz!$C$15,Matriz!$C$16)))) -> 0 | M19: =IF(ISNUMBER(SEARCH("Seguridad",S19)),Matriz!$C$20,0) -> 100 | N19: =K19+MIN(M19,Matriz!$C$24) -> 250 | P19: plancha, se baja sola al estar inoperante, con riesgo de atrapamiento a operador. | Q19: implementacion de un Shot pin de seguridad que mantenga la platina de la maquina en reposo y evite caerse aun si se queda sin energia neumatica. | R19: Felipe Angel Guerrero Herrera | S19: Seguridad | T19: Kaizen_Mtto_JUN_2026_Felipe Angel Guerrer.xlsx | U19: 3060762
A20: 16 | B20: 2026-06-30 | C20: 2026-06 | D20: Citlalli Ozuna | E20: Planta 3/4 | F20: Lanzamientos | G20: Seguridad | H20: 3 | I20: 1 | K20: =INDEX(Matriz!$C$7:$E$9,H20,I20) -> 150 | L20: =IF(J20="",0,IF(J20<Matriz!$B$14,Matriz!$C$13,IF(J20<Matriz!$B$15,Matriz!$C$14,IF(J20<Matriz!$B$16,Matriz!$C$15,Matriz!$C$16)))) -> 0 | M20: =IF(ISNUMBER(SEARCH("Seguridad",S20)),Matriz!$C$20,0) -> 100 | N20: =K20+MIN(M20,Matriz!$C$24) -> 250 | P20: Rack para coodo de materiales de ensamble en descansabrazos | Q20: colocar el ensamble de los descansabrazos; teniendo problemas de acomodo y ergonomia en el personal | R20: Citlalli Ozuna | S20: Seguridad;Ergonomía;5S's | T20: Kaizen lanzameintos Junio Planta 4_Citlalli Ozuna.xlsx | U20: 3039635
A21: 17 | B21: 2026-07-03 | C21: 2026-07 | D21: Gerardo Aguilar González | E21: Planta 1 | F21: Manufactura | G21: Productividad | H21: 2 | I21: 2 | K21: =INDEX(Matriz!$C$7:$E$9,H21,I21) -> 200 | L21: =IF(J21="",0,IF(J21<Matriz!$B$14,Matriz!$C$13,IF(J21<Matriz!$B$15,Matriz!$C$14,IF(J21<Matriz!$B$16,Matriz!$C$15,Matriz!$C$16)))) -> 0 | M21: =IF(ISNUMBER(SEARCH("Seguridad",S21)),Matriz!$C$20,0) -> 0 | N21: =K21+MIN(M21,Matriz!$C$24) -> 200 | P21: Se generaban tiempos de espera, acumulación de piezas, riesgos en las entregas por el volumen de piezas por retrabajar | Q21: se instaló una segunda pieza prensa dedicada para el porceso de retrabajo | R21: Gerardo Aguilar Gonzalez | S21: Eficiencia | T21: Kaizen Manufactura Julio 26_Gerardo Aguilar Gonz.xlsx | U21: 3060366
A22: 18 | B22: 2026-06-29 | C22: 2026-06 | D22: Mario Alberto Duron Sifuentes | E22: Planta 1 | F22: Calidad | G22: Calidad | H22: 3 | I22: 1 | K22: =INDEX(Matriz!$C$7:$E$9,H22,I22) -> 150 | L22: =IF(J22="",0,IF(J22<Matriz!$B$14,Matriz!$C$13,IF(J22<Matriz!$B$15,Matriz!$C$14,IF(J22<Matriz!$B$16,Matriz!$C$15,Matriz!$C$16)))) -> 0 | M22: =IF(ISNUMBER(SEARCH("Seguridad",S22)),Matriz!$C$20,0) -> 0 | N22: =K22+MIN(M22,Matriz!$C$24) -> 150 | P22: Camara de vision ajustada solo a un nivel de tiro corto presentado en lock tab de bracket | Q22: Se mejora el ajuste de la camara de vision con diferentes niveles de tiro corto en el lock tab del bracket, obteniendo 3 red rabbits para la liberacion del proceso y validacion de la camara de vision | R22: Mario Alberto Durón Sifuentes | S22: FTQ;Scrap | T22: Kaizen Julio 2026 Calidad Nuevo formato_Mario Alberto Durón.xlsx | U22: 3064460
A23: 19 | B23: 2026-06-29 | C23: 2026-06 | D23: Jose Isai Tostado Beltran | E23: Planta 1 | F23: Mantenimiento | G23: Productividad | H23: 3 | I23: 1 | K23: =INDEX(Matriz!$C$7:$E$9,H23,I23) -> 150 | L23: =IF(J23="",0,IF(J23<Matriz!$B$14,Matriz!$C$13,IF(J23<Matriz!$B$15,Matriz!$C$14,IF(J23<Matriz!$B$16,Matriz!$C$15,Matriz!$C$16)))) -> 0 | M23: =IF(ISNUMBER(SEARCH("Seguridad",S23)),Matriz!$C$20,0) -> 0 | N23: =K23+MIN(M23,Matriz!$C$24) -> 150 | P23: daño de secador y no se cuenta con tarjetas obsoletas no se puede reparar se realiza cambio de control y se reconecta dejando funcional secador | Q23: reparacion de control de secador | R23: Mariana Valencia | S23: Tiempo Muerto;Ahorro $ | T23: kaizen Junio 2026_Mariana Valencia.xlsx | U23: 3024217
A24: 20 | B24: 2026-07-04 | C24: 2026-07 | D24: Arturo Romo | E24: Planta 1 | F24: Manufactura | G24: Calidad | H24: 3 | I24: 1 | K24: =INDEX(Matriz!$C$7:$E$9,H24,I24) -> 150 | L24: =IF(J24="",0,IF(J24<Matriz!$B$14,Matriz!$C$13,IF(J24<Matriz!$B$15,Matriz!$C$14,IF(J24<Matriz!$B$16,Matriz!$C$15,Matriz!$C$16)))) -> 0 | M24: =IF(ISNUMBER(SEARCH("Seguridad",S24)),Matriz!$C$20,0) -> 0 | N24: =K24+MIN(M24,Matriz!$C$24) -> 150 | P24: TOLVA SE ESCARCHA DESPUES DE VARIAS CARGAS O TIEMPO | Q24: ESTABLECER UNA HORA PARA LA LIMPIEZA Y SECADO | R24: Arturo Romo Antonio | S24: Scrap;Tiempo Muerto;Eficiencia | T24: kaizen Julio 2026 Nitro_Arturo Romo Antonio.xlsx | U24: 3064592
A25: 21 | B25: 2026-06-01 | C25: 2026-06 | D25: Arsenio E Vazquez | E25: Planta 1 | F25: Calidad | G25: Calidad | H25: 3 | I25: 1 | K25: =INDEX(Matriz!$C$7:$E$9,H25,I25) -> 150 | L25: =IF(J25="",0,IF(J25<Matriz!$B$14,Matriz!$C$13,IF(J25<Matriz!$B$15,Matriz!$C$14,IF(J25<Matriz!$B$16,Matriz!$C$15,Matriz!$C$16)))) -> 0 | M25: =IF(ISNUMBER(SEARCH("Seguridad",S25)),Matriz!$C$20,0) -> 0 | N25: =K25+MIN(M25,Matriz!$C$24) -> 150 | O25: Contenido inválido: problema='Mexico', mejora=correo electrónico | P25: Mexico | Q25: evazquez@daimayus.com | R25: Arsenio Vazquez | S25: FTQ;Ahorro $ | T25: FM-MOP-0023-DR Formato de Kaizen -R3 (1)_Arsenio Vazquez.xlsx | U25: 3030820
A26: 22 | B26: 2026-07-13 | C26: 2026-07 | D26: Maximiliano Escobedo | E26: Planta 1 | F26: Lanzamientos | G26: Productividad | H26: 2 | I26: 3 | K26: =INDEX(Matriz!$C$7:$E$9,H26,I26) -> 300 | L26: =IF(J26="",0,IF(J26<Matriz!$B$14,Matriz!$C$13,IF(J26<Matriz!$B$15,Matriz!$C$14,IF(J26<Matriz!$B$16,Matriz!$C$15,Matriz!$C$16)))) -> 0 | M26: =IF(ISNUMBER(SEARCH("Seguridad",S26)),Matriz!$C$20,0) -> 0 | N26: =K26+MIN(M26,Matriz!$C$24) -> 300 | P26: No se tiene un checklist de transferencia en programas interplantas | Q26: Crear un checklist de transferencia de programas para un seguimiento puntual en las actividades a realizar | R26: Maximiliano Escobedo | S26: Eficiencia | T26: KAIZEN JULIO CHECKLIST DE TRANSFERENCIA_Maximiliano Escobedo.xlsx | U26: 3041291
A27: 23 | B27: 2026-07-14 | C27: 2026-07 | D27: Emiliano Zuñiga | E27: Planta 1 | F27: Lanzamientos | G27: Productividad | H27: 2 | I27: 2 | K27: =INDEX(Matriz!$C$7:$E$9,H27,I27) -> 200 | L27: =IF(J27="",0,IF(J27<Matriz!$B$14,Matriz!$C$13,IF(J27<Matriz!$B$15,Matriz!$C$14,IF(J27<Matriz!$B$16,Matriz!$C$15,Matriz!$C$16)))) -> 0 | M27: =IF(ISNUMBER(SEARCH("Seguridad",S27)),Matriz!$C$20,0) -> 0 | N27: =K27+MIN(M27,Matriz!$C$24) -> 200 | P27: En el área de nitrógeno, las cajas de material correspondientes a los botones se almacenan en un solo estante sin una organización definida. Actualmente se manejan más de 10 números de parte, los cuales se encuentran mezclados y sin una identificación visual clara. Esta condición dificulta que el operador o el runner localicen rápidamente el material requerido, incrementando el tiempo de búsqueda | Q27: se instalará un rack de mayor capacidad para organizar las cajas de material y asignar un espacio específico a cada número de parte. Además, se implementarán ayudas visuales mediante etiquetas y señalización para facilitar la identificación del material, reduciendo el tiempo de búsqueda y minimizando errores en el abastecimiento. | R27: Fannie Grettelle Aguilar Valero | S27: Eficiencia;Tiempo Muerto;5S's | T27: FM-MOP-0023-DR Formato de Kaizen -R3_Fannie Grettelle Agu.xlsx | U27: 3063949
A28: 24 | B28: 2026-07-10 | C28: 2026-07 | D28: Jose Isai Tostado Beltran | E28: Planta 1 | F28: Mantenimiento | G28: Ahorro | H28: 3 | I28: 2 | K28: =INDEX(Matriz!$C$7:$E$9,H28,I28) -> 300 | L28: =IF(J28="",0,IF(J28<Matriz!$B$14,Matriz!$C$13,IF(J28<Matriz!$B$15,Matriz!$C$14,IF(J28<Matriz!$B$16,Matriz!$C$15,Matriz!$C$16)))) -> 0 | M28: =IF(ISNUMBER(SEARCH("Seguridad",S28)),Matriz!$C$20,0) -> 0 | N28: =K28+MIN(M28,Matriz!$C$24) -> 300 | P28: Llegada de maquinas de inyeccion se necesita hacer espacio y facilidades | Q28: Movimiento de 2 maquinas 714 y 715 de 160 toneladas a nueva locacion para hacer espacio e instalar maquinas nuevas que mandaran de china realizacion de bajadas elecricas de agua de aire conexion de maquina nivelacion y pruebas de funcionamiento. | R28: Mariana Valencia | S28: Ahorro $ | T28: kaizen julio 2026_Mariana Valencia.xlsx | U28: 3024217
A29: 25 | B29: 2026-07-10 | C29: 2026-07 | D29: José Gerardo Gudiño Ruiz | E29: Planta 1 | F29: Cenzontle No. 7 Parque Industrial Finsa Ramos Arizpe, Coahuila, Mexico. | G29: Seguridad | H29: 3 | I29: 2 | K29: =INDEX(Matriz!$C$7:$E$9,H29,I29) -> 300 | L29: =IF(J29="",0,IF(J29<Matriz!$B$14,Matriz!$C$13,IF(J29<Matriz!$B$15,Matriz!$C$14,IF(J29<Matriz!$B$16,Matriz!$C$15,Matriz!$C$16)))) -> 0 | M29: =IF(ISNUMBER(SEARCH("Seguridad",S29)),Matriz!$C$20,0) -> 100 | N29: =K29+MIN(M29,Matriz!$C$24) -> 400 | O29: La descripción trae un correo pegado antes del texto | P29: No se tenia espejo concavo en DQMC Moldeo | Q29: jgudino@daimayus.comNo se tenia visibilidad efectiva en el área, y se opto por colocar un espejo concavo para mejorar la visibiidad del transito y eliminar el riesgo de accidentes por equipo motorizado | R29: Jose Gerardo Gudiño Ruiz | S29: Seguridad | T29: FM-MOP-0023-DR Formato de Kaizen junio 26_Jose Gerardo Gudiño.xlsx
A30: 26 | B30: 2026-06-18 | C30: 2026-06 | D30: Ulises Hernandez | E30: Planta 1 | F30: Producción | G30: Calidad | H30: 3 | I30: 2 | K30: =INDEX(Matriz!$C$7:$E$9,H30,I30) -> 300 | L30: =IF(J30="",0,IF(J30<Matriz!$B$14,Matriz!$C$13,IF(J30<Matriz!$B$15,Matriz!$C$14,IF(J30<Matriz!$B$16,Matriz!$C$15,Matriz!$C$16)))) -> 0 | M30: =IF(ISNUMBER(SEARCH("Seguridad",S30)),Matriz!$C$20,0) -> 0 | N30: =K30+MIN(M30,Matriz!$C$24) -> 300 | P30: Defectos y tiempo muerto por daños de molde | Q30: Se implementan camaras de vision para prevenir daños de molde | R30: Ulises Eduardo Hernandez Perez | S30: Scrap;Tiempo Muerto | T30: FM-MOP-0023-DR Formato de Kaizen -R2 (2)_Ulises Eduardo Herna.xlsx | U30: 3055561
A31: 27 | B31: 2026-06-25 | C31: 2026-06 | D31: Saúl Antonio Gallegos Sánchez | E31: Planta 2 | F31: EHS | G31: Seguridad | H31: 3 | I31: 2 | K31: =INDEX(Matriz!$C$7:$E$9,H31,I31) -> 300 | L31: =IF(J31="",0,IF(J31<Matriz!$B$14,Matriz!$C$13,IF(J31<Matriz!$B$15,Matriz!$C$14,IF(J31<Matriz!$B$16,Matriz!$C$15,Matriz!$C$16)))) -> 0 | M31: =IF(ISNUMBER(SEARCH("Seguridad",S31)),Matriz!$C$20,0) -> 100 | N31: =K31+MIN(M31,Matriz!$C$24) -> 400 | P31: El área no cuenta con una estación lava ojos | Q31: Colocar una estación lava ojos para cualquier emergencia | R31: Saul Antonio Gallegos Sanchez | S31: Seguridad | T31: FM-MOP-0023-DR Formato de Kaizen -R3 LAVA OJO_Saul Antonio Gallego.xlsx | U31: 3030328
A32: 28 | B32: 2026-06-10 | C32: 2026-06 | D32: Monserrat Arana | E32: Planta 1 | F32: Materiales | G32: Ahorro | H32: 3 | I32: 3 | K32: =INDEX(Matriz!$C$7:$E$9,H32,I32) -> 450 | L32: =IF(J32="",0,IF(J32<Matriz!$B$14,Matriz!$C$13,IF(J32<Matriz!$B$15,Matriz!$C$14,IF(J32<Matriz!$B$16,Matriz!$C$15,Matriz!$C$16)))) -> 0 | M32: =IF(ISNUMBER(SEARCH("Seguridad",S32)),Matriz!$C$20,0) -> 0 | N32: =K32+MIN(M32,Matriz!$C$24) -> 450 | O32: Descripción muy pobre para justificar puntos ('Ahorro en cambio de proveedor') | P32: Compra de material directo | Q32: Ahorro en cambio de proveedor | R32: Luis Gustavo Garcia Fuentes | S32: Ahorro $ | T32: FM-MOP-0023-DR Formato de Kaizen - EFLEXO_Luis Gustavo Garcia.xlsx | U32: 3041429
A33: 29 | B33: 2026-07-06 | C33: 2026-07 | D33: Ruben Siller | E33: Planta 6/7 | F33: Recursos Humanos | G33: Ahorro | H33: 3 | I33: 3 | K33: =INDEX(Matriz!$C$7:$E$9,H33,I33) -> 450 | L33: =IF(J33="",0,IF(J33<Matriz!$B$14,Matriz!$C$13,IF(J33<Matriz!$B$15,Matriz!$C$14,IF(J33<Matriz!$B$16,Matriz!$C$15,Matriz!$C$16)))) -> 0 | M33: =IF(ISNUMBER(SEARCH("Seguridad",S33)),Matriz!$C$20,0) -> 0 | N33: =K33+MIN(M33,Matriz!$C$24) -> 450 | P33: Ocupacion baja en rutas de transporte de fines de semana | Q33: Reduccion de rutas de transprote para aumentar la ocupacion y disminuir costo | R33: Ruben Alejandro Siller Valverde | S33: Ahorro $ | T33: Copy of FM-MOP-0023-DR Formato de Kaizen -JUL_Ruben Alejandro Sill.xlsx | U33: 3055539
A34: 30 | B34: 2026-07-10 | C34: 2026-07 | D34: Gerardo Gudiño Ruiz | E34: Planta 1 | F34: EHS | G34: Seguridad | H34: 3 | I34: 2 | K34: =INDEX(Matriz!$C$7:$E$9,H34,I34) -> 300 | L34: =IF(J34="",0,IF(J34<Matriz!$B$14,Matriz!$C$13,IF(J34<Matriz!$B$15,Matriz!$C$14,IF(J34<Matriz!$B$16,Matriz!$C$15,Matriz!$C$16)))) -> 0 | M34: =IF(ISNUMBER(SEARCH("Seguridad",S34)),Matriz!$C$20,0) -> 100 | N34: =K34+MIN(M34,Matriz!$C$24) -> 400 | P34: Daño en tuberias de sistema lavaojos por alta dureza en el agua utilizada. | Q34: Se coloca lavaojos portatil con agua y solución de Ag para eliminar sales minerales. | R34: Jose Gerardo Gudiño Ruiz | S34: Seguridad;Medio Ambiente | U34: 3058416
A35: 31 | B35: 2026-07-06 | C35: 2026-07 | D35: Eduardo Gonzalez | E35: Planta 1 | F35: Recursos Humanos | G35: Productividad | H35: 3 | I35: 3 | K35: =INDEX(Matriz!$C$7:$E$9,H35,I35) -> 450 | L35: =IF(J35="",0,IF(J35<Matriz!$B$14,Matriz!$C$13,IF(J35<Matriz!$B$15,Matriz!$C$14,IF(J35<Matriz!$B$16,Matriz!$C$15,Matriz!$C$16)))) -> 0 | M35: =IF(ISNUMBER(SEARCH("Seguridad",S35)),Matriz!$C$20,0) -> 0 | N35: =K35+MIN(M35,Matriz!$C$24) -> 450 | P35: no se tenia para personal directo registro de vacaciones en linea | Q35: se pone kiosko con aplicacion de porwer app para que puedan acceder a pedir sus vacaciones de manera electronica | R35: Diana Themis Zacanelles Orta | S35: Eficiencia;Tiempo Muerto;Ahorro $ | T35: Formato de Kaizen RH Julio_Diana Themis Zacanel.xlsx | U35: 3029246
A36: 32 | B36: 2026-07-17 | C36: 2026-07 | D36: Saúl Antonio Gallegos Sánchez | E36: Planta 2 | F36: EHS | G36: Seguridad | H36: 3 | I36: 2 | K36: =INDEX(Matriz!$C$7:$E$9,H36,I36) -> 300 | L36: =IF(J36="",0,IF(J36<Matriz!$B$14,Matriz!$C$13,IF(J36<Matriz!$B$15,Matriz!$C$14,IF(J36<Matriz!$B$16,Matriz!$C$15,Matriz!$C$16)))) -> 0 | M36: =IF(ISNUMBER(SEARCH("Seguridad",S36)),Matriz!$C$20,0) -> 100 | N36: =K36+MIN(M36,Matriz!$C$24) -> 400 | P36: Anteriormente se usaba una cinta para cubrir sus dedos, esa cinta generaba un gasto ya que era parte del proceso de producción | Q36: Se cambia a una cinta dedal mas economica exclusiva como equipo de protección | R36: Saul Antonio Gallegos Sanchez | S36: Seguridad;Ahorro $ | T36: FM-MOP-0023-DR Formato de Kaizen -R3 Julio EH_Saul Antonio Gallego.xlsx | U36: 3030328
A37: 33 | B37: 2026-07-15 | C37: 2026-07 | D37: Francisco Hernandez Ramirez | E37: Planta 2 | F37: Lanzamientos | G37: Seguridad | H37: 3 | I37: 2 | K37: =INDEX(Matriz!$C$7:$E$9,H37,I37) -> 300 | L37: =IF(J37="",0,IF(J37<Matriz!$B$14,Matriz!$C$13,IF(J37<Matriz!$B$15,Matriz!$C$14,IF(J37<Matriz!$B$16,Matriz!$C$15,Matriz!$C$16)))) -> 0 | M37: =IF(ISNUMBER(SEARCH("Seguridad",S37)),Matriz!$C$20,0) -> 0 | N37: =K37+MIN(M37,Matriz!$C$24) -> 300 | P37: acumulado de material productivo que se empalmaba y generaba daños | Q37: se coloca un tandedero par apoder tener mejor aocmodo dle material productivo | R37: Francisco Hernandez | S37: Ergonomía;Eficiencia;Scrap;Tiempo Muerto | T37: Kaizen_LAUNCH_JULIO_2026_Francisco Hernandez.xlsx | U37: 3055346
A38: 34 | B38: 2026-07-13 | C38: 2026-07 | D38: Monica Sifuentes Ortiz | E38: Planta 2 | F38: Recursos Humanos | G38: Productividad | H38: 2 | I38: 3 | K38: =INDEX(Matriz!$C$7:$E$9,H38,I38) -> 300 | L38: =IF(J38="",0,IF(J38<Matriz!$B$14,Matriz!$C$13,IF(J38<Matriz!$B$15,Matriz!$C$14,IF(J38<Matriz!$B$16,Matriz!$C$15,Matriz!$C$16)))) -> 0 | M38: =IF(ISNUMBER(SEARCH("Seguridad",S38)),Matriz!$C$20,0) -> 0 | N38: =K38+MIN(M38,Matriz!$C$24) -> 300 | P38: El sistema agrupaba a los colaboradores en líneas de producción de forma general. Era complicado identificar con precisión el área específica donde laboraba cada empleado. Esto ocasionaba demoras al generar reportes, realizar movimientos de personal o analizar indicadores por área. | Q38: Se actualizó el catálogo de líneas y se asignó a cada colaborador el área específica donde realmente desempeña sus funciones. Se homologó la nomenclatura para evitar confusiones entre áreas. | R38: Monica Arcelia Sifuentes Ortiz | S38: Eficiencia;Tiempo Muerto | T38: FM-MOP-0023-DR Formato de Kaizen -R3 - PROPUE_Monica Arcelia Sifue.xlsx | U38: 3065185
A39: 35 | B39: 2026-07-03 | C39: 2026-07 | D39: Gerardo Rodriguez Garay | E39: Planta 1 | F39: Calidad | G39: Productividad | H39: 2 | I39: 1 | K39: =INDEX(Matriz!$C$7:$E$9,H39,I39) -> 100 | L39: =IF(J39="",0,IF(J39<Matriz!$B$14,Matriz!$C$13,IF(J39<Matriz!$B$15,Matriz!$C$14,IF(J39<Matriz!$B$16,Matriz!$C$15,Matriz!$C$16)))) -> 0 | M39: =IF(ISNUMBER(SEARCH("Seguridad",S39)),Matriz!$C$20,0) -> 0 | N39: =K39+MIN(M39,Matriz!$C$24) -> 100 | P39: Cabecera T1XX con problemas de alineacion (deformacion) | Q39: revision de piezas con pin actuador de mecanismo | R39: Gerardo Rodriguez | S39: Eficiencia | T39: Kaizen Moldeo - Julio '2026 (1)_Gerardo Rodriguez.xlsx | U39: 1616978
A40: 36 | B40: 2026-07-27 | C40: 2026-07 | D40: Juan Carlos Guerrero Lozano | E40: Planta 2 | F40: Manufactura | G40: Productividad | H40: 2 | I40: 2 | K40: =INDEX(Matriz!$C$7:$E$9,H40,I40) -> 200 | L40: =IF(J40="",0,IF(J40<Matriz!$B$14,Matriz!$C$13,IF(J40<Matriz!$B$15,Matriz!$C$14,IF(J40<Matriz!$B$16,Matriz!$C$15,Matriz!$C$16)))) -> 0 | M40: =IF(ISNUMBER(SEARCH("Seguridad",S40)),Matriz!$C$20,0) -> 0 | N40: =K40+MIN(M40,Matriz!$C$24) -> 200 | P40: Lineas de produccion deficientes | Q40: Creacion de TOOL BOOK | R40: Carlos Lozano | S40: Eficiencia;5S's | T40: Kaizen_MFG_JULIO_2026_Carlos Lozano.xlsx | U40: 3038990
A41: 37 | B41: 2026-07-20 | C41: 2026-07 | D41: Hector Velasco | E41: Planta 6/7 | F41: Manufactura | G41: Productividad | H41: 2 | I41: 1 | K41: =INDEX(Matriz!$C$7:$E$9,H41,I41) -> 100 | L41: =IF(J41="",0,IF(J41<Matriz!$B$14,Matriz!$C$13,IF(J41<Matriz!$B$15,Matriz!$C$14,IF(J41<Matriz!$B$16,Matriz!$C$15,Matriz!$C$16)))) -> 0 | M41: =IF(ISNUMBER(SEARCH("Seguridad",S41)),Matriz!$C$20,0) -> 0 | N41: =K41+MIN(M41,Matriz!$C$24) -> 100 | P41: La máquina de ensamble de botón presenta fallas recurrentes desde principios de mayo. La principal causa es el movimiento de la cámara de visión, ya que no se encuentra correctamente sujeta. Esta condición provoca falsos rechazos de piezas y paros frecuentes de la máquina, afectando la estabilidad del proceso y la productividad. | Q41: Se propone diseñar e instalar una base de soporte para asegurar la correcta fijación de la cámara de visión y eliminar su movimiento durante el ciclo de operación de la máquina. Con esta mejora se busca reducir los falsos rechazos, minimizar los paros de máquina y aumentar la eficiencia del proceso de ensamble | R41: Jennifer Garcia Gregorio | S41: Eficiencia | T41: Formato de Kaizen Manufactura P6_Jennifer Garcia Greg.xlsx | U41: 3035216
A42: 38 | B42: 2026-07-27 | C42: 2026-07 | D42: Erik Fernando Zapata | E42: Planta 6/7 | F42: Lanzamientos | G42: Productividad | H42: 2 | I42: 2 | K42: =INDEX(Matriz!$C$7:$E$9,H42,I42) -> 200 | L42: =IF(J42="",0,IF(J42<Matriz!$B$14,Matriz!$C$13,IF(J42<Matriz!$B$15,Matriz!$C$14,IF(J42<Matriz!$B$16,Matriz!$C$15,Matriz!$C$16)))) -> 0 | M42: =IF(ISNUMBER(SEARCH("Seguridad",S42)),Matriz!$C$20,0) -> 0 | N42: =K42+MIN(M42,Matriz!$C$24) -> 200 | P42: La inspeccion de DQMC tiene altos tiempos ciclo de liberacion por que se han agregado diferentes inspecciones por las varias alertas de calidad que se han reportado | Q42: Se propone eliminar la inspeccion con el gage de distancia de postes para reducir el tiempo ciclo 1.50 seg y mejorar el tiempo general de ciclo que aumento por los diversos puntos agregados, ahora se toma esa misma distancia en el proceso anterior, unificando inspecciones (Esto representa un total de 143 piezas mas por turno por mesa y por version , dando un total 572 pieza totales. | R42: Hector Orduño Jauregui | S42: Eficiencia | T42: Kaizen Julio 2026_Hector Orduño Jaureg.xlsx | U42: 3048407
A43: 39 | B43: 2026-07-20 | C43: 2026-07 | D43: Alejandro Lopez Lopez | E43: Planta 3/4 | F43: Recursos Humanos | G43: Productividad | H43: 3 | I43: 3 | K43: =INDEX(Matriz!$C$7:$E$9,H43,I43) -> 450 | L43: =IF(J43="",0,IF(J43<Matriz!$B$14,Matriz!$C$13,IF(J43<Matriz!$B$15,Matriz!$C$14,IF(J43<Matriz!$B$16,Matriz!$C$15,Matriz!$C$16)))) -> 0 | M43: =IF(ISNUMBER(SEARCH("Seguridad",S43)),Matriz!$C$20,0) -> 0 | N43: =K43+MIN(M43,Matriz!$C$24) -> 450 | O43: Descripción circular ('Se digitaliza el reporte' = el problema) | P43: Se digitaliza proceso de reporte de transporte | Q43: Se digitaliza el reporte de transporte | R43: Alejandro Lopez Lopez | S43: Tiempo Muerto;Eficiencia;Ahorro $ | T43: FM-MOP-0023-DR_Kaizen_Reportes_Transporte_For_Alejandro Lopez Lope.xlsx | U43: 3044202
A44: 40 | B44: 2026-07-15 | C44: 2026-07 | D44: Tania Alejandra Lira Villarreal | E44: Planta 6/7 | F44: Logística | G44: Ahorro | H44: 3 | I44: 3 | J44: 438000 | K44: =INDEX(Matriz!$C$7:$E$9,H44,I44) -> 450 | L44: =IF(J44="",0,IF(J44<Matriz!$B$14,Matriz!$C$13,IF(J44<Matriz!$B$15,Matriz!$C$14,IF(J44<Matriz!$B$16,Matriz!$C$15,Matriz!$C$16)))) -> 1000 | M44: =IF(ISNUMBER(SEARCH("Seguridad",S44)),Matriz!$C$20,0) -> 0 | N44: =K44+MIN(M44,Matriz!$C$24) -> 450 | P44: COSTO ALTO EN RUTA DE SAGE LERMA | Q44: LICITACION PROVEEDORES EXTERNOS | R44: Tania Alejandra Lira Villarreal | S44: Ahorro $ | T44: FM-MOP-0023-DR Formato de Kaizen -R3 1 LOGIST_Tania Alejandra Lira 1.xlsx | U44: 3047688
A45: 41 | B45: 2026-07-22 | C45: 2026-07 | D45: Daniel Alejandro Parra Mendoza | E45: Parras | F45: EHS | G45: Seguridad | H45: 3 | I45: 2 | J45: 438000 | K45: =INDEX(Matriz!$C$7:$E$9,H45,I45) -> 300 | L45: =IF(J45="",0,IF(J45<Matriz!$B$14,Matriz!$C$13,IF(J45<Matriz!$B$15,Matriz!$C$14,IF(J45<Matriz!$B$16,Matriz!$C$15,Matriz!$C$16)))) -> 1000 | M45: =IF(ISNUMBER(SEARCH("Seguridad",S45)),Matriz!$C$20,0) -> 100 | N45: =K45+MIN(M45,Matriz!$C$24) -> 400 | P45: CONTAMINACION DE AREAS | Q45: SE ESTANDARIZO EL AREA DE DISPOSICION DE QUIMICOS PELIGROSOS DEL PROCESO DE FOAM | R45: Daniel Alejandro Parra Mendoza | S45: Seguridad;Medio Ambiente;Scrap;5S's | T45: FM-MOP-0023-DR Formato de Kaizen - Julio_Daniel Alejandro Par.xlsx | U45: 3066566
A46: 42 | B46: 2026-07-24 | C46: 2026-07 | D46: Omar Alvarez | E46: Planta 3/4 | F46: EHS | G46: Seguridad | H46: 3 | I46: 2 | K46: =INDEX(Matriz!$C$7:$E$9,H46,I46) -> 300 | L46: =IF(J46="",0,IF(J46<Matriz!$B$14,Matriz!$C$13,IF(J46<Matriz!$B$15,Matriz!$C$14,IF(J46<Matriz!$B$16,Matriz!$C$15,Matriz!$C$16)))) -> 0 | M46: =IF(ISNUMBER(SEARCH("Seguridad",S46)),Matriz!$C$20,0) -> 100 | N46: =K46+MIN(M46,Matriz!$C$24) -> 400 | P46: Extintores de stock colocados en piso, incumplimiento de NOM 002 STPS 2010 | Q46: Colocar canastilla para extintores de stock | R46: Omar Alejandro Alvarez Charles | S46: Seguridad | T46: FM-MOP-0023-DR Formato de Kaizen -R3 Julio EH_Omar Alejandro Alvar.xlsx | U46: 3067714
A47: 43 | B47: 2026-07-28 | C47: 2026-07 | D47: Felipe Angel Guerrero Herrera | E47: Planta 2 | F47: Mantenimiento | G47: Seguridad | H47: 3 | I47: 1 | K47: =INDEX(Matriz!$C$7:$E$9,H47,I47) -> 150 | L47: =IF(J47="",0,IF(J47<Matriz!$B$14,Matriz!$C$13,IF(J47<Matriz!$B$15,Matriz!$C$14,IF(J47<Matriz!$B$16,Matriz!$C$15,Matriz!$C$16)))) -> 0 | M47: =IF(ISNUMBER(SEARCH("Seguridad",S47)),Matriz!$C$20,0) -> 100 | N47: =K47+MIN(M47,Matriz!$C$24) -> 250 | P47: operacion manual, con cautin con riesgo a quemarse y a danar el producto | Q47: fabricacion de fixturo semiautomatico | R47: Felipe Angel Guerrero Herrera | S47: Seguridad;Eficiencia;Tiempo Muerto;Ahorro $;FTQ;Scrap;Ergonomía | T47: Kaizen_Mtto_JUL_2026 Mejora_Felipe Angel Guerrer.xlsx | U47: 3060762
A48: 44 | B48: 2026-07-18 | C48: 2026-07 | D48: Felipe Angel Guerrero Herrera | E48: Planta 2 | F48: Mantenimiento | G48: Seguridad | H48: 3 | I48: 3 | K48: =INDEX(Matriz!$C$7:$E$9,H48,I48) -> 450 | L48: =IF(J48="",0,IF(J48<Matriz!$B$14,Matriz!$C$13,IF(J48<Matriz!$B$15,Matriz!$C$14,IF(J48<Matriz!$B$16,Matriz!$C$15,Matriz!$C$16)))) -> 0 | M48: =IF(ISNUMBER(SEARCH("Seguridad",S48)),Matriz!$C$20,0) -> 100 | N48: =K48+MIN(M48,Matriz!$C$24) -> 550 | P48: Platina se cae, al perder presion con riesgo a danar al colaborador y pueda povocar un accidente | Q48: implementacion de shot pin, mejora en la logica del PLC y ayuda visual. | R48: Felipe Angel Guerrero Herrera | S48: Seguridad;Ergonomía;Eficiencia;Scrap;Tiempo Muerto | T48: Kaizen_Mtto_JUL_2026 Seguridad_Felipe Angel Guerrer.xlsx | U48: 3060762
A49: 45 | B49: 2026-08-17 | C49: 2026-08 | D49: Adrian Rodriguez Campos | E49: Planta 6/7 | F49: EHS | G49: Seguridad | H49: 3 | I49: 2 | K49: =INDEX(Matriz!$C$7:$E$9,H49,I49) -> 300 | L49: =IF(J49="",0,IF(J49<Matriz!$B$14,Matriz!$C$13,IF(J49<Matriz!$B$15,Matriz!$C$14,IF(J49<Matriz!$B$16,Matriz!$C$15,Matriz!$C$16)))) -> 0 | M49: =IF(ISNUMBER(SEARCH("Seguridad",S49)),Matriz!$C$20,0) -> 100 | N49: =K49+MIN(M49,Matriz!$C$24) -> 400 | P49: DESCONOCIMIENTO DE PUNTOS CIEGOS DE OPERADORES DE EQUIPO MOVIL | Q49: CAPACITACIÓN Y AYUDAS VISUALES | R49: Adrian Rodrigues Campos | S49: Seguridad;Ahorro $ | T49: FM-MOP-0023-DR Formato de Kaizen - Equipos mó_Adrian Rodrigues Cam.xlsx | U49: 3061108
A50: 46 | B50: 2026-07-29 | C50: 2026-07 | D50: Berenice Esquivel | E50: Planta 6/7 | F50: Producción | G50: Calidad | H50: 3 | I50: 2 | K50: =INDEX(Matriz!$C$7:$E$9,H50,I50) -> 300 | L50: =IF(J50="",0,IF(J50<Matriz!$B$14,Matriz!$C$13,IF(J50<Matriz!$B$15,Matriz!$C$14,IF(J50<Matriz!$B$16,Matriz!$C$15,Matriz!$C$16)))) -> 0 | M50: =IF(ISNUMBER(SEARCH("Seguridad",S50)),Matriz!$C$20,0) -> 0 | N50: =K50+MIN(M50,Matriz!$C$24) -> 300 | O50: Parece contención/recuperación, no mejora permanente | P50: Recuperacion de componentes por daño de maquina | Q50: Se realiza el desensamble de la pieza para recuperar componentes | R50: Berenice Esquivel Delgadillo | S50: Scrap | T50: FM-MOP-0023-DR Formato de Kaizen -R3_Berenice Esquivel De.xlsx | U50: 3027573
A51: 47 | B51: 2026-07-27 | C51: 2026-07 | D51: Ricardo Mendoza Hernandez | E51: Planta 2 | F51: Materiales | G51: Ahorro | H51: 3 | I51: 3 | J51: 18173 | K51: =INDEX(Matriz!$C$7:$E$9,H51,I51) -> 450 | L51: =IF(J51="",0,IF(J51<Matriz!$B$14,Matriz!$C$13,IF(J51<Matriz!$B$15,Matriz!$C$14,IF(J51<Matriz!$B$16,Matriz!$C$15,Matriz!$C$16)))) -> 500 | M51: =IF(ISNUMBER(SEARCH("Seguridad",S51)),Matriz!$C$20,0) -> 0 | N51: =K51+MIN(M51,Matriz!$C$24) -> 450 | O51: Convertido de 1,069.00 USD a MXN @ 17 (su formato declara USD). | P51: Ahorro de costo, cambio de proveedor externo a manufacturado en planta 7 | Q51: Ahorro anual de $1,069 USD | R51: Ricardo Mendoza Hernandez | S51: Ahorro $ | T51: FM-MOP-0023-DR Formato de Kaizen -R3 Cambio d_Ricardo Mendoza Hern.xlsx | U51: 3035680
A52: 48 | B52: 2026-07-29 | C52: 2026-07 | D52: Cristian Medrano | E52: Planta 3/4 | F52: Calidad | G52: Calidad | H52: 3 | I52: 1 | K52: =INDEX(Matriz!$C$7:$E$9,H52,I52) -> 150 | L52: =IF(J52="",0,IF(J52<Matriz!$B$14,Matriz!$C$13,IF(J52<Matriz!$B$15,Matriz!$C$14,IF(J52<Matriz!$B$16,Matriz!$C$15,Matriz!$C$16)))) -> 0 | M52: =IF(ISNUMBER(SEARCH("Seguridad",S52)),Matriz!$C$20,0) -> 0 | N52: =K52+MIN(M52,Matriz!$C$24) -> 150 | P52: Deteccion de posicion de bracket en rear header, se hacer por medio de uso de vernier, el proceso es tardado y podemos tener variacion | Q52: Incluir un gague con las tolerancias de Minimo, Nominal y Maximo, medidas seteadas y hacer mas rapido el proceso de inspeccion | R52: Laura Elena Velasco Villanueva | S52: FTQ | U52: 3044483
A53: 49 | B53: 2026-07-20 | C53: 2026-07 | D53: Erik Ovalle | E53: Planta 3/4 | F53: Manufactura | G53: Seguridad | H53: 2 | I53: 1 | K53: =INDEX(Matriz!$C$7:$E$9,H53,I53) -> 100 | L53: =IF(J53="",0,IF(J53<Matriz!$B$14,Matriz!$C$13,IF(J53<Matriz!$B$15,Matriz!$C$14,IF(J53<Matriz!$B$16,Matriz!$C$15,Matriz!$C$16)))) -> 0 | M53: =IF(ISNUMBER(SEARCH("Seguridad",S53)),Matriz!$C$20,0) -> 0 | N53: =K53+MIN(M53,Matriz!$C$24) -> 100 | P53: El Igloo no tenia donde podria colocarse | Q53: Se realiza una estructura movil para colocarlo y trasladarlo | R53: Guillermo Garcia | S53: Ergonomía;5S's | T53: Kaizen MFG P4_Guillermo Garcia.xlsx | U53: 1705611
A54: 50 | B54: 2026-07-31 | C54: 2026-07 | D54: Citlalli Ozuna | E54: Planta 3/4 | F54: Lanzamientos | G54: Productividad | H54: 2 | I54: 1 | K54: =INDEX(Matriz!$C$7:$E$9,H54,I54) -> 100 | L54: =IF(J54="",0,IF(J54<Matriz!$B$14,Matriz!$C$13,IF(J54<Matriz!$B$15,Matriz!$C$14,IF(J54<Matriz!$B$16,Matriz!$C$15,Matriz!$C$16)))) -> 0 | M54: =IF(ISNUMBER(SEARCH("Seguridad",S54)),Matriz!$C$20,0) -> 0 | N54: =K54+MIN(M54,Matriz!$C$24) -> 100 | P54: Cortes de vinil mal | Q54: Colocacion de pedestal para evitar movimiento de tela | R54: Citlalli Ozuna | S54: Eficiencia | U54: 3039635
A55: 51 | B55: 2026-07-13 | C55: 2026-07 | D55: Luis Reyes | E55: Parras | F55: Calidad | G55: Productividad | H55: 3 | I55: 2 | K55: =INDEX(Matriz!$C$7:$E$9,H55,I55) -> 300 | L55: =IF(J55="",0,IF(J55<Matriz!$B$14,Matriz!$C$13,IF(J55<Matriz!$B$15,Matriz!$C$14,IF(J55<Matriz!$B$16,Matriz!$C$15,Matriz!$C$16)))) -> 0 | M55: =IF(ISNUMBER(SEARCH("Seguridad",S55)),Matriz!$C$20,0) -> 0 | N55: =K55+MIN(M55,Matriz!$C$24) -> 300 | O55: Redactado como 'Evaluar el cambio' — ¿ya se implementó? | P55: material de 1mm se identifica OM para la alineacion durante el cerrado y la costura de alrededor | Q55: Evaluar el cambio de material laminado de 1mm a 5mm | R55: Fernanda Monserrath Vielma Zavala | S55: Tiempo Muerto;Ahorro $ | T55: Kaizen_Prueba_Material_5mm_T1XX-Luis Reyes_Fernanda Monserrath.xlsx | U55: 3066350
A56: 52 | B56: 2026-07-13 | C56: 2026-07 | D56: Moises Adame | E56: Planta 3/4 | F56: Mantenimiento | G56: Productividad | H56: 2 | I56: 2 | K56: =INDEX(Matriz!$C$7:$E$9,H56,I56) -> 200 | L56: =IF(J56="",0,IF(J56<Matriz!$B$14,Matriz!$C$13,IF(J56<Matriz!$B$15,Matriz!$C$14,IF(J56<Matriz!$B$16,Matriz!$C$15,Matriz!$C$16)))) -> 0 | M56: =IF(ISNUMBER(SEARCH("Seguridad",S56)),Matriz!$C$20,0) -> 0 | N56: =K56+MIN(M56,Matriz!$C$24) -> 200 | O56: Redactado como 'Se propone' — ¿ya se implementó? | P56: Actualmente cada prensa tiene un tiempo ciclo de 157.1 segundos por disparo generando la inyeccion de 8 piezas en cada disparo. | Q56: Se propone disminuir la distacia de cierre de platinas de 700 mm a 600 mm, para disminuir el tiempo de ciclo. | R56: Teresita Gallegos | S56: Eficiencia | T56: FM-MOP-0023-DR Formato de Kaizen -R3 (1)_Teresita Gallegos.xlsx | U56: 3051229
A57: 53 | B57: 2026-07-15 | C57: 2026-07 | D57: Marco Rodríguez | E57: Planta 3/4 | F57: Mantenimiento | G57: Ahorro | H57: 3 | I57: 2 | K57: =INDEX(Matriz!$C$7:$E$9,H57,I57) -> 300 | L57: =IF(J57="",0,IF(J57<Matriz!$B$14,Matriz!$C$13,IF(J57<Matriz!$B$15,Matriz!$C$14,IF(J57<Matriz!$B$16,Matriz!$C$15,Matriz!$C$16)))) -> 0 | M57: =IF(ISNUMBER(SEARCH("Seguridad",S57)),Matriz!$C$20,0) -> 0 | N57: =K57+MIN(M57,Matriz!$C$24) -> 300 | P57: No se cuentan con mesas de trabajo | Q57: Se realizan mesas de trabajo con racks que ya no serán utilizados | R57: Karla Guadalupe Padilla Gonzalez | S57: Ahorro $ | U57: 3030351
A58: 54 | B58: 2026-05-01 | C58: 2026-05 | D58: Citlali Nalleli Garza Hernandez | E58: Planta 1 | F58: Producción | G58: Productividad | H58: 3 | I58: 2 | K58: =INDEX(Matriz!$C$7:$E$9,H58,I58) -> 300 | L58: =IF(J58="",0,IF(J58<Matriz!$B$14,Matriz!$C$13,IF(J58<Matriz!$B$15,Matriz!$C$14,IF(J58<Matriz!$B$16,Matriz!$C$15,Matriz!$C$16)))) -> 0 | M58: =IF(ISNUMBER(SEARCH("Seguridad",S58)),Matriz!$C$20,0) -> 0 | N58: =K58+MIN(M58,Matriz!$C$24) -> 300 | P58: Cambio de herramienta (brochas) de trabajo por rápido desgaste y generar más desperdicio de ECL | Q58: Se remplaza la herramienta actual | R58: Ensamble Produccion | S58: Eficiencia;Ahorro $ | T58: KAIZEN JULIO ENSAMBLE 2026_Ensamble Produccion.xlsx | U58: 3042836
A59: 55 | B59: 2026-07-07 | C59: 2026-07 | D59: Alejandra Armendariz | E59: Planta 3/4 | F59: Manufactura | G59: Calidad | H59: 3 | I59: 1 | K59: =INDEX(Matriz!$C$7:$E$9,H59,I59) -> 150 | L59: =IF(J59="",0,IF(J59<Matriz!$B$14,Matriz!$C$13,IF(J59<Matriz!$B$15,Matriz!$C$14,IF(J59<Matriz!$B$16,Matriz!$C$15,Matriz!$C$16)))) -> 0 | M59: =IF(ISNUMBER(SEARCH("Seguridad",S59)),Matriz!$C$20,0) -> 0 | N59: =K59+MIN(M59,Matriz!$C$24) -> 150 | P59: Daño de piezas al momento de el forrado, por acomulacion de piezas | Q59: Implementacion de estante para colocacion de piezas | R59: Nestor Garcia Castro Garcia Castro | S59: Scrap;Ahorro $ | T59: Kaizen Rivian Door julio_Nestor Garcia Castr.xlsx | U59: 105079
A60: 56 | B60: 2026-07-01 | C60: 2026-07 | D60: Alejandra Natali Puente Vielma | E60: Parras | F60: Recursos Humanos | G60: Ahorro | H60: 3 | I60: 3 | K60: =INDEX(Matriz!$C$7:$E$9,H60,I60) -> 450 | L60: =IF(J60="",0,IF(J60<Matriz!$B$14,Matriz!$C$13,IF(J60<Matriz!$B$15,Matriz!$C$14,IF(J60<Matriz!$B$16,Matriz!$C$15,Matriz!$C$16)))) -> 0 | M60: =IF(ISNUMBER(SEARCH("Seguridad",S60)),Matriz!$C$20,0) -> 0 | N60: =K60+MIN(M60,Matriz!$C$24) -> 450 | P60: Costo de servicio de hospedaje | Q60: Reducción del costo por noche de hospedaje | R60: Alejandra Natali Puente Vielma | S60: Ahorro $ | T60: FM-MOP-0023-DR Formato de Kaizen -R3 Natali P_Alejandra Natali Pue.xlsx | U60: 3026412
A61: 57 | B61: 2026-07-06 | C61: 2026-07 | D61: Federico Alberto Obispo Florencio | E61: Planta 2 | F61: Calidad | G61: Calidad | H61: 3 | I61: 2 | K61: =INDEX(Matriz!$C$7:$E$9,H61,I61) -> 300 | L61: =IF(J61="",0,IF(J61<Matriz!$B$14,Matriz!$C$13,IF(J61<Matriz!$B$15,Matriz!$C$14,IF(J61<Matriz!$B$16,Matriz!$C$15,Matriz!$C$16)))) -> 0 | M61: =IF(ISNUMBER(SEARCH("Seguridad",S61)),Matriz!$C$20,0) -> 0 | N61: =K61+MIN(M61,Matriz!$C$24) -> 300 | P61: Falta de trazabilidad en el subensamble del modulo | Q61: Colocacion de etiqueta para trazabilidad de las piezas | R61: Jose Emmanuel Alejo Wong | S61: FTQ;Scrap | T61: FM-MOP-0023-DR Formato de Kaizen -R2 Calidad-_Jose Emmanuel Alejo 1.xlsx | U61: 3039850
A62: 58 | B62: 2026-07-31 | C62: 2026-07 | D62: Jaziel Mancilla | E62: Planta 2 | F62: Producción | G62: Calidad | H62: 3 | I62: 2 | K62: =INDEX(Matriz!$C$7:$E$9,H62,I62) -> 300 | L62: =IF(J62="",0,IF(J62<Matriz!$B$14,Matriz!$C$13,IF(J62<Matriz!$B$15,Matriz!$C$14,IF(J62<Matriz!$B$16,Matriz!$C$15,Matriz!$C$16)))) -> 0 | M62: =IF(ISNUMBER(SEARCH("Seguridad",S62)),Matriz!$C$20,0) -> 0 | N62: =K62+MIN(M62,Matriz!$C$24) -> 300 | P62: Componentes dañados en empaque | Q62: Se mejora el estandar pack de 50 piezas a 40 piezas para evitar peso excesivo que dañe los componentes | R62: Hector Jaziel Martinez | S62: Scrap;FTQ;5S's | T62: Copy of Kaizen_Produccion_Julio_2026_Hector Jaziel Martin.xlsx | U62: 3026189
A63: 59 | B63: 2026-06-28 | C63: 2026-06 | D63: Jaziel Mancilla | E63: Planta 2 | F63: Producción | G63: Calidad | H63: 3 | I63: 2 | K63: =INDEX(Matriz!$C$7:$E$9,H63,I63) -> 300 | L63: =IF(J63="",0,IF(J63<Matriz!$B$14,Matriz!$C$13,IF(J63<Matriz!$B$15,Matriz!$C$14,IF(J63<Matriz!$B$16,Matriz!$C$15,Matriz!$C$16)))) -> 0 | M63: =IF(ISNUMBER(SEARCH("Seguridad",S63)),Matriz!$C$20,0) -> 0 | N63: =K63+MIN(M63,Matriz!$C$24) -> 300 | P63: Generar parciales con la cantidad y mezcla en los cambios de Numeros de Parte | Q63: Pizarron de cambios y prioridades desde la primera operacion | R63: Hector Jaziel Martinez | S63: Scrap;5S's | T63: Copy of Kaizen_Produccion_Junio_2026_Hector Jaziel Martin.xlsx | U63: 3026189
A64: 60 | B64: 2026-07-20 | C64: 2026-07 | D64: Hector Juan Rodriguez | E64: Planta 6/7 | F64: Calidad | G64: Productividad | H64: 2 | I64: 2 | K64: =INDEX(Matriz!$C$7:$E$9,H64,I64) -> 200 | L64: =IF(J64="",0,IF(J64<Matriz!$B$14,Matriz!$C$13,IF(J64<Matriz!$B$15,Matriz!$C$14,IF(J64<Matriz!$B$16,Matriz!$C$15,Matriz!$C$16)))) -> 0 | M64: =IF(ISNUMBER(SEARCH("Seguridad",S64)),Matriz!$C$20,0) -> 0 | N64: =K64+MIN(M64,Matriz!$C$24) -> 200 | P64: Falta de identificacion para producto inspeccionado y no inspeccionado en el area de inspeccion final DQMC | Q64: FORRADO DE MESAS EN INSPECCION FINAL DQMC PLANTA 7 | R64: Fernanda Monserrath Vielma Zavala | S64: Eficiencia | T64: Kaizen Mesa de inspección DQMC -Hector Rodrig_Fernanda Monserrath.xlsx | U64: 3062084
A65: 61 | B65: 2026-08-13 | C65: 2026-08 | D65: Omar Alvarez | E65: Planta 3/4 | F65: EHS | G65: Seguridad | H65: 3 | I65: 2 | K65: =INDEX(Matriz!$C$7:$E$9,H65,I65) -> 300 | L65: =IF(J65="",0,IF(J65<Matriz!$B$14,Matriz!$C$13,IF(J65<Matriz!$B$15,Matriz!$C$14,IF(J65<Matriz!$B$16,Matriz!$C$15,Matriz!$C$16)))) -> 0 | M65: =IF(ISNUMBER(SEARCH("Seguridad",S65)),Matriz!$C$20,0) -> 100 | N65: =K65+MIN(M65,Matriz!$C$24) -> 400 | P65: Tableros informativos están con colocados de tal manera que el personal debe de llenarlos en paso de equipo móvil | Q65: Reubicación de los tableros | R65: Omar Alejandro Alvarez Charles | S65: Seguridad | U65: 3067714
A66: 62 | B66: 2026-07-06 | C66: 2026-07 | D66: Gustavo Vargas | E66: Planta 6/7 | F66: Materiales | G66: Productividad | H66: 2 | I66: 3 | K66: =INDEX(Matriz!$C$7:$E$9,H66,I66) -> 300 | L66: =IF(J66="",0,IF(J66<Matriz!$B$14,Matriz!$C$13,IF(J66<Matriz!$B$15,Matriz!$C$14,IF(J66<Matriz!$B$16,Matriz!$C$15,Matriz!$C$16)))) -> 0 | M66: =IF(ISNUMBER(SEARCH("Seguridad",S66)),Matriz!$C$20,0) -> 0 | N66: =K66+MIN(M66,Matriz!$C$24) -> 300 | P66: Cliente no envia transmite su release considerando cubicaje y acomodo de cajas | Q66: Se genera archivo de cubicaje para considerar cubicaje del req de cliente y disputar cajas adicionales en caso de ser necesario y mejorar tiempos en acomodos de material | R66: Gustavo Vargas Quiroz | S66: Eficiencia | T66: KAIZEN MATERIALES JULIO_Gustavo Vargas Quiro.xlsx | U66: 3061983
A67: 63 | B67: 2026-08-29 | C67: 2026-08 | D67: Miguel Villegas | E67: Planta 1 | F67: Lanzamientos | G67: Calidad | H67: 3 | I67: 2 | K67: =INDEX(Matriz!$C$7:$E$9,H67,I67) -> 300 | L67: =IF(J67="",0,IF(J67<Matriz!$B$14,Matriz!$C$13,IF(J67<Matriz!$B$15,Matriz!$C$14,IF(J67<Matriz!$B$16,Matriz!$C$15,Matriz!$C$16)))) -> 0 | M67: =IF(ISNUMBER(SEARCH("Seguridad",S67)),Matriz!$C$20,0) -> 0 | N67: =K67+MIN(M67,Matriz!$C$24) -> 300 | P67: Se estaba teniendo mucho desperdicio en el hilo por falta de un uso exacto del hilo | Q67: Se opto agregar cintas métricas a las metas de costura para tener una medida exacta en el hilo para eviar variaacion | R67: Miguel Eduardo Villegas Prieto | S67: Scrap | T67: FM-MOP-0023-DR Formato de Kaizen -R3_Miguel Eduardo Ville.xlsx | U67: 3055580
A68: 64 | B68: 2026-07-27 | C68: 2026-07 | D68: Juan Carlos Guerrero Lozano | E68: Planta 2 | F68: Manufactura | G68: Productividad | H68: 2 | I68: 2 | K68: =INDEX(Matriz!$C$7:$E$9,H68,I68) -> 200 | L68: =IF(J68="",0,IF(J68<Matriz!$B$14,Matriz!$C$13,IF(J68<Matriz!$B$15,Matriz!$C$14,IF(J68<Matriz!$B$16,Matriz!$C$15,Matriz!$C$16)))) -> 0 | M68: =IF(ISNUMBER(SEARCH("Seguridad",S68)),Matriz!$C$20,0) -> 0 | N68: =K68+MIN(M68,Matriz!$C$24) -> 200 | P68: Lineas de produccion deficientes | Q68: Creacion de aereos e identificaciones para las lineas y estaciones (Facilitar el encontrar un area) | R68: Carlos Lozano | S68: Eficiencia;5S's | T68: Kaizen_MFG_AGOSTO_2026 -_Carlos Lozano.xlsx | U68: 3038990
A69: 65 | B69: 2026-08-18 | C69: 2026-08 | D69: Saúl Antonio Gallegos Sánchez | E69: Planta 2 | F69: EHS | G69: Seguridad | H69: 3 | I69: 3 | K69: =INDEX(Matriz!$C$7:$E$9,H69,I69) -> 450 | L69: =IF(J69="",0,IF(J69<Matriz!$B$14,Matriz!$C$13,IF(J69<Matriz!$B$15,Matriz!$C$14,IF(J69<Matriz!$B$16,Matriz!$C$15,Matriz!$C$16)))) -> 0 | M69: =IF(ISNUMBER(SEARCH("Seguridad",S69)),Matriz!$C$20,0) -> 100 | N69: =K69+MIN(M69,Matriz!$C$24) -> 550 | P69: No se contaba con dispositivos y candados LOT suficientes para los mantenimientos. | Q69: Se coloca estación de dispositivos al disponibles para el personal de mantenimiento. | R69: Saul Antonio Gallegos Sanchez | S69: Seguridad | T69: FM-MOP-0023-DR Formato de Kaizen -R3 Agosto E_Saul Antonio Gallego.xlsx | U69: 3030328
A70: 66 | B70: 2026-08-21 | C70: 2026-08 | D70: Anayeli Rivera Callejas | E70: Planta 2 | F70: Calidad | G70: Calidad | H70: 3 | I70: 3 | K70: =INDEX(Matriz!$C$7:$E$9,H70,I70) -> 450 | L70: =IF(J70="",0,IF(J70<Matriz!$B$14,Matriz!$C$13,IF(J70<Matriz!$B$15,Matriz!$C$14,IF(J70<Matriz!$B$16,Matriz!$C$15,Matriz!$C$16)))) -> 0 | M70: =IF(ISNUMBER(SEARCH("Seguridad",S70)),Matriz!$C$20,0) -> 0 | N70: =K70+MIN(M70,Matriz!$C$24) -> 450 | P70: Se manejan tonalidades parecidas en las piezas producidas y hay que validar que sea el color correcto | Q70: Un llavero portátil para la comparación de las tonalidades que nos ayude a diferenciar rápida y claramente las tonalidades | R70: Anayeli Rivera | S70: Scrap;Tiempo Muerto;Eficiencia | T70: FM-MOP-0023-DR Formato de Kaizen -R3 prov_Anayeli Rivera.xlsx | U70: 3031203
A71: 67 | B71: 2026-08-18 | C71: 2026-08 | D71: José Carlos Herrera Dávila | E71: Planta 2 | F71: Calidad | G71: Productividad | H71: 2 | I71: 3 | K71: =INDEX(Matriz!$C$7:$E$9,H71,I71) -> 300 | L71: =IF(J71="",0,IF(J71<Matriz!$B$14,Matriz!$C$13,IF(J71<Matriz!$B$15,Matriz!$C$14,IF(J71<Matriz!$B$16,Matriz!$C$15,Matriz!$C$16)))) -> 0 | M71: =IF(ISNUMBER(SEARCH("Seguridad",S71)),Matriz!$C$20,0) -> 0 | N71: =K71+MIN(M71,Matriz!$C$24) -> 300 | P71: La información de calidad de las líneas Ford & Stellantis se encuentra dispersa, dificultando su consulta y seguimiento oportuno, principalmente en documentación, alertas de calidad y desempeño del FTQ. | Q71: Implementación de un dashboard digital con información real y actualizada para centralizar y facilitar el seguimiento de documentación, alertas de calidad y FTQ de las líneas Ford & Stellantis. | R71: Jose Carlos Herrera Davila | S71: Eficiencia;Tiempo Muerto | U71: 3067718
A72: 68 | B72: 2026-08-24 | C72: 2026-08 | D72: Francisco Hernandez Ramirez | E72: Planta 2 | F72: Lanzamientos | G72: Calidad | H72: 3 | I72: 2 | K72: =INDEX(Matriz!$C$7:$E$9,H72,I72) -> 300 | L72: =IF(J72="",0,IF(J72<Matriz!$B$14,Matriz!$C$13,IF(J72<Matriz!$B$15,Matriz!$C$14,IF(J72<Matriz!$B$16,Matriz!$C$15,Matriz!$C$16)))) -> 0 | M72: =IF(ISNUMBER(SEARCH("Seguridad",S72)),Matriz!$C$20,0) -> 0 | N72: =K72+MIN(M72,Matriz!$C$24) -> 300 | P72: Queja de cliente por ruido en visera | Q72: Se fabrica tapa de acrilico para evitar que entren objetos dentro de la visera | R72: Francisco Hernandez | S72: Scrap;Eficiencia | T72: Kaizen_LAUNCH_AGOSTO_2026_Francisco Hernandez.xlsx | U72: 3055346
A73: 69 | B73: 2026-08-17 | C73: 2026-08 | D73: Eduardo Gonzalez | E73: Planta 1 | F73: Recursos Humanos | G73: Productividad | H73: 2 | I73: 3 | K73: =INDEX(Matriz!$C$7:$E$9,H73,I73) -> 300 | L73: =IF(J73="",0,IF(J73<Matriz!$B$14,Matriz!$C$13,IF(J73<Matriz!$B$15,Matriz!$C$14,IF(J73<Matriz!$B$16,Matriz!$C$15,Matriz!$C$16)))) -> 0 | M73: =IF(ISNUMBER(SEARCH("Seguridad",S73)),Matriz!$C$20,0) -> 0 | N73: =K73+MIN(M73,Matriz!$C$24) -> 300 | P73: No se tiene un control de las incidencias de transporte y buen seguimiento | Q73: se diseña codigo QR para reportar fallas en el servicio de transporte y dar segumiento | R73: Diana Themis Zacanelles Orta | S73: Eficiencia;Tiempo Muerto | T73: Formato de Kaizen RH Agosto_Diana Themis Zacanel.xlsx | U73: 3029246
A74: 70 | B74: 2026-08-07 | C74: 2026-08 | D74: Diego Valencia | E74: Planta 1 | F74: Calidad | G74: Productividad | H74: 2 | I74: 1 | K74: =INDEX(Matriz!$C$7:$E$9,H74,I74) -> 100 | L74: =IF(J74="",0,IF(J74<Matriz!$B$14,Matriz!$C$13,IF(J74<Matriz!$B$15,Matriz!$C$14,IF(J74<Matriz!$B$16,Matriz!$C$15,Matriz!$C$16)))) -> 0 | M74: =IF(ISNUMBER(SEARCH("Seguridad",S74)),Matriz!$C$20,0) -> 0 | N74: =K74+MIN(M74,Matriz!$C$24) -> 100 | P74: Alto nivel de rechazo por falta de clips en piezas | Q74: Se optimiza nido de ensamble de clips, se colocan sensores de detección y pisador con marcaje de pieza | R74: Diego Valencia Alcazar | S74: Tiempo Muerto | T74: Kaizen Moldeo Agosto 2026_Diego Valencia Alcaz.xlsx | U74: 3062213
A75: 71 | B75: 2026-07-27 | C75: 2026-07 | D75: Ulises Hernandez | E75: Planta 1 | F75: Operaciones | G75: Productividad | H75: 2 | I75: 1 | K75: =INDEX(Matriz!$C$7:$E$9,H75,I75) -> 100 | L75: =IF(J75="",0,IF(J75<Matriz!$B$14,Matriz!$C$13,IF(J75<Matriz!$B$15,Matriz!$C$14,IF(J75<Matriz!$B$16,Matriz!$C$15,Matriz!$C$16)))) -> 0 | M75: =IF(ISNUMBER(SEARCH("Seguridad",S75)),Matriz!$C$20,0) -> 0 | N75: =K75+MIN(M75,Matriz!$C$24) -> 100 | P75: Baja eficiencia en maquina IMM-102 y past due con cliente. T1XX Front Housing. | Q75: Disminuir tiempo de ciclo de maquina para incrementar eficiencia mediante ajustes de parametros del proceso | R75: Ulises Eduardo Hernandez Perez | S75: Eficiencia | T75: Kaizen Julio_Ulises Eduardo Herna.xlsx | U75: 3055561
A76: 72 | B76: 2026-08-09 | C76: 2026-08 | D76: Erik Javier Aguirre Ramirez | E76: Planta 3/4 | F76: Recursos Humanos | G76: Productividad | H76: 3 | I76: 3 | K76: =INDEX(Matriz!$C$7:$E$9,H76,I76) -> 450 | L76: =IF(J76="",0,IF(J76<Matriz!$B$14,Matriz!$C$13,IF(J76<Matriz!$B$15,Matriz!$C$14,IF(J76<Matriz!$B$16,Matriz!$C$15,Matriz!$C$16)))) -> 0 | M76: =IF(ISNUMBER(SEARCH("Seguridad",S76)),Matriz!$C$20,0) -> 0 | N76: =K76+MIN(M76,Matriz!$C$24) -> 450 | P76: no se publica prenomina en areas por lo que se genera impacto en las incidencias de nomina | Q76: se crea pagina para la carga de informacion de la prenomina y que el personal la pueda revisar desde su telefono | R76: Erik Aguirre Ramirez | S76: Tiempo Muerto;5S's;Ahorro $;Eficiencia;Medio Ambiente | T76: Kaizen_Prenomina_Digital_Daimay_Erik Aguirre Ramirez.xlsx | U76: 3067002
A77: 73 | B77: 2026-08-11 | C77: 2026-08 | D77: Jose Isai Tostado Beltran | E77: Planta 1 | F77: Mantenimiento | G77: Calidad | H77: 3 | I77: 1 | K77: =INDEX(Matriz!$C$7:$E$9,H77,I77) -> 150 | L77: =IF(J77="",0,IF(J77<Matriz!$B$14,Matriz!$C$13,IF(J77<Matriz!$B$15,Matriz!$C$14,IF(J77<Matriz!$B$16,Matriz!$C$15,Matriz!$C$16)))) -> 0 | M77: =IF(ISNUMBER(SEARCH("Seguridad",S77)),Matriz!$C$20,0) -> 0 | N77: =K77+MIN(M77,Matriz!$C$24) -> 150 | P77: maquina no cuenta con herramental de robot las piezas caen a una caja esto ocaciona que se golpe generando scrap y t.m. | Q77: se fabrica herramental se busca refaccionamiento y se realiza programa y valida en maquina | R77: Mariana Valencia | S77: Scrap | T77: kaizen Agosto 2026_Mariana Valencia.xlsx | U77: 3024217
A78: 74 | B78: 2026-08-26 | C78: 2026-08 | D78: Alejandro Caseres | E78: Planta 6/7 | F78: Operaciones | G78: Calidad | H78: 3 | I78: 2 | K78: =INDEX(Matriz!$C$7:$E$9,H78,I78) -> 300 | L78: =IF(J78="",0,IF(J78<Matriz!$B$14,Matriz!$C$13,IF(J78<Matriz!$B$15,Matriz!$C$14,IF(J78<Matriz!$B$16,Matriz!$C$15,Matriz!$C$16)))) -> 0 | M78: =IF(ISNUMBER(SEARCH("Seguridad",S78)),Matriz!$C$20,0) -> 0 | N78: =K78+MIN(M78,Matriz!$C$24) -> 300 | P78: reduccion de marcas en cover F3003360 | Q78: Proceso de pre-vaporeo antes de llegar a la estación de ensamble de cover | R78: Eduardo Morales Rodriguez | S78: Scrap;Eficiencia | T78: FM-MOP-0023-DR Formato de Kaizen -R3_Eduardo Morales Rodr.xlsx | U78: 3031856
A79: 75 | B79: 2026-08-26 | C79: 2026-08 | D79: Jose Tolentino | E79: Planta 6/7 | F79: Operaciones | G79: Productividad | H79: 2 | I79: 2 | K79: =INDEX(Matriz!$C$7:$E$9,H79,I79) -> 200 | L79: =IF(J79="",0,IF(J79<Matriz!$B$14,Matriz!$C$13,IF(J79<Matriz!$B$15,Matriz!$C$14,IF(J79<Matriz!$B$16,Matriz!$C$15,Matriz!$C$16)))) -> 0 | M79: =IF(ISNUMBER(SEARCH("Seguridad",S79)),Matriz!$C$20,0) -> 0 | N79: =K79+MIN(M79,Matriz!$C$24) -> 200 | P79: Se hacia una deformacion en las piezas costruidas | Q79: Con ayuda de una base implementada en las mesas de tapizado se logro evitar la deformacion de las piezas | R79: Berenice Esquivel Delgadillo | S79: Tiempo Muerto;Eficiencia | T79: Kaizen - Operaciones_Berenice Esquivel De.xlsx | U79: 3032490
A80: 76 | B80: 2026-08-05 | C80: 2026-08 | D80: Paola Fernandez | E80: Planta 1 | F80: Materiales | G80: Productividad | H80: 2 | I80: 2 | K80: =INDEX(Matriz!$C$7:$E$9,H80,I80) -> 200 | L80: =IF(J80="",0,IF(J80<Matriz!$B$14,Matriz!$C$13,IF(J80<Matriz!$B$15,Matriz!$C$14,IF(J80<Matriz!$B$16,Matriz!$C$15,Matriz!$C$16)))) -> 0 | M80: =IF(ISNUMBER(SEARCH("Seguridad",S80)),Matriz!$C$20,0) -> 0 | N80: =K80+MIN(M80,Matriz!$C$24) -> 200 | P80: Malos etiquetados moldeo | Q80: Implementacion de formato LH con sombra | R80: Paola Fernandez | S80: Eficiencia | T80: FM-MOP-0023-DR Formato de Kaizen -R3 2_Paola Fernandez.xlsx | U80: 3030819
A81: 77 | B81: 2026-08-10 | C81: 2026-08 | D81: Fernando Rodríguez | E81: Planta 1 | F81: EHS | G81: Medio Ambiente | H81: 1 | I81: 3 | K81: =INDEX(Matriz!$C$7:$E$9,H81,I81) -> 150 | L81: =IF(J81="",0,IF(J81<Matriz!$B$14,Matriz!$C$13,IF(J81<Matriz!$B$15,Matriz!$C$14,IF(J81<Matriz!$B$16,Matriz!$C$15,Matriz!$C$16)))) -> 0 | M81: =IF(ISNUMBER(SEARCH("Seguridad",S81)),Matriz!$C$20,0) -> 0 | N81: =K81+MIN(M81,Matriz!$C$24) -> 150 | O81: Indicador 'Medio Ambiente' pero el beneficio principal es método/eficiencia | P81: La inspección de escaleras en papel causaba pérdida de información, complicaba el seguimiento de hallazgos y generaba altos costos de impresión y almacenamiento | Q81: Se implementó un código QR vinculado a una plataforma digital para registrar las inspecciones de escaleras de forma electrónica y Reduce el consumo de papel e impresión, disminuyendo costos y apoyando el cuidado del medio ambiente. | R81: Fernando Rodriguez Garcia | S81: Medio Ambiente | U81: 3040837
A82: 78 | B82: 2026-06-01 | C82: 2026-06 | D82: Nestor Estrada | E82: Planta 1 | F82: Mantenimiento | G82: Ahorro | H82: 3 | I82: 2 | K82: =INDEX(Matriz!$C$7:$E$9,H82,I82) -> 300 | L82: =IF(J82="",0,IF(J82<Matriz!$B$14,Matriz!$C$13,IF(J82<Matriz!$B$15,Matriz!$C$14,IF(J82<Matriz!$B$16,Matriz!$C$15,Matriz!$C$16)))) -> 0 | M82: =IF(ISNUMBER(SEARCH("Seguridad",S82)),Matriz!$C$20,0) -> 0 | N82: =K82+MIN(M82,Matriz!$C$24) -> 300 | P82: Se dañaba frecuentemente el conector de la prueba de luz por lo cual cada que se dañaba se tenia que mandar comprar uno con proveedores locales el cual el costo era un poco alto. | Q82: Se mando dibujar y fabricar en tooling en el cual se realizo una mejora en el area donde conecta los pines para cuando se nos dañe solamente se cambien las puntas y no todo el conector. | R82: Jose Ignacio Arias Palacios | S82: Ahorro $ | T82: FM-MOP-0023-DR Formato de Kaizen -R1_Jose Ignacio Arias P.xlsx | U82: 3044346
A83: 79 | B83: 2026-08-25 | C83: 2026-08 | D83: Luis Gerardo Rivera Salazar | E83: Planta 1 | F83: Producción | G83: Productividad | H83: 2 | I83: 3 | K83: =INDEX(Matriz!$C$7:$E$9,H83,I83) -> 300 | L83: =IF(J83="",0,IF(J83<Matriz!$B$14,Matriz!$C$13,IF(J83<Matriz!$B$15,Matriz!$C$14,IF(J83<Matriz!$B$16,Matriz!$C$15,Matriz!$C$16)))) -> 0 | M83: =IF(ISNUMBER(SEARCH("Seguridad",S83)),Matriz!$C$20,0) -> 0 | N83: =K83+MIN(M83,Matriz!$C$24) -> 300 | P83: Paros constantes de líneas en planta 8 por falta de control de subensambles de codo, vanity y tela cortada | Q83: Se crea locación de "Elbow Subassembly" para fabricar mediante órdenes de trabajo (Job) y se genera formato para control de seguimiento a programas de subensambles | R83: Ensamble Produccion | S83: Eficiencia;Tiempo Muerto | T83: KAIZEN AGOSTO ENSAMBLE 2026_Ensamble Produccion.xlsx | U83: 1680380
A84: 80 | B84: 2026-08-20 | C84: 2026-08 | D84: Arsenio E Vazquez | E84: Planta 1 | F84: Calidad | G84: Productividad | H84: 3 | I84: 1 | K84: =INDEX(Matriz!$C$7:$E$9,H84,I84) -> 150 | L84: =IF(J84="",0,IF(J84<Matriz!$B$14,Matriz!$C$13,IF(J84<Matriz!$B$15,Matriz!$C$14,IF(J84<Matriz!$B$16,Matriz!$C$15,Matriz!$C$16)))) -> 0 | M84: =IF(ISNUMBER(SEARCH("Seguridad",S84)),Matriz!$C$20,0) -> 0 | N84: =K84+MIN(M84,Matriz!$C$24) -> 150 | P84: Ensamble incorrecto del carrier, colocandose de forma invertida y provocando luz inoperante y que la pieza no haga detent. | Q84: Instalacion de camara para verifcar la correcta posicion del carrier. | R84: Diego Valencia Alcazar | S84: Ahorro $;Eficiencia | T84: KAIZEN CALIDAD ENSAMBLE - PLANTA 1 - AGOSTO 2_Diego Valencia Alcaz.xlsx | U84: 3030820
A85: 81 | B85: 2026-08-27 | C85: 2026-08 | D85: Erik Ovalle | E85: Planta 3/4 | F85: Manufactura | G85: Productividad | H85: 2 | I85: 1 | K85: =INDEX(Matriz!$C$7:$E$9,H85,I85) -> 100 | L85: =IF(J85="",0,IF(J85<Matriz!$B$14,Matriz!$C$13,IF(J85<Matriz!$B$15,Matriz!$C$14,IF(J85<Matriz!$B$16,Matriz!$C$15,Matriz!$C$16)))) -> 0 | M85: =IF(ISNUMBER(SEARCH("Seguridad",S85)),Matriz!$C$20,0) -> 0 | N85: =K85+MIN(M85,Matriz!$C$24) -> 100 | P85: Exceso de cortes de excedentes en mesas de forrado door upper rivian | Q85: se hacen perforaciones a las mesas de forrado para que el operador tiren los ecxesos por los orificios | R85: Erik Ovalle | S85: Tiempo Muerto;5S's | T85: Kaizen manufactura mes agosto_Erik Ovalle.xlsx | U85: 1705611
A86: 82 | B86: 2026-08-10 | C86: 2026-08 | D86: Gerardo del Angel Zarate | E86: Planta 2 | F86: Recursos Humanos | G86: Ahorro | H86: 3 | I86: 3 | K86: =INDEX(Matriz!$C$7:$E$9,H86,I86) -> 450 | L86: =IF(J86="",0,IF(J86<Matriz!$B$14,Matriz!$C$13,IF(J86<Matriz!$B$15,Matriz!$C$14,IF(J86<Matriz!$B$16,Matriz!$C$15,Matriz!$C$16)))) -> 0 | M86: =IF(ISNUMBER(SEARCH("Seguridad",S86)),Matriz!$C$20,0) -> 0 | N86: =K86+MIN(M86,Matriz!$C$24) -> 450 | P86: Se detectó un alto consumo y desperdicio de conos desechables para tomar agua. Los conos eran colocados directamente sobre los dispensadores de agua, lo que provocaba que algunos se cayeran, se utilizaran de manera innecesaria o fueran desechados sin haber sido utilizados. | Q86: Se instalaron porta conos en los dispensadores de agua para establecer un punto de almacenamiento y suministro controlado. Las actividades incluyeron identificar los puntos con mayor desperdicio, definir la cantidad de porta conos necesarios, realizar su instalación, abastecerlos, comunicar su correcto uso y dar seguimiento al consumo de conos para verificar la efectividad de la mejora. | R86: Monica Arcelia Sifuentes Ortiz | S86: Ahorro $;5S's;Medio Ambiente | T86: FM-MOP-0023-DR Formato de Kaizen -R3 AGOSTO_Monica Arcelia Sifue.xlsx | U86: 3026520
A87: 83 | B87: 2026-08-28 | C87: 2026-08 | D87: Citlalli Ozuna | E87: Planta 3/4 | F87: Lanzamientos | G87: 5S | H87: 1 | I87: 2 | K87: =INDEX(Matriz!$C$7:$E$9,H87,I87) -> 100 | L87: =IF(J87="",0,IF(J87<Matriz!$B$14,Matriz!$C$13,IF(J87<Matriz!$B$15,Matriz!$C$14,IF(J87<Matriz!$B$16,Matriz!$C$15,Matriz!$C$16)))) -> 0 | M87: =IF(ISNUMBER(SEARCH("Seguridad",S87)),Matriz!$C$20,0) -> 0 | N87: =K87+MIN(M87,Matriz!$C$24) -> 100 | O87: Alcance dudoso: rack de termos, beneficio de servicio más que de proceso | P87: Rack de termos | Q87: Rack para colocar termos de personal operativo | R87: Citlalli Ozuna | S87: 5S's | T87: Kaizen lanzamientos-Agosto_Citlalli Ozuna.xlsx | U87: 3039635
A88: 84 | B88: 2026-08-28 | C88: 2026-08 | D88: Ricardo Mendoza Hernandez | E88: Planta 2 | F88: Materiales | G88: Ahorro | H88: 3 | I88: 3 | J88: 644569 | K88: =INDEX(Matriz!$C$7:$E$9,H88,I88) -> 450 | L88: =IF(J88="",0,IF(J88<Matriz!$B$14,Matriz!$C$13,IF(J88<Matriz!$B$15,Matriz!$C$14,IF(J88<Matriz!$B$16,Matriz!$C$15,Matriz!$C$16)))) -> 1000 | M88: =IF(ISNUMBER(SEARCH("Seguridad",S88)),Matriz!$C$20,0) -> 0 | N88: =K88+MIN(M88,Matriz!$C$24) -> 450 | O88: Convertido de 37,915.84 USD a MXN @ 17 (su formato declara USD). | P88: Cambio de proveedor externo para foam C300 a manufacturado en planta 7 | Q88: Ahorro anual de $37915.84 USD | R88: Ricardo Mendoza Hernandez | S88: Ahorro $ | T88: FM-MOP-0023-DR Formato de Kaizen -R3 Cambio d_Ricardo Mendoza Hern 1.xlsx | U88: 3035680
A89: 85 | B89: 2026-08-27 | C89: 2026-08 | D89: Daniel Alejandro Parra Mendoza | E89: Parras | F89: EHS | G89: Calidad | H89: 3 | I89: 3 | K89: =INDEX(Matriz!$C$7:$E$9,H89,I89) -> 450 | L89: =IF(J89="",0,IF(J89<Matriz!$B$14,Matriz!$C$13,IF(J89<Matriz!$B$15,Matriz!$C$14,IF(J89<Matriz!$B$16,Matriz!$C$15,Matriz!$C$16)))) -> 0 | M89: =IF(ISNUMBER(SEARCH("Seguridad",S89)),Matriz!$C$20,0) -> 0 | N89: =K89+MIN(M89,Matriz!$C$24) -> 450 | P89: EN PLANTA PARRAS NO SE CUENTA CON RECICLADO DE PLASTICOS POR LO QUE SE IMPLEMENTA PARA LA REDUCCION DE COSTOS | Q89: REDUCCION DE BASURA GENERAL Y REDUCCION DE COSTOS DE DISPOSICION | R89: Daniel Alejandro Parra Mendoza | S89: Ahorro $;Scrap;Medio Ambiente | T89: KAIZEN AGOSTO_Daniel Alejandro Par.xlsx | U89: 3066566
A90: 86 | B90: 2026-08-01 | C90: 2026-08 | D90: Hugo Alcalá | E90: Parras | F90: Calidad | G90: Calidad | H90: 3 | I90: 2 | K90: =INDEX(Matriz!$C$7:$E$9,H90,I90) -> 300 | L90: =IF(J90="",0,IF(J90<Matriz!$B$14,Matriz!$C$13,IF(J90<Matriz!$B$15,Matriz!$C$14,IF(J90<Matriz!$B$16,Matriz!$C$15,Matriz!$C$16)))) -> 0 | M90: =IF(ISNUMBER(SEARCH("Seguridad",S90)),Matriz!$C$20,0) -> 0 | N90: =K90+MIN(M90,Matriz!$C$24) -> 300 | P90: El área de inspección contaba con mesas de trabajo considerablemente desgastadas y con un diseño poco funcional. | Q90: Se diseñaron e instalaron nuevas mesas de inspección ergonómicas y funcionales, incorporando espacios destinados para colocar y mantener visibles las piezas master y primeras piezas. | R90: Brandon Ramon Cano Resendez | S90: Eficiecia;FTQ;5S's;Tiempo Muerto;Scrap | T90: FM-MOP-0023-DR Formato de Kaizen Calidad_Brandon Ramon Cano R.xlsx | U90: 3056806
A91: 87 | B91: 2026-08-17 | C91: 2026-08 | D91: Fernando Gonzalez Delgado | E91: Planta 3/4 | F91: Calidad | G91: Calidad | H91: 3 | I91: 3 | K91: =INDEX(Matriz!$C$7:$E$9,H91,I91) -> 450 | L91: =IF(J91="",0,IF(J91<Matriz!$B$14,Matriz!$C$13,IF(J91<Matriz!$B$15,Matriz!$C$14,IF(J91<Matriz!$B$16,Matriz!$C$15,Matriz!$C$16)))) -> 0 | M91: =IF(ISNUMBER(SEARCH("Seguridad",S91)),Matriz!$C$20,0) -> 0 | N91: =K91+MIN(M91,Matriz!$C$24) -> 450 | P91: La incorrecta identificación de defectos en rollos de foam por parte de proveedor, hacia que la gente de producción del área de corte tuviera muchas fugas de cortes con defectos al área de ensamble Rivian | Q91: Mejora en la identificación de defectos de proveedor para evitar escapes al área de ensamble | R91: Fernando Gonzalez | S91: Scrap | T91: Calidad - P3y4 - Agosto_Fernando Gonzalez.xlsx | U91: 3054279
A92: 88 | B92: 2026-08-19 | C92: 2026-08 | D92: Tania Alejandra Lira Villarreal | E92: Planta 3/4 | F92: Logística | G92: Productividad | H92: 3 | I92: 3 | J92: 288000 | K92: =INDEX(Matriz!$C$7:$E$9,H92,I92) -> 450 | L92: =IF(J92="",0,IF(J92<Matriz!$B$14,Matriz!$C$13,IF(J92<Matriz!$B$15,Matriz!$C$14,IF(J92<Matriz!$B$16,Matriz!$C$15,Matriz!$C$16)))) -> 1000 | M92: =IF(ISNUMBER(SEARCH("Seguridad",S92)),Matriz!$C$20,0) -> 0 | N92: =K92+MIN(M92,Matriz!$C$24) -> 450 | P92: COSTO ALTO EN RUTA DE FLEXTRONICS | Q92: LICITACION PROVEEDORES EXTERNOS | R92: Tania Alejandra Lira Villarreal | S92: Ahorro $;Eficiecia | T92: FM-MOP-0023-DR Formato de Kaizen -R3 1 LOGIST_Tania Alejandra Lira 2.xlsx | U92: 3047688
A93: 89 | B93: 2026-08-28 | C93: 2026-08 | D93: Felipe Angel Guerrero Herrera | E93: Planta 2 | F93: Mantenimiento | G93: Seguridad | H93: 3 | I93: 2 | K93: =INDEX(Matriz!$C$7:$E$9,H93,I93) -> 300 | L93: =IF(J93="",0,IF(J93<Matriz!$B$14,Matriz!$C$13,IF(J93<Matriz!$B$15,Matriz!$C$14,IF(J93<Matriz!$B$16,Matriz!$C$15,Matriz!$C$16)))) -> 0 | M93: =IF(ISNUMBER(SEARCH("Seguridad",S93)),Matriz!$C$20,0) -> 100 | N93: =K93+MIN(M93,Matriz!$C$24) -> 400 | P93: Condición de riesgo y paros de línea por desborde de agua caliente de condensados en área OPAL A | Q93: Automatización del desalojo de condensados mediante tanque pulmón y sistema de bombeo. | R93: Felipe Angel Guerrero Herrera | S93: Ahorro $;Eficiecia;Tiempo Muerto;FTQ;5S's;Medio Ambiente;Seguridad | T93: Kaizen_Mtto_AGO_2026 Mejora_Felipe Angel Guerrer.xlsx | U93: 3060762
A94: 90 | B94: 2026-08-28 | C94: 2026-08 | D94: Felipe Angel Guerrero Herrera | E94: Planta 2 | F94: Mantenimiento | G94: Seguridad | H94: 3 | I94: 1 | K94: =INDEX(Matriz!$C$7:$E$9,H94,I94) -> 150 | L94: =IF(J94="",0,IF(J94<Matriz!$B$14,Matriz!$C$13,IF(J94<Matriz!$B$15,Matriz!$C$14,IF(J94<Matriz!$B$16,Matriz!$C$15,Matriz!$C$16)))) -> 0 | M94: =IF(ISNUMBER(SEARCH("Seguridad",S94)),Matriz!$C$20,0) -> 100 | N94: =K94+MIN(M94,Matriz!$C$24) -> 250 | P94: Instalación de guarda de acrílico de seguridad en prensa doble | Q94: Instalación de guardas fijas de policarbonato/acrílico de alto impacto en el perímetro frontal y lateral de la máquina de doble prensa | R94: Felipe Angel Guerrero Herrera | S94: Eficiecia;Tiempo Muerto;5S's;Medio Ambiente;Seguridad | T94: Kaizen_Mtto_AGO_Seguridad_2026_Felipe Angel Guerrer.xlsx | U94: 3060762
A95: 91 | B95: 2026-08-26 | C95: 2026-08 | D95: Rafael Rodriguez | E95: Planta 3/4 | F95: Mantenimiento | G95: Calidad | H95: 3 | I95: 1 | K95: =INDEX(Matriz!$C$7:$E$9,H95,I95) -> 150 | L95: =IF(J95="",0,IF(J95<Matriz!$B$14,Matriz!$C$13,IF(J95<Matriz!$B$15,Matriz!$C$14,IF(J95<Matriz!$B$16,Matriz!$C$15,Matriz!$C$16)))) -> 0 | M95: =IF(ISNUMBER(SEARCH("Seguridad",S95)),Matriz!$C$20,0) -> 0 | N95: =K95+MIN(M95,Matriz!$C$24) -> 150 | P95: Se encuentra área de oportunidad en la detección de arandela de componente back panel, donde se requiere asegurar que esta se instala correctamente | Q95: Se instalan sensores de presencia para detectar que a la hora de hacer el proceso en maquina de soldadura estén presentes dichas arandelas | R95: Karla Guadalupe Padilla Gonzalez | S95: Scrap | T95: FM-MOP-0023-DR Formato de Kaizen AGOSTO_Karla Guadalupe Padi.xlsx | U95: 3024118
A96: 92 | B96: 2026-08-31 | C96: 2026-08 | D96: Jaziel Mancilla | E96: Planta 2 | F96: Producción | G96: 5S | H96: 1 | I96: 2 | K96: =INDEX(Matriz!$C$7:$E$9,H96,I96) -> 100 | L96: =IF(J96="",0,IF(J96<Matriz!$B$14,Matriz!$C$13,IF(J96<Matriz!$B$15,Matriz!$C$14,IF(J96<Matriz!$B$16,Matriz!$C$15,Matriz!$C$16)))) -> 0 | M96: =IF(ISNUMBER(SEARCH("Seguridad",S96)),Matriz!$C$20,0) -> 0 | N96: =K96+MIN(M96,Matriz!$C$24) -> 100 | P96: Raw Material mezclado en linea de produccion | Q96: Instalacion de Rack para Raw Material | R96: Hector Jaziel Martinez | S96: 5S's | T96: 8. Kaizen_Produccion_Agosto_2026_Hector Jaziel Martin.xlsx | U96: 3026189
A97: 93 | B97: 2026-08-31 | C97: 2026-08 | D97: Jaziel Mancilla | E97: Planta 2 | F97: Producción | G97: Seguridad | H97: 3 | I97: 2 | K97: =INDEX(Matriz!$C$7:$E$9,H97,I97) -> 300 | L97: =IF(J97="",0,IF(J97<Matriz!$B$14,Matriz!$C$13,IF(J97<Matriz!$B$15,Matriz!$C$14,IF(J97<Matriz!$B$16,Matriz!$C$15,Matriz!$C$16)))) -> 0 | M97: =IF(ISNUMBER(SEARCH("Seguridad",S97)),Matriz!$C$20,0) -> 100 | N97: =K97+MIN(M97,Matriz!$C$24) -> 400 | P97: Tomacorriente sin ayuda visual | Q97: Se agrega ayuda visual y se retoralimenta al personal sobre el riesgo electrico | R97: Hector Jaziel Martinez | S97: Seguridad | T97: 8. Kaizen_Produccion_Seguridad_Agosto_2026_Hector Jaziel Martin.xlsx | U97: 3026189
A98: 94 | B98: 2026-09-15 | C98: 2026-09 | D98: Fannie Aguilar | E98: Planta 1 | F98: Lanzamientos | G98: Ahorro | H98: 3 | I98: 3 | J98: 208420 | K98: =INDEX(Matriz!$C$7:$E$9,H98,I98) -> 450 | L98: =IF(J98="",0,IF(J98<Matriz!$B$14,Matriz!$C$13,IF(J98<Matriz!$B$15,Matriz!$C$14,IF(J98<Matriz!$B$16,Matriz!$C$15,Matriz!$C$16)))) -> 1000 | M98: =IF(ISNUMBER(SEARCH("Seguridad",S98)),Matriz!$C$20,0) -> 0 | N98: =K98+MIN(M98,Matriz!$C$24) -> 450 | O98: Convertido de 12,260.00 USD a MXN @ 17 (su formato declara USD). | P98: El arnés del programa Ford CD9 tiene un costo actual de $6.73 USD por pieza con el proveedor EDS, generando una oportunidad de reducción de costo. | Q98: Se desarrolló una fuente alternativa en China, validada para el programa, con un costo de $0.60 USD por pieza, generando un ahorro de $6.13 USD por pieza. | R98: Fannie Grettelle Aguilar Valero | S98: Ahorro $ | T98: FM-MOP-0023-DR Formato de Kaizen -R3 (_Fannie Grettelle Agu.xlsx | U98: 3053215
A99: 95 | B99: 2026-08-15 | C99: 2026-08 | D99: Carlos Mendez | E99: Planta 6/7 | F99: Calidad | G99: Productividad | H99: 2 | I99: 2 | K99: =INDEX(Matriz!$C$7:$E$9,H99,I99) -> 200 | L99: =IF(J99="",0,IF(J99<Matriz!$B$14,Matriz!$C$13,IF(J99<Matriz!$B$15,Matriz!$C$14,IF(J99<Matriz!$B$16,Matriz!$C$15,Matriz!$C$16)))) -> 0 | M99: =IF(ISNUMBER(SEARCH("Seguridad",S99)),Matriz!$C$20,0) -> 0 | N99: =K99+MIN(M99,Matriz!$C$24) -> 200 | P99: En DOCK AUDIT no se tenia un flujo establecido, generando mezclas de material liberado y material por inspeccionar | Q99: Se definieron carriles identificados por color | R99: Fernanda Monserrath Vielma Zavala | S99: Eficiecia;Tiempo Muerto | T99: 08_29_Kaizen_Flujo de Dock Audit_Carlos_Mende_Fernanda Monserrath.xlsx | U99: 3067207
A100: 96 | B100: 2026-08-01 | C100: 2026-08 | D100: Francisco Daniel Charles Sanchez | E100: Planta 2 | F100: Materiales | G100: Productividad | H100: 3 | I100: 3 | K100: =INDEX(Matriz!$C$7:$E$9,H100,I100) -> 450 | L100: =IF(J100="",0,IF(J100<Matriz!$B$14,Matriz!$C$13,IF(J100<Matriz!$B$15,Matriz!$C$14,IF(J100<Matriz!$B$16,Matriz!$C$15,Matriz!$C$16)))) -> 0 | M100: =IF(ISNUMBER(SEARCH("Seguridad",S100)),Matriz!$C$20,0) -> 0 | N100: =K100+MIN(M100,Matriz!$C$24) -> 450 | P100: Alta frecuencia de recolecciones con bajos volúmenes, debido a una falta de consolidación y planeación logística, lo que incrementaba los costos de transporte y genera ineficiencias operativas. | Q100: Consolidar embarques y optimizar la programación de recolecciones para reducir la frecuencia, maximizar los volúmenes por embarque y disminuir los costos de transporte. | R100: Francisco Daniel Charles Sanchez | S100: Ahorro $;Eficiecia | T100: FM-MOP-0023-DR Formato de Kaizen -R3 - Reducc_Francisco Daniel Cha.xlsx | U100: 3062322
A101: 97 | B101: 2026-08-10 | C101: 2026-08 | D101: Arsenio E Vazquez | E101: Planta 1 | F101: Calidad | G101: Ahorro | H101: 3 | I101: 1 | K101: =INDEX(Matriz!$C$7:$E$9,H101,I101) -> 150 | L101: =IF(J101="",0,IF(J101<Matriz!$B$14,Matriz!$C$13,IF(J101<Matriz!$B$15,Matriz!$C$14,IF(J101<Matriz!$B$16,Matriz!$C$15,Matriz!$C$16)))) -> 0 | M101: =IF(ISNUMBER(SEARCH("Seguridad",S101)),Matriz!$C$20,0) -> 0 | N101: =K101+MIN(M101,Matriz!$C$24) -> 150 | P101: Frame BMW - G64 presenta ruido por falta de grasa | Q101: Instalación de un sensor para alertar en caso de falta de grasa; la máquina se detiene automáticamente hasta que se rellena el dispensador. | R101: Salome Dominguez | S101: Ahorro $ | T101: FM-MOP-0023-DR Formato de Kaizen -R3_Salome Dominguez.xlsx | U101: 3030820
...

Sheet Resumen
A1: RESUMEN — abril a septiembre 2026
A2: Todas las cifras son fórmulas sobre la hoja Evaluación. Excluye el ID 1 (prueba).
A4: POR PLANTA
A5: Planta | B5: Kaizen | C5: DaiPuntos | D5: Promedio | E5: Meta anual* | F5: % meta
A6: Planta 1 | B6: =COUNTIFS(Evaluación!$E$5:$E$136,A6,Evaluación!$A$5:$A$136,">1") -> 32 | C6: =SUMIFS(Evaluación!$N$5:$N$136,Evaluación!$E$5:$E$136,A6,Evaluación!$A$5:$A$136,">1") -> 8050 | D6: =IF(B6=0,0,ROUND(C6/B6,0)) -> 252 | E6: 70 | F6: =IF(E6=0,0,B6/E6) -> 0.45714286
A7: Planta 2 | B7: =COUNTIFS(Evaluación!$E$5:$E$136,A7,Evaluación!$A$5:$A$136,">1") -> 38 | C7: =SUMIFS(Evaluación!$N$5:$N$136,Evaluación!$E$5:$E$136,A7,Evaluación!$A$5:$A$136,">1") -> 11650 | D7: =IF(B7=0,0,ROUND(C7/B7,0)) -> 307 | E7: 70 | F7: =IF(E7=0,0,B7/E7) -> 0.54285714
A8: Planta 3/4 | B8: =COUNTIFS(Evaluación!$E$5:$E$136,A8,Evaluación!$A$5:$A$136,">1") -> 27 | C8: =SUMIFS(Evaluación!$N$5:$N$136,Evaluación!$E$5:$E$136,A8,Evaluación!$A$5:$A$136,">1") -> 6800 | D8: =IF(B8=0,0,ROUND(C8/B8,0)) -> 252 | E8: 70 | F8: =IF(E8=0,0,B8/E8) -> 0.38571429
A9: Planta 6/7 | B9: =COUNTIFS(Evaluación!$E$5:$E$136,A9,Evaluación!$A$5:$A$136,">1") -> 19 | C9: =SUMIFS(Evaluación!$N$5:$N$136,Evaluación!$E$5:$E$136,A9,Evaluación!$A$5:$A$136,">1") -> 4400 | D9: =IF(B9=0,0,ROUND(C9/B9,0)) -> 232 | E9: 70 | F9: =IF(E9=0,0,B9/E9) -> 0.27142857
A10: Planta 8 | B10: =COUNTIFS(Evaluación!$E$5:$E$136,A10,Evaluación!$A$5:$A$136,">1") -> 0 | C10: =SUMIFS(Evaluación!$N$5:$N$136,Evaluación!$E$5:$E$136,A10,Evaluación!$A$5:$A$136,">1") -> 0 | D10: =IF(B10=0,0,ROUND(C10/B10,0)) -> 0 | E10: 70 | F10: =IF(E10=0,0,B10/E10) -> 0
A11: Parras | B11: =COUNTIFS(Evaluación!$E$5:$E$136,A11,Evaluación!$A$5:$A$136,">1") -> 10 | C11: =SUMIFS(Evaluación!$N$5:$N$136,Evaluación!$E$5:$E$136,A11,Evaluación!$A$5:$A$136,">1") -> 3400 | D11: =IF(B11=0,0,ROUND(C11/B11,0)) -> 340 | E11: 70 | F11: =IF(E11=0,0,B11/E11) -> 0.14285714
A12: TOTAL | B12: =SUM(B6:B11) -> 126 | C12: =SUM(C6:C11) -> 34300 | D12: =IF(B12=0,0,ROUND(C12/B12,0)) -> 272 | E12: =SUM(E6:E11) -> 420 | F12: =IF(E12=0,0,B12/E12) -> 0.3
A13: * Meta anual por planta = 420 Kaizen/año de la red entre 6 sitios. Ritmo real jun-ago: 29/mes.
A15: POR MES
A16: Mes | B16: Kaizen | C16: DaiPuntos | D16: Promedio | E16: Meta mensual | F16: % meta
A17: 2026-04 | B17: =COUNTIFS(Evaluación!$C$5:$C$136,A17,Evaluación!$A$5:$A$136,">1") -> 2 | C17: =SUMIFS(Evaluación!$N$5:$N$136,Evaluación!$C$5:$C$136,A17,Evaluación!$A$5:$A$136,">1") -> 900 | D17: =IF(B17=0,0,ROUND(C17/B17,0)) -> 450 | E17: 48 | F17: =IF(E17=0,0,B17/E17) -> 0.041666667
A18: 2026-05 | B18: =COUNTIFS(Evaluación!$C$5:$C$136,A18,Evaluación!$A$5:$A$136,">1") -> 7 | C18: =SUMIFS(Evaluación!$N$5:$N$136,Evaluación!$C$5:$C$136,A18,Evaluación!$A$5:$A$136,">1") -> 1550 | D18: =IF(B18=0,0,ROUND(C18/B18,0)) -> 221 | E18: 48 | F18: =IF(E18=0,0,B18/E18) -> 0.14583333
A19: 2026-06 | B19: =COUNTIFS(Evaluación!$C$5:$C$136,A19,Evaluación!$A$5:$A$136,">1") -> 14 | C19: =SUMIFS(Evaluación!$N$5:$N$136,Evaluación!$C$5:$C$136,A19,Evaluación!$A$5:$A$136,">1") -> 4050 | D19: =IF(B19=0,0,ROUND(C19/B19,0)) -> 289 | E19: 48 | F19: =IF(E19=0,0,B19/E19) -> 0.29166667
A20: 2026-07 | B20: =COUNTIFS(Evaluación!$C$5:$C$136,A20,Evaluación!$A$5:$A$136,">1") -> 43 | C20: =SUMIFS(Evaluación!$N$5:$N$136,Evaluación!$C$5:$C$136,A20,Evaluación!$A$5:$A$136,">1") -> 12200 | D20: =IF(B20=0,0,ROUND(C20/B20,0)) -> 284 | E20: 48 | F20: =IF(E20=0,0,B20/E20) -> 0.89583333
A21: 2026-08 | B21: =COUNTIFS(Evaluación!$C$5:$C$136,A21,Evaluación!$A$5:$A$136,">1") -> 34 | C21: =SUMIFS(Evaluación!$N$5:$N$136,Evaluación!$C$5:$C$136,A21,Evaluación!$A$5:$A$136,">1") -> 10150 | D21: =IF(B21=0,0,ROUND(C21/B21,0)) -> 299 | E21: 48 | F21: =IF(E21=0,0,B21/E21) -> 0.70833333
A22: 2026-09 | B22: =COUNTIFS(Evaluación!$C$5:$C$136,A22,Evaluación!$A$5:$A$136,">1") -> 28 | C22: =SUMIFS(Evaluación!$N$5:$N$136,Evaluación!$C$5:$C$136,A22,Evaluación!$A$5:$A$136,">1") -> 5550 | D22: =IF(B22=0,0,ROUND(C22/B22,0)) -> 198 | E22: 48 | F22: =IF(E22=0,0,B22/E22) -> 0.58333333
A23: Septiembre está incompleto (datos al 24-sep).
A26: POR DEPARTAMENTO (toda la red)
A27: Departamento | B27: Kaizen | C27: DaiPuntos | D27: Promedio | E27: Meta anual** | F27: % meta
A28: Calidad | B28: =COUNTIFS(Evaluación!$F$5:$F$136,A28,Evaluación!$A$5:$A$136,">1") -> 21 | C28: =SUMIFS(Evaluación!$N$5:$N$136,Evaluación!$F$5:$F$136,A28,Evaluación!$A$5:$A$136,">1") -> 4350 | D28: =IF(B28=0,0,ROUND(C28/B28,0)) -> 207 | E28: 72 | F28: =IF(E28=0,0,B28/E28) -> 0.29166667
A29: Lanzamientos | B29: =COUNTIFS(Evaluación!$F$5:$F$136,A29,Evaluación!$A$5:$A$136,">1") -> 14 | C29: =SUMIFS(Evaluación!$N$5:$N$136,Evaluación!$F$5:$F$136,A29,Evaluación!$A$5:$A$136,">1") -> 3250 | D29: =IF(B29=0,0,ROUND(C29/B29,0)) -> 232 | E29: 72 | F29: =IF(E29=0,0,B29/E29) -> 0.19444444
A30: Mantenimiento | B30: =COUNTIFS(Evaluación!$F$5:$F$136,A30,Evaluación!$A$5:$A$136,">1") -> 18 | C30: =SUMIFS(Evaluación!$N$5:$N$136,Evaluación!$F$5:$F$136,A30,Evaluación!$A$5:$A$136,">1") -> 4550 | D30: =IF(B30=0,0,ROUND(C30/B30,0)) -> 253 | E30: 72 | F30: =IF(E30=0,0,B30/E30) -> 0.25
A31: Manufactura | B31: =COUNTIFS(Evaluación!$F$5:$F$136,A31,Evaluación!$A$5:$A$136,">1") -> 15 | C31: =SUMIFS(Evaluación!$N$5:$N$136,Evaluación!$F$5:$F$136,A31,Evaluación!$A$5:$A$136,">1") -> 2500 | D31: =IF(B31=0,0,ROUND(C31/B31,0)) -> 167 | E31: 72 | F31: =IF(E31=0,0,B31/E31) -> 0.20833333
A32: EHS | B32: =COUNTIFS(Evaluación!$F$5:$F$136,A32,Evaluación!$A$5:$A$136,">1") -> 13 | C32: =SUMIFS(Evaluación!$N$5:$N$136,Evaluación!$F$5:$F$136,A32,Evaluación!$A$5:$A$136,">1") -> 4700 | D32: =IF(B32=0,0,ROUND(C32/B32,0)) -> 362 | E32: 72 | F32: =IF(E32=0,0,B32/E32) -> 0.18055556
A33: Recursos Humanos | B33: =COUNTIFS(Evaluación!$F$5:$F$136,A33,Evaluación!$A$5:$A$136,">1") -> 11 | C33: =SUMIFS(Evaluación!$N$5:$N$136,Evaluación!$F$5:$F$136,A33,Evaluación!$A$5:$A$136,">1") -> 4200 | D33: =IF(B33=0,0,ROUND(C33/B33,0)) -> 382 | E33: 72 | F33: =IF(E33=0,0,B33/E33) -> 0.15277778
A34: Materiales | B34: =COUNTIFS(Evaluación!$F$5:$F$136,A34,Evaluación!$A$5:$A$136,">1") -> 17 | C34: =SUMIFS(Evaluación!$N$5:$N$136,Evaluación!$F$5:$F$136,A34,Evaluación!$A$5:$A$136,">1") -> 4750 | D34: =IF(B34=0,0,ROUND(C34/B34,0)) -> 279 | E34: 72 | F34: =IF(E34=0,0,B34/E34) -> 0.23611111
A35: Producción | B35: =COUNTIFS(Evaluación!$F$5:$F$136,A35,Evaluación!$A$5:$A$136,">1") -> 11 | C35: =SUMIFS(Evaluación!$N$5:$N$136,Evaluación!$F$5:$F$136,A35,Evaluación!$A$5:$A$136,">1") -> 2850 | D35: =IF(B35=0,0,ROUND(C35/B35,0)) -> 259 | E35: 72 | F35: =IF(E35=0,0,B35/E35) -> 0.15277778
A36: Logística | B36: =COUNTIFS(Evaluación!$F$5:$F$136,A36,Evaluación!$A$5:$A$136,">1") -> 5 | C36: =SUMIFS(Evaluación!$N$5:$N$136,Evaluación!$F$5:$F$136,A36,Evaluación!$A$5:$A$136,">1") -> 2250 | D36: =IF(B36=0,0,ROUND(C36/B36,0)) -> 450 | E36: 72 | F36: =IF(E36=0,0,B36/E36) -> 0.069444444
A37: Operaciones | B37: =COUNTIFS(Evaluación!$F$5:$F$136,A37,Evaluación!$A$5:$A$136,">1") -> 3 | C37: =SUMIFS(Evaluación!$N$5:$N$136,Evaluación!$F$5:$F$136,A37,Evaluación!$A$5:$A$136,">1") -> 600 | D37: =IF(B37=0,0,ROUND(C37/B37,0)) -> 200 | E37: 72 | F37: =IF(E37=0,0,B37/E37) -> 0.041666667
A38: Compras | B38: =COUNTIFS(Evaluación!$F$5:$F$136,A38,Evaluación!$A$5:$A$136,">1") -> 2 | C38: =SUMIFS(Evaluación!$N$5:$N$136,Evaluación!$F$5:$F$136,A38,Evaluación!$A$5:$A$136,">1") -> 750 | D38: =IF(B38=0,0,ROUND(C38/B38,0)) -> 375 | E38: 72 | F38: =IF(E38=0,0,B38/E38) -> 0.027777778
A39: Cenzontle No. 7 Parque Industrial Finsa Ramos Arizpe, Coahuila, Mexico. | B39: =COUNTIFS(Evaluación!$F$5:$F$136,A39,Evaluación!$A$5:$A$136,">1") -> 1 | C39: =SUMIFS(Evaluación!$N$5:$N$136,Evaluación!$F$5:$F$136,A39,Evaluación!$A$5:$A$136,">1") -> 400 | D39: =IF(B39=0,0,ROUND(C39/B39,0)) -> 400 | E39: 72 | F39: =IF(E39=0,0,B39/E39) -> 0.013888889
A40: ** 6 sitios × 12 meses = 72 al año por departamento si participaran los 6.

Sheet Auditoría formatos
A1: AUDITORÍA DE LOS 91 FORMATOS FM-MOP-0023-DR
A4: RESUMEN
A5: A. Cuantificado en $ (tiene (B) Beneficio o Ahorro al año) | D5: 12 | E5: 0.13186813
A6: B. Con números en Antes/Después pero sin total en $ | D6: 29 | E6: 0.31868132
A7: C. Solo descripción de texto, cero números | D7: 42 | E7: 0.46153846
A8: D. Tabla de beneficio completamente vacía | D8: 8 | E8: 0.087912088
A9: TOTAL | D9: 91
A11: Formatos que NO marcaron el estatus (Implementada/Aprobada/…) | D11: 87
A12: Formatos que NO marcaron '¿Se puede implementar en otra área?' | D12: 64
A13: Formatos con (B) Beneficio $ numérico | D13: 12
A14: Formatos con 'Ahorro al año' lleno | D14: 1
A17: DETALLE POR KAIZEN
A18: ID | B18: Persona | C18: Planta | D18: Clase | E18: (B) Benef. | F18: (C) Costo | G18: Unidad declarada | H18: Estatus | I18: Expansión | J18: ¿Dónde? | K18: Archivo
A19: 40 | B19: Tania Alejandra Lira Villarreal | C19: Planta 6/7 | D19: A. Cuantificado en $ | E19: 474000 | F19: 552000 | G19: MXN | H19: — sin marcar | I19: — | K19: FM-MOP-0023-DR Formato de Kaizen -R3 1 LOGIST_Tania Alejandra Lira 1.xlsx
A20: 88 | B20: Tania Alejandra Lira Villarreal | C20: Planta 3/4 | D20: A. Cuantificado en $ | E20: 438000 | F20: 510000 | G20: MXN | H20: — sin marcar | I20: — | K20: FM-MOP-0023-DR Formato de Kaizen -R3 1 LOGIST_Tania Alejandra Lira 2.xlsx
A21: 96 | B21: Francisco Daniel Charles Sanchez | C21: Planta 2 | D21: A. Cuantificado en $ | E21: 437483.41 | F21: 115868.45 | G21: Evento | H21: — sin marcar | I21: — | J21: Area de Compras Indirectas | K21: FM-MOP-0023-DR Formato de Kaizen -R3 - Reducc_Francisco Daniel Cha.xlsx
A22: 91 | B22: Karla Guadalupe Padilla Gonzalez | C22: Planta 3/4 | D22: A. Cuantificado en $ | E22: 130000 | F22: 550 | G22: Total | H22: — sin marcar | I22: — | K22: FM-MOP-0023-DR Formato de Kaizen AGOSTO_Karla Guadalupe Padi.xlsx
A23: 43 | B23: Felipe Angel Guerrero Herrera | C23: Planta 2 | D23: A. Cuantificado en $ | E23: 25000 | G23: Total | H23: — sin marcar | I23: — | K23: Kaizen_Mtto_JUL_2026 Mejora_Felipe Angel Guerrer.xlsx
A24: 55 | B24: Nestor Garcia Castro Garcia Castro | C24: Planta 3/4 | D24: A. Cuantificado en $ | E24: 15800 | F24: 1000 | H24: — sin marcar | I24: — | J24: Area de UPPER | K24: Kaizen Rivian Door julio_Nestor Garcia Castr.xlsx
A25: 70 | B25: Diego Valencia Alcazar | C25: Planta 1 | D25: A. Cuantificado en $ | E25: 14000 | F25: 0 | G25: HRS | H25: — sin marcar | I25: NO | K25: Kaizen Moldeo Agosto 2026_Diego Valencia Alcaz.xlsx
A26: 7 | B26: Luis Gustavo Garcia Fuentes | C26: Planta 1 | D26: A. Cuantificado en $ | E26: 4166.96 | F26: 0 | G26: 7920.0 | H26: — sin marcar | I26: NO | K26: FM-MOP-0023-DR Formato de Kaizen -R3 2_Luis Gustavo Garcia.xlsx
A27: 97 | B27: Salome Dominguez | C27: Planta 1 | D27: A. Cuantificado en $ | E27: 499.25 | G27: % | H27: — sin marcar | I27: — | J27: Procesos donde aplique grasa | K27: FM-MOP-0023-DR Formato de Kaizen -R3_Salome Dominguez.xlsx
A28: 87 | B28: Fernando Gonzalez | C28: Planta 3/4 | D28: A. Cuantificado en $ | E28: 460.89 | F28: 0 | G28: USD | H28: — sin marcar | I28: — | K28: Calidad - P3y4 - Agosto_Fernando Gonzalez.xlsx
A29: 28 | B29: Luis Gustavo Garcia Fuentes | C29: Planta 1 | D29: A. Cuantificado en $ | E29: 430 | F29: 0 | G29: 1.0 | H29: — sin marcar | I29: NO | K29: FM-MOP-0023-DR Formato de Kaizen - EFLEXO_Luis Gustavo Garcia.xlsx
A30: 94 | B30: Fannie Grettelle Aguilar Valero | C30: Planta 1 | D30: A. Cuantificado en $ | E30: 6.73 | F30: 0.6 | G30: USD/ Pza | H30: — sin marcar | I30: NO | K30: FM-MOP-0023-DR Formato de Kaizen -R3 (_Fannie Grettelle Agu.xlsx
A31: 29 | B31: Ruben Alejandro Siller Valverde | C31: Planta 6/7 | D31: B. Números sin total en $ | F31: 0 | G31: Rutas | H31: — sin marcar | I31: — | K31: Copy of FM-MOP-0023-DR Formato de Kaizen -JUL_Ruben Alejandro Sill.xlsx
A32: 25 | B32: Jose Gerardo Gudiño Ruiz | C32: Planta 1 | D32: B. Números sin total en $ | E32: 0 | F32: 0 | G32: Total | H32: — sin marcar | I32: — | K32: FM-MOP-0023-DR Formato de Kaizen junio 26_Jose Gerardo Gudiño.xlsx
A33: 45 | B33: Adrian Rodrigues Campos | C33: Planta 6/7 | D33: B. Números sin total en $ | G33: $ | H33: — sin marcar | I33: — | J33: Cartonera P7 | K33: FM-MOP-0023-DR Formato de Kaizen - Equipos mó_Adrian Rodrigues Cam.xlsx
A34: 11 | B34: Monica Arcelia Sifuentes Ortiz | C34: Planta 2 | D34: B. Números sin total en $ | G34: N/A | H34: — sin marcar | I34: SI | J34: N/A | K34: FM-MOP-0023-DR Formato de Kaizen -R3 (003)_Monica Arcelia Sifue.xlsx
A35: 21 | B35: Arsenio Vazquez | C35: Planta 1 | D35: B. Números sin total en $ | G35: Total | H35: — sin marcar | I35: — | K35: FM-MOP-0023-DR Formato de Kaizen -R3 (1)_Arsenio Vazquez.xlsx
A36: 52 | B36: Teresita Gallegos | C36: Planta 3/4 | D36: B. Números sin total en $ | G36: Seg. | H36: — sin marcar | I36: NO | K36: FM-MOP-0023-DR Formato de Kaizen -R3 (1)_Teresita Gallegos.xlsx
A37: 9 | B37: Brandon Alejandro Duran Rios | C37: Planta 1 | D37: B. Números sin total en $ | F37: 0 | G37: USD | H37: — sin marcar | I37: — | K37: FM-MOP-0023-DR Formato de Kaizen -R3 1 JUNIO_Brandon Alejandro Du.xlsx
A38: 4 | B38: Tania Alejandra Lira Villarreal | C38: Planta 3/4 | D38: B. Números sin total en $ | G38: USD | H38: — sin marcar | I38: — | K38: FM-MOP-0023-DR Formato de Kaizen -R3 1 LOGIST_Tania Alejandra Lira.xlsx
A39: 84 | B39: Ricardo Mendoza Hernandez | C39: Planta 2 | D39: B. Números sin total en $ | G39: USD | H39: — sin marcar | I39: NO | J39: N/A | K39: FM-MOP-0023-DR Formato de Kaizen -R3 Cambio d_Ricardo Mendoza Hern 1.xlsx
A40: 47 | B40: Ricardo Mendoza Hernandez | C40: Planta 2 | D40: B. Números sin total en $ | G40: USD | H40: — sin marcar | I40: NO | J40: N/A | K40: FM-MOP-0023-DR Formato de Kaizen -R3 Cambio d_Ricardo Mendoza Hern.xlsx
A41: 56 | B41: Alejandra Natali Puente Vielma | C41: Parras | D41: B. Números sin total en $ | G41: KM | H41: — sin marcar | I41: — | K41: FM-MOP-0023-DR Formato de Kaizen -R3 Natali P_Alejandra Natali Pue.xlsx
A42: 66 | B42: Anayeli Rivera | C42: Planta 2 | D42: B. Números sin total en $ | G42: Total | H42: — sin marcar | I42: — | K42: FM-MOP-0023-DR Formato de Kaizen -R3 prov_Anayeli Rivera.xlsx
A43: 46 | B43: Berenice Esquivel Delgadillo | C43: Planta 6/7 | D43: B. Números sin total en $ | G43: 3.66 | H43: — sin marcar | I43: — | J43: Frame SUV | K43: FM-MOP-0023-DR Formato de Kaizen -R3_Berenice Esquivel De.xlsx
A44: 74 | B44: Eduardo Morales Rodriguez | C44: Planta 6/7 | D44: B. Números sin total en $ | G44: 307.0539419087137 | H44: — sin marcar | I44: — | K44: FM-MOP-0023-DR Formato de Kaizen -R3_Eduardo Morales Rodr.xlsx
A45: 23 | B45: Fannie Grettelle Aguilar Valero | C45: Planta 1 | D45: B. Números sin total en $ | G45: Segundos | H45: — sin marcar | I45: NO | K45: FM-MOP-0023-DR Formato de Kaizen -R3_Fannie Grettelle Agu.xlsx
A46: 2 | B46: Karina Guadalupe Flores Gonzalez | C46: Parras | D46: B. Números sin total en $ | G46: EA | H46: — sin marcar | I46: SI | J46: Otros proveedores | K46: FM-MOP-0023-DR Formato de Kaizen -R3_Karina Guadalupe Flo.xlsx
A47: 86 | B47: Brandon Ramon Cano Resendez | C47: Parras | D47: B. Números sin total en $ | G47: segundos | H47: aprobada | I47: NO | J47: Mesa de corte | K47: FM-MOP-0023-DR Formato de Kaizen Calidad_Brandon Ramon Cano R.xlsx
A48: 39 | B48: Alejandro Lopez Lopez | C48: Planta 3/4 | D48: B. Números sin total en $ | F48: 0 | G48: % | H48: efectiva,implementada | I48: SI | K48: FM-MOP-0023-DR_Kaizen_Reportes_Transporte_For_Alejandro Lopez Lope.xlsx
A49: 80 | B49: Diego Valencia Alcazar | C49: Planta 1 | D49: B. Números sin total en $ | G49: Total | H49: — sin marcar | I49: — | K49: KAIZEN CALIDAD ENSAMBLE - PLANTA 1 - AGOSTO 2_Diego Valencia Alcaz.xlsx
A50: 62 | B50: Gustavo Vargas Quiroz | C50: Planta 6/7 | D50: B. Números sin total en $ | G50: hrs | H50: — sin marcar | I50: — | K50: KAIZEN MATERIALES JULIO_Gustavo Vargas Quiro.xlsx
B51: (sin cruce) | D51: B. Números sin total en $ | G51: MIN | H51: — sin marcar | I51: SI | K51: KAIZEN_DASHBOARD FORD & STELLANTIS_Jose Carlos Herrera.xlsx
A52: 12 | B52: Ricardo Valdivia Leyva | C52: Planta 3/4 | D52: B. Números sin total en $ | G52: Piezas | H52: — sin marcar | I52: — | K52: Kaizen Calidad P3-4-Junio_Ricardo Valdivia Ley.xlsx
A53: 38 | B53: Hector Orduño Jauregui | C53: Planta 6/7 | D53: B. Números sin total en $ | G53: seg | H53: — sin marcar | I53: — | K53: Kaizen Julio 2026_Hector Orduño Jaureg.xlsx
A54: 17 | B54: Gerardo Aguilar Gonzalez | C54: Planta 1 | D54: B. Números sin total en $ | G54: piezas x hra | H54: — sin marcar | I54: SI | K54: Kaizen Manufactura Julio 26_Gerardo Aguilar Gonz.xlsx
A55: 3 | B55: Idalia Recio | C55: Planta 3/4 | D55: B. Números sin total en $ | G55: NA | H55: — sin marcar | I55: — | J55: NA | K55: Kaizen Mayo Calidad_Idalia Recio.xlsx
A56: 14 | B56: Fernanda Monserrath Vielma Zavala | C56: Planta 6/7 | D56: B. Números sin total en $ | G56: minutos | H56: — sin marcar | I56: SI | J56: no | K56: Kaizen Mesas de inspección Cuarentena -Antoni_Fernanda Monserrath.xlsx
A57: 72 | B57: Erik Aguirre Ramirez | C57: Planta 3/4 | D57: B. Números sin total en $ | G57: % | H57: implementada | I57: SI | J57: ¿Dónde? Plantas / áreas Daimay | K57: Kaizen_Prenomina_Digital_Daimay_Erik Aguirre Ramirez.xlsx
A58: 51 | B58: Fernanda Monserrath Vielma Zavala | C58: Parras | D58: B. Números sin total en $ | G58: seg/pza | H58: aprobada,efectiva,implementada | I58: SI | J58: Costura T1XX | K58: Kaizen_Prueba_Material_5mm_T1XX-Luis Reyes_Fernanda Monserrath.xlsx
A59: 73 | B59: Mariana Valencia | C59: Planta 1 | D59: B. Números sin total en $ | G59: Total | H59: — sin marcar | I59: — | K59: kaizen Agosto 2026_Mariana Valencia.xlsx
A60: 95 | B60: Fernanda Monserrath Vielma Zavala | C60: Planta 6/7 | D60: C. Solo texto | G60: NA | H60: — sin marcar | I60: — | J60: NA | K60: 08_29_Kaizen_Flujo de Dock Audit_Carlos_Mende_Fernanda Monserrath.xlsx
A61: 92 | B61: Hector Jaziel Martinez | C61: Planta 2 | D61: C. Solo texto | G61: Total | H61: — sin marcar | I61: — | J61: Nuevos Proyectos | K61: 8. Kaizen_Produccion_Agosto_2026_Hector Jaziel Martin.xlsx
A62: 93 | B62: Hector Jaziel Martinez | C62: Planta 2 | D62: C. Solo texto | G62: Total | H62: — sin marcar | I62: — | J62: Nuevos Proyectos | K62: 8. Kaizen_Produccion_Seguridad_Agosto_2026_Hector Jaziel Martin.xlsx
A63: 58 | B63: Hector Jaziel Martinez | C63: Planta 2 | D63: C. Solo texto | G63: Total | H63: — sin marcar | I63: — | J63: Nuevos Proyectos | K63: Copy of Kaizen_Produccion_Julio_2026_Hector Jaziel Martin.xlsx
A64: 59 | B64: Hector Jaziel Martinez | C64: Planta 2 | D64: C. Solo texto | G64: Total | H64: — sin marcar | I64: — | J64: Nuevos Proyectos | K64: Copy of Kaizen_Produccion_Junio_2026_Hector Jaziel Martin.xlsx
A65: 41 | B65: Daniel Alejandro Parra Mendoza | C65: Parras | D65: C. Solo texto | G65: Total | H65: — sin marcar | I65: — | K65: FM-MOP-0023-DR Formato de Kaizen - Julio_Daniel Alejandro Par.xlsx
A66: 57 | B66: Jose Emmanuel Alejo Wong | C66: Planta 2 | D66: C. Solo texto | G66: Total | H66: — sin marcar | I66: — | K66: FM-MOP-0023-DR Formato de Kaizen -R2 Calidad-_Jose Emmanuel Alejo 1.xlsx
A67: 34 | B67: Monica Arcelia Sifuentes Ortiz | C67: Planta 2 | D67: C. Solo texto | G67: Total | H67: — sin marcar | I67: SI | K67: FM-MOP-0023-DR Formato de Kaizen -R3 - PROPUE_Monica Arcelia Sifue.xlsx
A68: 76 | B68: Paola Fernandez | C68: Planta 1 | D68: C. Solo texto | F68: 0 | G68: Total | H68: — sin marcar | I68: SI | J68: Ensamble | K68: FM-MOP-0023-DR Formato de Kaizen -R3 2_Paola Fernandez.xlsx
A69: 82 | B69: Monica Arcelia Sifuentes Ortiz | C69: Planta 2 | D69: C. Solo texto | G69: Total | H69: — sin marcar | I69: — | K69: FM-MOP-0023-DR Formato de Kaizen -R3 AGOSTO_Monica Arcelia Sifue.xlsx
A70: 65 | B70: Saul Antonio Gallegos Sanchez | C70: Planta 2 | D70: C. Solo texto | G70: Total | H70: — sin marcar | I70: — | K70: FM-MOP-0023-DR Formato de Kaizen -R3 Agosto E_Saul Antonio Gallego.xlsx
A71: 42 | B71: Omar Alejandro Alvarez Charles | C71: Planta 3/4 | D71: C. Solo texto | G71: Total | H71: — sin marcar | I71: — | K71: FM-MOP-0023-DR Formato de Kaizen -R3 Julio EH_Omar Alejandro Alvar.xlsx
A72: 32 | B72: Saul Antonio Gallegos Sanchez | C72: Planta 2 | D72: C. Solo texto | G72: Total | H72: — sin marcar | I72: — | K72: FM-MOP-0023-DR Formato de Kaizen -R3 Julio EH_Saul Antonio Gallego.xlsx
A73: 27 | B73: Saul Antonio Gallegos Sanchez | C73: Planta 2 | D73: C. Solo texto | G73: Total | H73: — sin marcar | I73: — | K73: FM-MOP-0023-DR Formato de Kaizen -R3 LAVA OJO_Saul Antonio Gallego.xlsx
A74: 13 | B74: Ricardo Mendoza Hernandez | C74: Planta 2 | D74: C. Solo texto | G74: Total | H74: — sin marcar | I74: NO | J74: N/A | K74: FM-MOP-0023-DR Formato de Kaizen -R3 Reemplaz_Ricardo Mendoza Hern.xlsx
A75: 63 | B75: Miguel Eduardo Villegas Prieto | C75: Planta 1 | D75: C. Solo texto | G75: Total | H75: — sin marcar | I75: NO | K75: FM-MOP-0023-DR Formato de Kaizen -R3_Miguel Eduardo Ville.xlsx
A76: 37 | B76: Jennifer Garcia Gregorio | C76: Planta 6/7 | D76: C. Solo texto | G76: Total | H76: — sin marcar | I76: — | K76: Formato de Kaizen Manufactura P6_Jennifer Garcia Greg.xlsx
A77: 69 | B77: Diana Themis Zacanelles Orta | C77: Planta 1 | D77: C. Solo texto | G77: Total | H77: — sin marcar | I77: NO | J77: no | K77: Formato de Kaizen RH Agosto_Diana Themis Zacanel.xlsx
A78: 31 | B78: Diana Themis Zacanelles Orta | C78: Planta 1 | D78: C. Solo texto | G78: Total | H78: — sin marcar | I78: NO | J78: no | K78: Formato de Kaizen RH Julio_Diana Themis Zacanel.xlsx
A79: 85 | B79: Daniel Alejandro Parra Mendoza | C79: Parras | D79: C. Solo texto | G79: Total | H79: — sin marcar | I79: — | J79: en produccion | K79: KAIZEN AGOSTO_Daniel Alejandro Par.xlsx
A80: 22 | B80: Maximiliano Escobedo | C80: Planta 1 | D80: C. Solo texto | G80: Total | H80: — sin marcar | I80: — | J80: N/A | K80: KAIZEN JULIO CHECKLIST DE TRANSFERENCIA_Maximiliano Escobedo.xlsx
A81: 75 | B81: Berenice Esquivel Delgadillo | C81: Planta 6/7 | D81: C. Solo texto | G81: Total | H81: — sin marcar | I81: — | K81: Kaizen - Operaciones_Berenice Esquivel De.xlsx
A82: 49 | B82: Guillermo Garcia | C82: Planta 3/4 | D82: C. Solo texto | G82: Total | H82: — sin marcar | I82: — | K82: Kaizen MFG P4_Guillermo Garcia.xlsx
A83: 60 | B83: Fernanda Monserrath Vielma Zavala | C83: Planta 6/7 | D83: C. Solo texto | F83: 21711 | G83: Total | H83: — sin marcar | I83: — | K83: Kaizen Mesa de inspección DQMC -Hector Rodrig_Fernanda Monserrath.xlsx
A84: 99 | B84: Guillermo Garcia | C84: Planta 3/4 | D84: C. Solo texto | G84: Total | H84: — sin marcar | I84: SI | J84: Mesa de alineado Door upper | K84: Kaizen S_Guillermo Garcia.xlsx
A85: 16 | B85: Citlalli Ozuna | C85: Planta 3/4 | D85: C. Solo texto | E85: 0 | G85: Total | H85: — sin marcar | I85: — | K85: Kaizen lanzameintos Junio Planta 4_Citlalli Ozuna.xlsx
A86: 83 | B86: Citlalli Ozuna | C86: Planta 3/4 | D86: C. Solo texto | G86: Total | H86: — sin marcar | I86: — | J86: En todas las areas | K86: Kaizen lanzamientos-Agosto_Citlalli Ozuna.xlsx
A87: 81 | B87: Erik Ovalle | C87: Planta 3/4 | D87: C. Solo texto | G87: Total | H87: — sin marcar | I87: SI | J87: Mesas de forrado | K87: Kaizen manufactura mes agosto_Erik Ovalle.xlsx
A88: 68 | B88: Francisco Hernandez | C88: Planta 2 | D88: C. Solo texto | G88: Total | H88: — sin marcar | I88: — | K88: Kaizen_LAUNCH_AGOSTO_2026_Francisco Hernandez.xlsx
A89: 33 | B89: Francisco Hernandez | C89: Planta 2 | D89: C. Solo texto | G89: Total | H89: — sin marcar | I89: — | J89: Mesas de trabajo frame | K89: Kaizen_LAUNCH_JULIO_2026_Francisco Hernandez.xlsx
A90: 8 | B90: Francisco Hernandez | C90: Planta 2 | D90: C. Solo texto | G90: Total | H90: — sin marcar | I90: — | J90: Pruebas electricas | K90: Kaizen_LAUNCH_JUNIO_2026_Francisco Hernandez.xlsx
A91: 64 | B91: Carlos Lozano | C91: Planta 2 | D91: C. Solo texto | G91: Total | H91: — sin marcar | I91: — | K91: Kaizen_MFG_AGOSTO_2026 -_Carlos Lozano.xlsx
A92: 36 | B92: Carlos Lozano | C92: Planta 2 | D92: C. Solo texto | G92: Total | H92: — sin marcar | I92: — | K92: Kaizen_MFG_JULIO_2026_Carlos Lozano.xlsx
A93: 10 | B93: Carlos Lozano | C93: Planta 2 | D93: C. Solo texto | G93: Total | H93: — sin marcar | I93: — | K93: Kaizen_MFG_JUNIO_2026_Carlos Lozano.xlsx
A94: 89 | B94: Felipe Angel Guerrero Herrera | C94: Planta 2 | D94: C. Solo texto | G94: Total | H94: — sin marcar | I94: NO | J94: n/a | K94: Kaizen_Mtto_AGO_2026 Mejora_Felipe Angel Guerrer.xlsx
A95: 90 | B95: Felipe Angel Guerrero Herrera | C95: Planta 2 | D95: C. Solo texto | G95: Total | H95: — sin marcar | I95: — | J95: todas las dobles plancha | K95: Kaizen_Mtto_AGO_Seguridad_2026_Felipe Angel Guerrer.xlsx
A96: 44 | B96: Felipe Angel Guerrero Herrera | C96: Planta 2 | D96: C. Solo texto | H96: — sin marcar | I96: — | J96: en todas las maquinas de rebordeo | K96: Kaizen_Mtto_JUL_2026 Seguridad_Felipe Angel Guerrer.xlsx
A97: 15 | B97: Felipe Angel Guerrero Herrera | C97: Planta 2 | D97: C. Solo texto | H97: — sin marcar | I97: — | J97: en todas las maquinas de rebordeo | K97: Kaizen_Mtto_JUN_2026_Felipe Angel Guerrer.xlsx
A98: 20 | B98: Arturo Romo Antonio | C98: Planta 1 | D98: C. Solo texto | G98: MENOS PIEZAS REC | H98: — sin marcar | I98: — | J98: N/A | K98: kaizen Julio 2026 Nitro_Arturo Romo Antonio.xlsx
A99: 19 | B99: Mariana Valencia | C99: Planta 1 | D99: C. Solo texto | G99: Total | H99: — sin marcar | I99: — | K99: kaizen Junio 2026_Mariana Valencia.xlsx
A100: 98 | B100: Guillermo Garcia | C100: Planta 3/4 | D100: C. Solo texto | G100: Total | H100: — sin marcar | I100: SI | J100: Mesas de alineado insertos | K100: kaizen MC_Guillermo Garcia.xlsx
A101: 24 | B101: Mariana Valencia | C101: Planta 1 | D101: C. Solo texto | G101: Total | H101: — sin marcar | I101: — | K101: kaizen julio 2026_Mariana Valencia.xlsx
A102: 78 | B102: Jose Ignacio Arias Palacios | C102: Planta 1 | D102: D. Vacío | H102: — sin marcar | I102: — | K102: FM-MOP-0023-DR Formato de Kaizen -R1_Jose Ignacio Arias P.xlsx
A103: 26 | B103: Ulises Eduardo Hernandez Perez | C103: Planta 1 | D103: D. Vacío | H103: — sin marcar | I103: — | K103: FM-MOP-0023-DR Formato de Kaizen -R2 (2)_Ulises Eduardo Herna.xlsx
A104: 5 | B104: Jose Emmanuel Alejo Wong | C104: Planta 2 | D104: D. Vacío | H104: — sin marcar | I104: — | K104: FM-MOP-0023-DR Formato de Kaizen -R2 Calidad-_Jose Emmanuel Alejo.xlsx
A105: 79 | B105: Ensamble Produccion | C105: Planta 1 | D105: D. Vacío | H105: — sin marcar | I105: — | K105: KAIZEN AGOSTO ENSAMBLE 2026_Ensamble Produccion.xlsx
...

Sheet Salón del Ahorro
A1: SALÓN DEL AHORRO
A2: Reconocimiento aparte del ranking de DaiPuntos. Aquí van los Kaizen con ahorro en pesos.
A3: Solo los marcados VALIDADO cuentan para el total que se reporta a Dirección. El estado lo cambias tú (columna azul).
A5: # | B5: Persona | C5: Planta | D5: Depto | E5: Ahorro MXN/año | F5: Estado | G5: Evidencia en su formato | H5: El Kaizen
A6: 1 | B6: Ricardo Mendoza Hernandez | C6: Planta 2 | D6: Materiales | E6: 644569 | F6: Pendiente | G6: Formato declara 37,915.84 USD/año — convertido a MXN @17 | H6: Ahorro anual de $37915.84 USD
A7: 2 | B7: Tania Alejandra Lira Villarreal | C7: Planta 3/4 | D7: Logística | E7: 474000 | F7: Pendiente | G7: Su formato NO trae cifras (unidades 'USD','Total' sin valor) | H7: COSTOS FIJOS POR PERIODOS DE 3 MESES
A8: 3 | B8: Federico Alberto Obispo Florencio | C8: Planta 2 | D8: Calidad | E8: 438000 | F8: Pendiente | G8: Su formato NO trae ninguna cifra | Líder real; lo registró Jose Emmanuel Alejo Wong | H8: Se implementa una lampara para la inspeccion visual y deteccion de presencia de componentes del cargador
A9: 4 | B9: Tania Alejandra Lira Villarreal | C9: Planta 6/7 | D9: Logística | E9: 438000 | F9: Pendiente | G9: Su formato dice B=474,000 C=552,000 MXN — el costo SUPERA al beneficio | H9: LICITACION PROVEEDORES EXTERNOS
A10: 5 | B10: Daniel Alejandro Parra Mendoza | C10: Parras | D10: EHS | E10: 438000 | F10: Pendiente | G10: Su formato NO trae ninguna cifra | H10: SE ESTANDARIZO EL AREA DE DISPOSICION DE QUIMICOS PELIGROSOS DEL PROCESO DE FOAM
A11: 6 | B11: Tania Alejandra Lira Villarreal | C11: Planta 3/4 | D11: Logística | E11: 288000 | F11: Pendiente | G11: Su formato dice B=438,000 C=510,000 MXN — el costo SUPERA al beneficio | H11: LICITACION PROVEEDORES EXTERNOS
A12: 7 | B12: Fannie Aguilar | C12: Planta 1 | D12: Lanzamientos | E12: 208420 | F12: Pendiente | G12: Formato con Ahorro al año lleno: 12,260 USD/año — convertido @17 | H12: Se desarrolló una fuente alternativa en China, validada para el programa, con un costo de $0.60 USD por pieza, generando un ahorro de $6.13 USD por pieza.
A13: 8 | B13: Ricardo Mendoza Hernandez | C13: Planta 2 | D13: Materiales | E13: 18173 | F13: Pendiente | G13: Formato declara 1,069 USD/año — convertido a MXN @17 | H13: Ahorro anual de $1,069 USD
D15: TOTAL DECLARADO | E15: =SUM(E6:E13) -> 2947162
D16: TOTAL VALIDADO | E16: =SUMIF(F6:F13,"Validado",E6:E13) -> 0
A18: Escribe 'Validado' en la columna Estado cuando Finanzas firme el caso. Ese es el número que puedes llevar a Dirección.
A19: Los 5 renglones en rojo necesitan soporte: o su formato no trae cifras, o el costo declarado supera al beneficio.

Sheet Ranking
A1: RANKING INDIVIDUAL — abril a septiembre 2026
A2: Cuenta el LÍDER del Kaizen (col. "Nombre de líder" del Form), no quien lo subió. Solo matriz + bonos; los ahorros van al Salón del Ahorro.
A4: # | B4: Persona | C4: Planta | D4: Kaizen | E4: DaiPuntos | F4: Proyección anual | G4: Nivel (anual)
A5: 1 | B5: Felipe Angel Guerrero Herrera | C5: Planta 2 | D5: =COUNTIFS(Evaluación!$D$5:$D$139,$B5) -> 5 | E5: =SUMIFS(Evaluación!$N$5:$N$139,Evaluación!$D$5:$D$139,$B5) -> 1700 | F5: =E5*2 -> 3400 | G5: =IF(F5>=2500,"Platino",IF(F5>=1500,"Oro",IF(F5>=600,"Plata","Bronce"))) -> Platino
A6: 2 | B6: Saúl Antonio Gallegos Sánchez | C6: Planta 2 | D6: =COUNTIFS(Evaluación!$D$5:$D$139,$B6) -> 4 | E6: =SUMIFS(Evaluación!$N$5:$N$139,Evaluación!$D$5:$D$139,$B6) -> 1600 | F6: =E6*2 -> 3200 | G6: =IF(F6>=2500,"Platino",IF(F6>=1500,"Oro",IF(F6>=600,"Plata","Bronce"))) -> Platino
A7: 3 | B7: Tania Alejandra Lira Villarreal | C7: Planta 3/4 | D7: =COUNTIFS(Evaluación!$D$5:$D$139,$B7) -> 3 | E7: =SUMIFS(Evaluación!$N$5:$N$139,Evaluación!$D$5:$D$139,$B7) -> 1350 | F7: =E7*2 -> 2700 | G7: =IF(F7>=2500,"Platino",IF(F7>=1500,"Oro",IF(F7>=600,"Plata","Bronce"))) -> Platino
A8: 4 | B8: Ricardo Mendoza Hernandez | C8: Planta 2 | D8: =COUNTIFS(Evaluación!$D$5:$D$139,$B8) -> 3 | E8: =SUMIFS(Evaluación!$N$5:$N$139,Evaluación!$D$5:$D$139,$B8) -> 1300 | F8: =E8*2 -> 2600 | G8: =IF(F8>=2500,"Platino",IF(F8>=1500,"Oro",IF(F8>=600,"Plata","Bronce"))) -> Platino
A9: 5 | B9: Jaziel Mancilla | C9: Planta 2 | D9: =COUNTIFS(Evaluación!$D$5:$D$139,$B9) -> 5 | E9: =SUMIFS(Evaluación!$N$5:$N$139,Evaluación!$D$5:$D$139,$B9) -> 1250 | F9: =E9*2 -> 2500 | G9: =IF(F9>=2500,"Platino",IF(F9>=1500,"Oro",IF(F9>=600,"Plata","Bronce"))) -> Platino
A10: 6 | B10: Daniel Alejandro Parra Mendoza | C10: Parras | D10: =COUNTIFS(Evaluación!$D$5:$D$139,$B10) -> 3 | E10: =SUMIFS(Evaluación!$N$5:$N$139,Evaluación!$D$5:$D$139,$B10) -> 1100 | F10: =E10*2 -> 2200 | G10: =IF(F10>=2500,"Platino",IF(F10>=1500,"Oro",IF(F10>=600,"Plata","Bronce"))) -> Oro
A11: 7 | B11: Omar Alvarez | C11: Planta 3/4 | D11: =COUNTIFS(Evaluación!$D$5:$D$139,$B11) -> 3 | E11: =SUMIFS(Evaluación!$N$5:$N$139,Evaluación!$D$5:$D$139,$B11) -> 1050 | F11: =E11*2 -> 2100 | G11: =IF(F11>=2500,"Platino",IF(F11>=1500,"Oro",IF(F11>=600,"Plata","Bronce"))) -> Oro
A12: 8 | B12: Francisco Hernandez Ramirez | C12: Planta 2 | D12: =COUNTIFS(Evaluación!$D$5:$D$139,$B12) -> 3 | E12: =SUMIFS(Evaluación!$N$5:$N$139,Evaluación!$D$5:$D$139,$B12) -> 800 | F12: =E12*2 -> 1600 | G12: =IF(F12>=2500,"Platino",IF(F12>=1500,"Oro",IF(F12>=600,"Plata","Bronce"))) -> Oro
A13: 9 | B13: Eduardo Gonzalez | C13: Planta 1 | D13: =COUNTIFS(Evaluación!$D$5:$D$139,$B13) -> 2 | E13: =SUMIFS(Evaluación!$N$5:$N$139,Evaluación!$D$5:$D$139,$B13) -> 750 | F13: =E13*2 -> 1500 | G13: =IF(F13>=2500,"Platino",IF(F13>=1500,"Oro",IF(F13>=600,"Plata","Bronce"))) -> Oro
A14: 10 | B14: Karina Guadalupe Flores González | C14: Parras | D14: =COUNTIFS(Evaluación!$D$5:$D$139,$B14) -> 2 | E14: =SUMIFS(Evaluación!$N$5:$N$139,Evaluación!$D$5:$D$139,$B14) -> 750 | F14: =E14*2 -> 1500 | G14: =IF(F14>=2500,"Platino",IF(F14>=1500,"Oro",IF(F14>=600,"Plata","Bronce"))) -> Oro
A15: 11 | B15: Citlalli Ozuna | C15: Planta 3/4 | D15: =COUNTIFS(Evaluación!$D$5:$D$139,$B15) -> 4 | E15: =SUMIFS(Evaluación!$N$5:$N$139,Evaluación!$D$5:$D$139,$B15) -> 700 | F15: =E15*2 -> 1400 | G15: =IF(F15>=2500,"Platino",IF(F15>=1500,"Oro",IF(F15>=600,"Plata","Bronce"))) -> Plata
A16: 12 | B16: Juan Carlos Guerrero Lozano | C16: Planta 2 | D16: =COUNTIFS(Evaluación!$D$5:$D$139,$B16) -> 3 | E16: =SUMIFS(Evaluación!$N$5:$N$139,Evaluación!$D$5:$D$139,$B16) -> 700 | F16: =E16*2 -> 1400 | G16: =IF(F16>=2500,"Platino",IF(F16>=1500,"Oro",IF(F16>=600,"Plata","Bronce"))) -> Plata
... A92: 88 | B92: Mario Alvarado | C92: Planta 6/7 | D92: =COUNTIFS(Evaluación!$D$5:$D$139,$B92) -> 1 | E92: =SUMIFS(Evaluación!$N$5:$N$139,Evaluación!$D$5:$D$139,$B92) -> 100 | F92: =E92*2 -> 200 | G92: =IF(F92>=2500,"Platino",IF(F92>=1500,"Oro",IF(F92>=600,"Plata","Bronce"))) -> Bronce

Sheet Cambio de líder
A1: CORRECCIÓN DE ATRIBUCIÓN — LÍDER vs QUIEN REGISTRÓ
A2: Los DaiPuntos se acreditan al campo "Nombre de líder" del Form, no a la cuenta que subió el registro. El Número de Empleado del Form corresponde al líder, lo que permitió validar la asignación.
A4: ID | B4: Planta | C4: Registró en el Form | D4: Líder real (recibe los puntos) | E4: # Empleado | F4: DaiPuntos | G4: Tipo de cambio | H4: Nota
A5: 7 | B5: Planta 1 | C5: Luis Gustavo Garcia Fuentes | D5: Maria Fernanda Tovanche | E5: 3049161 | F5: 450 | G5: Los puntos cambian de persona
A6: 9 | B6: Planta 1 | C6: Brandon Alejandro Duran Rios | D6: Brandon Durán | E6: 3059699 | F6: 450 | G6: Solo se corrigió la escritura del nombre
A7: 28 | B7: Planta 1 | C7: Luis Gustavo Garcia Fuentes | D7: Monserrat Arana | E7: 3041429 | F7: 450 | G7: Los puntos cambian de persona
A8: 29 | B8: Planta 6/7 | C8: Ruben Alejandro Siller Valverde | D8: Ruben Siller | E8: 3055539 | F8: 450 | G8: Solo se corrigió la escritura del nombre
A9: 31 | B9: Planta 1 | C9: Diana Themis Zacanelles Orta | D9: Eduardo Gonzalez | E9: 3029246 | F9: 450 | G9: Los puntos cambian de persona
A10: 66 | B10: Planta 2 | C10: Anayeli Rivera | D10: Anayeli Rivera Callejas | E10: 3031203 | F10: 450 | G10: Solo se corrigió la escritura del nombre
A11: 72 | B11: Planta 3/4 | C11: Erik Aguirre Ramirez | D11: Erik Javier Aguirre Ramirez | E11: 3044202 | F11: 450 | G11: Los puntos cambian de persona | H11: Líder = quien ejecutó (criterio confirmado): coincide con quien registró
A12: 82 | B12: Planta 2 | C12: Monica Arcelia Sifuentes Ortiz | D12: Gerardo del Angel Zarate | E12: 3026520 | F12: 450 | G12: Los puntos cambian de persona
A13: 87 | B13: Planta 3/4 | C13: Fernando Gonzalez | D13: Fernando Gonzalez Delgado | E13: 3054279 | F13: 450 | G13: Solo se corrigió la escritura del nombre
A14: 94 | B14: Planta 1 | C14: Fannie Grettelle Aguilar Valero | D14: Fannie Aguilar | E14: 3053215 | F14: 450 | G14: Solo se corrigió la escritura del nombre
A15: 96 | B15: Planta 2 | C15: Francisco Daniel Charles Sanchez | D15: Francisco Daniel Charles Sanchez | E15: 3062322 | F15: 450 | G15: Los puntos cambian de persona | H15: Líder = quien ejecutó (criterio confirmado): coincide con quien registró
A16: 30 | B16: Planta 1 | C16: Jose Gerardo Gudiño Ruiz | D16: Gerardo Gudiño Ruiz | E16: 3058416 | F16: 400 | G16: Los puntos cambian de persona
A17: 42 | B17: Planta 3/4 | C17: Omar Alejandro Alvarez Charles | D17: Omar Alvarez | E17: 3067714 | F17: 400 | G17: Solo se corrigió la escritura del nombre
A18: 45 | B18: Planta 6/7 | C18: Adrian Rodrigues Campos | D18: Adrian Rodriguez Campos | E18: 3061108 | F18: 400 | G18: Solo se corrigió la escritura del nombre | H18: Mismo # de empleado en ambos registros; confirmar apellido correcto.
A19: 61 | B19: Planta 3/4 | C19: Omar Alejandro Alvarez Charles | D19: Omar Alvarez | E19: 3067714 | F19: 400 | G19: Solo se corrigió la escritura del nombre
A20: 93 | B20: Planta 2 | C20: Hector Jaziel Martinez | D20: Jaziel Mancilla | E20: 3026189 | F20: 400 | G20: Solo se corrigió la escritura del nombre | H20: Mismo # de empleado en ambos registros; confirmar apellido correcto.
A21: 10 | B21: Planta 2 | C21: Carlos Lozano | D21: Juan Carlos Guerrero Lozano | E21: 3038990 | F21: 300 | G21: Los puntos cambian de persona
A22: 11 | B22: Planta 2 | C22: Monica Arcelia Sifuentes Ortiz | D22: Monica Sifuentes Ortiz | E22: 3065185 | F22: 300 | G22: Solo se corrigió la escritura del nombre
A23: 24 | B23: Planta 1 | C23: Mariana Valencia | D23: Jose Isai Tostado Beltran | E23: 3024217 | F23: 300 | G23: Los puntos cambian de persona
A24: 26 | B24: Planta 1 | C24: Ulises Eduardo Hernandez Perez | D24: Ulises Hernandez | E24: 3055561 | F24: 300 | G24: Solo se corrigió la escritura del nombre
A25: 33 | B25: Planta 2 | C25: Francisco Hernandez | D25: Francisco Hernandez Ramirez | E25: 3055346 | F25: 300 | G25: Solo se corrigió la escritura del nombre
A26: 34 | B26: Planta 2 | C26: Monica Arcelia Sifuentes Ortiz | D26: Monica Sifuentes Ortiz | E26: 3065185 | F26: 300 | G26: Solo se corrigió la escritura del nombre
A27: 46 | B27: Planta 6/7 | C27: Berenice Esquivel Delgadillo | D27: Berenice Esquivel | E27: 3027573 | F27: 300 | G27: Solo se corrigió la escritura del nombre
A28: 51 | B28: Parras | C28: Fernanda Monserrath Vielma Zavala | D28: Luis Reyes | E28: 3066350 | F28: 300 | G28: Los puntos cambian de persona
A29: 53 | B29: Planta 3/4 | C29: Karla Guadalupe Padilla Gonzalez | D29: Marco Rodríguez | E29: 3030351 | F29: 300 | G29: Los puntos cambian de persona
A30: 54 | B30: Planta 1 | C30: Ensamble Produccion | D30: Citlali Nalleli Garza Hernandez | E30: 3042836 | F30: 300 | G30: Los puntos cambian de persona
A31: 57 | B31: Planta 2 | C31: Jose Emmanuel Alejo Wong | D31: Federico Alberto Obispo Florencio | E31: 3039850 | F31: 300 | G31: Los puntos cambian de persona
A32: 58 | B32: Planta 2 | C32: Hector Jaziel Martinez | D32: Jaziel Mancilla | E32: 3026189 | F32: 300 | G32: Solo se corrigió la escritura del nombre | H32: Mismo # de empleado en ambos registros; confirmar apellido correcto.
A33: 59 | B33: Planta 2 | C33: Hector Jaziel Martinez | D33: Jaziel Mancilla | E33: 3026189 | F33: 300 | G33: Solo se corrigió la escritura del nombre | H33: Mismo # de empleado en ambos registros; confirmar apellido correcto.
A34: 62 | B34: Planta 6/7 | C34: Gustavo Vargas Quiroz | D34: Gustavo Vargas | E34: 3061983 | F34: 300 | G34: Solo se corrigió la escritura del nombre
A35: 63 | B35: Planta 1 | C35: Miguel Eduardo Villegas Prieto | D35: Miguel Villegas | E35: 3055580 | F35: 300 | G35: Solo se corrigió la escritura del nombre
A36: 68 | B36: Planta 2 | C36: Francisco Hernandez | D36: Francisco Hernandez Ramirez | E36: 3055346 | F36: 300 | G36: Solo se corrigió la escritura del nombre
A37: 69 | B37: Planta 1 | C37: Diana Themis Zacanelles Orta | D37: Eduardo Gonzalez | E37: 3029246 | F37: 300 | G37: Los puntos cambian de persona
A38: 74 | B38: Planta 6/7 | C38: Eduardo Morales Rodriguez | D38: Alejandro Caseres | E38: 3031856 | F38: 300 | G38: Los puntos cambian de persona
A39: 78 | B39: Planta 1 | C39: Jose Ignacio Arias Palacios | D39: Nestor Estrada | E39: 3044346 | F39: 300 | G39: Los puntos cambian de persona
A40: 79 | B40: Planta 1 | C40: Ensamble Produccion | D40: Luis Gerardo Rivera Salazar | E40: 1680380 | F40: 300 | G40: Los puntos cambian de persona
A41: 86 | B41: Parras | C41: Brandon Ramon Cano Resendez | D41: Hugo Alcalá | E41: 3056806 | F41: 300 | G41: Los puntos cambian de persona
A42: 99 | B42: Planta 3/4 | C42: Guillermo Garcia | D42: Erik Ovalle | E42: 1705611 | F42: 250 | G42: Los puntos cambian de persona
A43: 8 | B43: Planta 2 | C43: Francisco Hernandez | D43: Francisco Hernandez Ramirez | E43: 3055346 | F43: 200 | G43: Solo se corrigió la escritura del nombre
A44: 23 | B44: Planta 1 | C44: Fannie Grettelle Aguilar Valero | D44: Emiliano Zuñiga | E44: 3063949 | F44: 200 | G44: Los puntos cambian de persona
A45: 36 | B45: Planta 2 | C45: Carlos Lozano | D45: Juan Carlos Guerrero Lozano | E45: 3038990 | F45: 200 | G45: Los puntos cambian de persona
... A62: 97 | B62: Planta 1 | C62: Salome Dominguez | D62: Arsenio E Vazquez | E62: 3030820 | F62: 150 | G62: Los puntos cambian de persona
A63: 14 | B63: Planta 6/7 | C63: Fernanda Monserrath Vielma Zavala | D63: (líder no identificado) | E63: 3062914 | F63: 100 | G63: Pendiente | H63: El Form trae "Optimización del area de trabajo" en lugar de un nombre. Nómina 3062914.
A64: 35 | B64: Planta 1 | C64: Gerardo Rodriguez | D64: Gerardo Rodriguez Garay | E64: 1616978 | F64: 100 | G64: Solo se corrigió la escritura del nombre
A65: 37 | B65: Planta 6/7 | C65: Jennifer Garcia Gregorio | D65: Hector Velasco | E65: 3035216 | F65: 100 | G65: Los puntos cambian de persona
A66: 49 | B66: Planta 3/4 | C66: Guillermo Garcia | D66: Erik Ovalle | E66: 1705611 | F66: 100 | G66: Los puntos cambian de persona
A67: 70 | B67: Planta 1 | C67: Diego Valencia Alcazar | D67: Diego Valencia | E67: 3062213 | F67: 100 | G67: Solo se corrigió la escritura del nombre
A68: 71 | B68: Planta 1 | C68: Ulises Eduardo Hernandez Perez | D68: Ulises Hernandez | E68: 3055561 | F68: 100 | G68: Solo se corrigió la escritura del nombre
A69: 92 | B69: Planta 2 | C69: Hector Jaziel Martinez | D69: Jaziel Mancilla | E69: 3026189 | F69: 100 | G69: Solo se corrigió la escritura del nombre | H69: Mismo # de empleado en ambos registros; confirmar apellido correcto.
A70: 98 | B70: Planta 3/4 | C70: Guillermo Garcia | D70: Erik Ovalle | E70: 1705611 | F70: 100 | G70: Los puntos cambian de persona
A72: Total de kaizenes cuyos puntos cambian de persona: 38 | solo corrección de nombre: 27

Sheet Nuevos (provisional)
A1: NUEVOS KAIZEN (carpeta Question (1)) — EVALUACIÓN PROVISIONAL
A2: Provisional: planta/depto/líder salen de los archivos, no del Form (el concentrado está desactualizado). Impacto y alcance son mi lectura del archivo. No se han subido al dashboard. 'Cuenta' = Sí / Dudoso / No.
A4: ID | B4: Autor del archivo | C4: Planta / Depto | D4: Kaizen | E4: Líder / firmantes (por confirmar) | F4: Fecha impl. | G4: Estatus | H4: Indicador | I4: IMPACTO | J4: ALCANCE | K4: Ahorro declarado MXN (informativo) | L4: Pts matriz | M4: Bono seg. | N4: TOTAL (si Cuenta=Sí) | O4: Cuenta | P4: Banderas
A5: N01 | B5: Héctor Jaziel Martín | C5: P2 Producción | D5: Ayuda visual de atrapamiento en prensas de tela | E5: Mauricio Ramírez | F5: 2026-09-28 | G5: Implementado | H5: Seguridad | I5: 3 | J5: 1 | L5: =INDEX(Matriz!$C$7:$E$9,I5,J5) -> 150 | M5: =IF(ISNUMBER(SEARCH("Seguridad",H5)),Matriz!$C$20,0) -> 100 | N5: =IF(O5="Sí",L5+MIN(M5,Matriz!$C$24),0) -> 250 | O5: Sí | P5: [CARGADO al Excel y dashboard] Actividades copiadas de otra plantilla (humidificador); beneficios vacíos
A6: N02 | B6: Héctor Jaziel Martín | C6: P2 Producción (Frame) | D6: Pokayoke de posición de pieza en prensas | E6: Jaziel Mancilla | F6: 2026-09-28 | G6: Implementado | H6: FTQ | I6: 3 | J6: 1 | L6: =INDEX(Matriz!$C$7:$E$9,I6,J6) -> 150 | M6: =IF(ISNUMBER(SEARCH("Seguridad",H6)),Matriz!$C$20,0) -> 0 | N6: =IF(O6="Sí",L6+MIN(M6,Matriz!$C$24),0) -> 150 | O6: Sí | P6: [CARGADO al Excel y dashboard] Evita daño a tarjeta electrónica; sin datos antes/después. Misma nómina que Héctor Jaziel (por aclarar)
A7: N03 | B7: Rubén Siller | C7: P6-7 RH | D7: Onboarding nuevo ingreso nivel operativo | E7: Rubén Siller | F7: 2026-08-31 | G7: Implementado | H7: Tiempo | I7: 2 | J7: 3 | L7: =INDEX(Matriz!$C$7:$E$9,I7,J7) -> 300 | M7: =IF(ISNUMBER(SEARCH("Seguridad",H7)),Matriz!$C$20,0) -> 0 | N7: =IF(O7="Sí",L7+MIN(M7,Matriz!$C$24),0) -> 0 | O7: Dudoso | P7: [CARGADO, marcado amarillo en Evaluación] Fecha de agosto (otra celda marca 9-jul): fuera de septiembre
A8: N04 | B8: Eduardo Morales | C8: P7 PIP | D8: Incremento de piezas por turno (100 → 350) | E8: Diego Briones (implementó) | F8: 2026-09-21 | G8: Implementado | H8: Eficiencia | I8: 2 | J8: 1 | L8: =INDEX(Matriz!$C$7:$E$9,I8,J8) -> 100 | M8: =IF(ISNUMBER(SEARCH("Seguridad",H8)),Matriz!$C$20,0) -> 0 | N8: =IF(O8="Sí",L8+MIN(M8,Matriz!$C$24),0) -> 100 | O8: Sí | P8: [CARGADO al Excel y dashboard] +250% sin evidencia del método; firma de supervisor vacía
A9: N05 | B9: Tania Lira | C9: Logística (todas) | D9: Ahorro ruta Puerto de Altamira | E9: Hiram González / Jesús Guajardo | F9: Julio | G9: Implementado (¿?) | H9: Ahorro | I9: 3 | J9: 3 | L9: =INDEX(Matriz!$C$7:$E$9,I9,J9) -> 450 | M9: =IF(ISNUMBER(SEARCH("Seguridad",H9)),Matriz!$C$20,0) -> 0 | N9: =IF(O9="Sí",L9+MIN(M9,Matriz!$C$24),0) -> 0 | O9: Dudoso | P9: [CARGADO, marcado amarillo en Evaluación] Narrativa 14,400 USD/año vs tabla 1,200 MXN en 3 meses; fecha 'Julio'
A10: N06 | B10: Omar Alvarez | C10: P4 Materiales | D10: Guarda para grapadora | E10: Omar Alvarez | F10: 2026-10-01 | G10: Implementado | H10: Seguridad | I10: 3 | J10: 1 | L10: =INDEX(Matriz!$C$7:$E$9,I10,J10) -> 150 | M10: =IF(ISNUMBER(SEARCH("Seguridad",H10)),Matriz!$C$20,0) -> 100 | N10: =IF(O10="Sí",L10+MIN(M10,Matriz!$C$24),0) -> 250 | O10: Sí | P10: [CARGADO al Excel y dashboard] Fecha de implementación en octubre
A11: N07 | B11: Saúl Gallegos | C11: P2 Mantenimiento | D11: Tapete dieléctrico para tableros eléctricos | E11: Saúl Gallegos | G11: Implementado (sin fecha) | H11: Seguridad | I11: 3 | J11: 1 | L11: =INDEX(Matriz!$C$7:$E$9,I11,J11) -> 150 | M11: =IF(ISNUMBER(SEARCH("Seguridad",H11)),Matriz!$C$20,0) -> 100 | N11: =IF(O11="Sí",L11+MIN(M11,Matriz!$C$24),0) -> 0 | O11: Dudoso | P11: [CARGADO, marcado amarillo en Evaluación] Sin fechas; costo 750 MXN
A12: N08 | B12: Anayeli Rivera | C12: P2 Calidad proveedores | D12: Rebabeadores (reduce retrabajo) | E12: Anayeli Rivera | F12: 2026-09-22 | G12: Implementado | H12: Scrap | I12: 3 | J12: 1 | L12: =INDEX(Matriz!$C$7:$E$9,I12,J12) -> 150 | M12: =IF(ISNUMBER(SEARCH("Seguridad",H12)),Matriz!$C$20,0) -> 0 | N12: =IF(O12="Sí",L12+MIN(M12,Matriz!$C$24),0) -> 150 | O12: Sí | P12: [CARGADO al Excel y dashboard] Retrabajo 36 → 2; sin ahorro monetizado
A13: N09 | B13: Luis Veloz | C13: Parras Materiales | D13: Ubicaciones de material en planta | E13: Luis Veloz | G13: Sin fecha | H13: Tiempo | I13: 2 | J13: 2 | L13: =INDEX(Matriz!$C$7:$E$9,I13,J13) -> 200 | M13: =IF(ISNUMBER(SEARCH("Seguridad",H13)),Matriz!$C$20,0) -> 0 | N13: =IF(O13="Sí",L13+MIN(M13,Matriz!$C$24),0) -> 0 | O13: Dudoso | P13: [CARGADO, marcado amarillo en Evaluación] Sin fechas; búsqueda 10 → 6 min
A14: N10 | B14: Isaac Arámbulo | C14: P4 Lanzamientos | D14: Referencia en costura de elástico en toe kick | E14: Isaac Arámbulo (sup.) | F14: 2026-09-30 | G14: Implementado | H14: FTQ | I14: 3 | J14: 1 | L14: =INDEX(Matriz!$C$7:$E$9,I14,J14) -> 150 | M14: =IF(ISNUMBER(SEARCH("Seguridad",H14)),Matriz!$C$20,0) -> 0 | N14: =IF(O14="Sí",L14+MIN(M14,Matriz!$C$24),0) -> 150 | O14: Sí | P14: [CARGADO al Excel y dashboard] Beneficio cualitativo (evitar reclamo)
A15: N11 | B15: Jorge Zertuche | C15: P4 Materiales | D15: Empaque planta 4 (lugar para cartón) | E15: Juan Medrano | F15: 2026-09-26 | G15: Implementado | H15: Tiempo muerto | I15: 2 | J15: 1 | L15: =INDEX(Matriz!$C$7:$E$9,I15,J15) -> 100 | M15: =IF(ISNUMBER(SEARCH("Seguridad",H15)),Matriz!$C$20,0) -> 0 | N15: =IF(O15="Sí",L15+MIN(M15,Matriz!$C$24),0) -> 100 | O15: Sí | P15: [CARGADO al Excel y dashboard] Beneficios sin cifras ('TBD')
A16: N12 | B16: Fernando Rodríguez | C16: P1 Cuarto de batería | D16: Lavaojos y extintor | E16: Fernando Rodríguez | F16: 2026-09-21 | G16: Implementado | H16: Seguridad | I16: 3 | J16: 1 | L16: =INDEX(Matriz!$C$7:$E$9,I16,J16) -> 150 | M16: =IF(ISNUMBER(SEARCH("Seguridad",H16)),Matriz!$C$20,0) -> 100 | N16: =IF(O16="Sí",L16+MIN(M16,Matriz!$C$24),0) -> 250 | O16: Sí | P16: [CARGADO al Excel y dashboard] Cumplimiento NOM-005/002 STPS
A17: N13 | B17: Sergio Zuñiga | C17: (sin dato) | D17: (sin título) | E17: Sergio Zuñiga | F17: 2026-10-30 | G17: Planeado | H17: — | I17: 1 | J17: 1 | L17: =INDEX(Matriz!$C$7:$E$9,I17,J17) -> 50 | M17: =IF(ISNUMBER(SEARCH("Seguridad",H17)),Matriz!$C$20,0) -> 0 | N17: =IF(O17="Sí",L17+MIN(M17,Matriz!$C$24),0) -> 0 | O17: No | P17: [NO CARGADO: no implementado] Fecha de fin 30-oct: aún no implementado
A18: N14 | B18: Karla Padilla | C18: P4 Mantenimiento | D18: Pokayoke bracket (Rivian HL) | E18: Rafael Rodríguez / Valentín Alvarado | F18: 2026-09-23 | G18: Implementado | H18: Scrap | I18: 3 | J18: 2 | K18: 332865 | L18: =INDEX(Matriz!$C$7:$E$9,I18,J18) -> 300 | M18: =IF(ISNUMBER(SEARCH("Seguridad",H18)),Matriz!$C$20,0) -> 0 | N18: =IF(O18="Sí",L18+MIN(M18,Matriz!$C$24),0) -> 300 | O18: Sí | P18: [CARGADO al Excel y dashboard] 19,580 USD (declarado B 19,850 vs 19,580); periodo no declarado; ventana post-impl. de pocos días; USD −76% vs PPM −35%
A19: N15 | B19: Erik Aguirre | C19: P3-4 RH | D19: Automatización de RH por WhatsApp | E19: Erik Aguirre | F19: 2026-10-23 | G19: Piloto planeado | H19: Otro | I19: 1 | J19: 3 | L19: =INDEX(Matriz!$C$7:$E$9,I19,J19) -> 150 | M19: =IF(ISNUMBER(SEARCH("Seguridad",H19)),Matriz!$C$20,0) -> 0 | N19: =IF(O19="Sí",L19+MIN(M19,Matriz!$C$24),0) -> 0 | O19: No | P19: [NO CARGADO: no implementado] Meta al 23-oct; todo 'por medir/por cotizar'
A20: N16 | B20: Christian Escobedo | C20: P6 Línea 12 | D20: Dispositivo de inspección Notch T1XX | E20: Enrique Ramos (sup.) | F20: 2026-09-25 | G20: Implementado | H20: FTQ | I20: 3 | J20: 1 | L20: =INDEX(Matriz!$C$7:$E$9,I20,J20) -> 150 | M20: =IF(ISNUMBER(SEARCH("Seguridad",H20)),Matriz!$C$20,0) -> 0 | N20: =IF(O20="Sí",L20+MIN(M20,Matriz!$C$24),0) -> 150 | O20: Sí | P20: [CARGADO al Excel y dashboard] Sin costo
A21: N17 | B21: Héctor Velasco | C21: P6 Frame T1XX RR | D21: Elevar altura de dispositivo de frame | E21: Enrique Ramos (sup.) | F21: 2026-09-25 | G21: Implementado | H21: Ergonomía | I21: 2 | J21: 1 | L21: =INDEX(Matriz!$C$7:$E$9,I21,J21) -> 100 | M21: =IF(ISNUMBER(SEARCH("Seguridad",H21)),Matriz!$C$20,0) -> 0 | N21: =IF(O21="Sí",L21+MIN(M21,Matriz!$C$24),0) -> 100 | O21: Sí | P21: [CARGADO al Excel y dashboard] Inicio 29-ago, fin 25-sep; sin datos del beneficio
A22: N18 | B22: Fernanda Monserrath | C22: Parras Laminado | D22: Parámetros óptimos de laminado (DOE) | E22: Isaac Olvera / Carlos Rodríguez | F22: 2026-09-30 | G22: Implementado | H22: Scrap | I22: 3 | J22: 2 | K22: 460938 | L22: =INDEX(Matriz!$C$7:$E$9,I22,J22) -> 300 | M22: =IF(ISNUMBER(SEARCH("Seguridad",H22)),Matriz!$C$20,0) -> 0 | N22: =IF(O22="Sí",L22+MIN(M22,Matriz!$C$24),0) -> 300 | O22: Sí | P22: [CARGADO al Excel y dashboard] 27,114 USD; periodo no declarado; DOE/SPC sin soporte; USD −76% vs PPM −35%
A23: N19 | B23: Daniel Parra | C23: Parras SCI | D23: Eficiencia del sistema contra incendios | E23: Daniel Parra | F23: 2026-09-26 | G23: Implementado | H23: Seguridad | I23: 3 | J23: 1 | L23: =INDEX(Matriz!$C$7:$E$9,I23,J23) -> 150 | M23: =IF(ISNUMBER(SEARCH("Seguridad",H23)),Matriz!$C$20,0) -> 100 | N23: =IF(O23="Sí",L23+MIN(M23,Matriz!$C$24),0) -> 250 | O23: Sí | P23: [CARGADO al Excel y dashboard] Alcance por confirmar (podría ser planta)
A24: N20 | B24: José Carlos Herrera | C24: P2 Calidad | D24: Control maestro de alertas de calidad | E24: José Carlos Herrera | F24: 2026-09-30 | G24: Implementado | H24: Tiempo | I24: 2 | J24: 2 | L24: =INDEX(Matriz!$C$7:$E$9,I24,J24) -> 200 | M24: =IF(ISNUMBER(SEARCH("Seguridad",H24)),Matriz!$C$20,0) -> 0 | N24: =IF(O24="Sí",L24+MIN(M24,Matriz!$C$24),0) -> 200 | O24: Sí | P24: [CARGADO al Excel y dashboard] 25 → 5 min por llenado
A25: N21 | B25: Mario Alvarado | C25: P7 Mantenimiento | D25: Prevención de daños al inyector | E25: Mario Alvarado | F25: 2026-09-21 | G25: Implementado | H25: Tiempo muerto | I25: 2 | J25: 1 | L25: =INDEX(Matriz!$C$7:$E$9,I25,J25) -> 100 | M25: =IF(ISNUMBER(SEARCH("Seguridad",H25)),Matriz!$C$20,0) -> 0 | N25: =IF(O25="Sí",L25+MIN(M25,Matriz!$C$24),0) -> 100 | O25: Sí | P25: [CARGADO al Excel y dashboard] Sin cifras ni indicador
A26: N22 | B26: Guadalupe Arriaga | C26: P6-7 Materiales | D26: Confiabilidad en inventario | E26: Ricardo Reyna | F26: 2026-01-02 | G26: Implementado (¿?) | H26: Tiempo | I26: 2 | J26: 2 | L26: =INDEX(Matriz!$C$7:$E$9,I26,J26) -> 200 | M26: =IF(ISNUMBER(SEARCH("Seguridad",H26)),Matriz!$C$20,0) -> 0 | N26: =IF(O26="Sí",L26+MIN(M26,Matriz!$C$24),0) -> 0 | O26: Dudoso | P26: [CARGADO, marcado amarillo en Evaluación] Fechas = 2-4 ene 2026 (¿error de captura?)
A27: N23 | B27: Francisco Hernández | C27: Lanzamientos | D27: Dispositivo de funcionalidad | E27: Enrique Cervantes | F27: 2026-09-13 | G27: Implementado | H27: FTQ | I27: 3 | J27: 1 | L27: =INDEX(Matriz!$C$7:$E$9,I27,J27) -> 150 | M27: =IF(ISNUMBER(SEARCH("Seguridad",H27)),Matriz!$C$20,0) -> 0 | N27: =IF(O27="Sí",L27+MIN(M27,Matriz!$C$24),0) -> 150 | O27: Sí | P27: [CARGADO al Excel y dashboard] Sin cifras
A28: N24 | B28: Felipe Guerrero | C28: P2 Mantenimiento | D28: Rediseño y ampliación de infraestructura | E28: Luis Carlos Ruiz | F28: 2026-12-01 | G28: Planeado | H28: — | I28: 1 | J28: 2 | L28: =INDEX(Matriz!$C$7:$E$9,I28,J28) -> 100 | M28: =IF(ISNUMBER(SEARCH("Seguridad",H28)),Matriz!$C$20,0) -> 0 | N28: =IF(O28="Sí",L28+MIN(M28,Matriz!$C$24),0) -> 0 | O28: No | P28: [NO CARGADO: no implementado] Cierre en diciembre
A29: N25 | B29: Felipe Guerrero | C29: P2 Mantenimiento | D29: Rediseño del sistema de guardas | E29: Luis Carlos Ruiz | F29: 2026-09-30 | G29: Implementado | H29: Seguridad | I29: 3 | J29: 2 | L29: =INDEX(Matriz!$C$7:$E$9,I29,J29) -> 300 | M29: =IF(ISNUMBER(SEARCH("Seguridad",H29)),Matriz!$C$20,0) -> 100 | N29: =IF(O29="Sí",L29+MIN(M29,Matriz!$C$24),0) -> 400 | O29: Sí | P29: [CARGADO al Excel y dashboard] Alcance por confirmar
A30: N26 | B30: Giovani Hernández | C30: P2 Materiales | D30: Ahorro de costos (uso de pe…) | E30: Giovani Hernández | F30: 2026-09-01 | G30: Implementado (¿?) | H30: Ahorro | I30: 3 | J30: 1 | L30: =INDEX(Matriz!$C$7:$E$9,I30,J30) -> 150 | M30: =IF(ISNUMBER(SEARCH("Seguridad",H30)),Matriz!$C$20,0) -> 0 | N30: =IF(O30="Sí",L30+MIN(M30,Matriz!$C$24),0) -> 0 | O30: Dudoso | P30: [CARGADO, marcado amarillo en Evaluación] 14,000 sin moneda ni periodo; fechas 30-jun/1-sep
A31: N27 | B31: Mariana Valencia | C31: P1 Moldeo | D31: Herramental para toma de piezas | E31: Sergio Velázquez / Isai Tostado | F31: 2026-05-09 | G31: Implementado (¿?) | H31: Tiempo | I31: 2 | J31: 1 | L31: =INDEX(Matriz!$C$7:$E$9,I31,J31) -> 100 | M31: =IF(ISNUMBER(SEARCH("Seguridad",H31)),Matriz!$C$20,0) -> 0 | N31: =IF(O31="Sí",L31+MIN(M31,Matriz!$C$24),0) -> 0 | O31: Dudoso | P31: [CARGADO, marcado amarillo en Evaluación] Fecha 9-may; '115→120 pzs' vs '+30 %' no cuadra
A32: N28 | B32: Karina Flores | C32: Parras Compras | D32: Arranque de almacén MRO | E32: Gerardo Brondo | F32: 2026-01-04 | G32: Implementado (¿?) | H32: Ahorro | I32: 3 | J32: 2 | L32: =INDEX(Matriz!$C$7:$E$9,I32,J32) -> 300 | M32: =IF(ISNUMBER(SEARCH("Seguridad",H32)),Matriz!$C$20,0) -> 0 | N32: =IF(O32="Sí",L32+MIN(M32,Matriz!$C$24),0) -> 0 | O32: Dudoso | P32: [CARGADO, marcado amarillo en Evaluación] Fechas 2-4 ene 2026; ahorro en 'EA' (304,000), sin MXN
A33: N29 | B33: Mónica Sifuentes | C33: P2 RH | D33: Reducción de rutas de fin de semana (18 → 15) | E33: A. Guzmán | F33: 2026-09-19 | G33: Implementado | H33: Ahorro | I33: 3 | J33: 2 | K33: 9942 | L33: =INDEX(Matriz!$C$7:$E$9,I33,J33) -> 300 | M33: =IF(ISNUMBER(SEARCH("Seguridad",H33)),Matriz!$C$20,0) -> 0 | N33: =IF(O33="Sí",L33+MIN(M33,Matriz!$C$24),0) -> 300 | O33: Sí | P33: [CARGADO al Excel y dashboard] B/C 1.2; periodo del ahorro no declarado
A34: N30 | B34: José Arias | C34: Mtto Ensamble (RF-07 LH) | D34: Nidos nuevos en acero Toolox 44 | E34: Ricardo Perales / Daniel Galván | F34: 2026-09-05 | G34: Implementado | H34: Scrap | I34: 3 | J34: 1 | L34: =INDEX(Matriz!$C$7:$E$9,I34,J34) -> 150 | M34: =IF(ISNUMBER(SEARCH("Seguridad",H34)),Matriz!$C$20,0) -> 0 | N34: =IF(O34="Sí",L34+MIN(M34,Matriz!$C$24),0) -> 150 | O34: Sí | P34: [CARGADO, marcado amarillo en Evaluación] '2,800 por cada pieza' sin periodo ni volumen
A35: N31 | B35: Mariana Rangel | C35: Materiales | D35: Mesas de planchado (hoja oculta) | E35: Diana Ramos / Miguel Ramos | F35: 2026-06-18 | G35: Implementado (¿?) | H35: Seguridad | I35: 3 | J35: 1 | L35: =INDEX(Matriz!$C$7:$E$9,I35,J35) -> 150 | M35: =IF(ISNUMBER(SEARCH("Seguridad",H35)),Matriz!$C$20,0) -> 100 | N35: =IF(O35="Sí",L35+MIN(M35,Matriz!$C$24),0) -> 0 | O35: Dudoso | P35: [CARGADO, marcado amarillo en Evaluación] Hoja oculta; fecha 18-jun
A36: N32 | B36: Mariana Rangel | C36: Materiales | D36: Claxon y señalización para patines (hoja oculta) | E36: Diana Ramos / Miguel Ramos | F36: 2026-06-18 | G36: Implementado (¿?) | H36: Seguridad | I36: 3 | J36: 1 | L36: =INDEX(Matriz!$C$7:$E$9,I36,J36) -> 150 | M36: =IF(ISNUMBER(SEARCH("Seguridad",H36)),Matriz!$C$20,0) -> 100 | N36: =IF(O36="Sí",L36+MIN(M36,Matriz!$C$24),0) -> 0 | O36: Dudoso | P36: [CARGADO, marcado amarillo en Evaluación] Hoja oculta; fecha 18-jun
A37: N33 | B37: Mariana Rangel | C37: Materiales | D37: Manejo de químico: resguardo en gabinete | E37: (sin líder) | F37: 2026-09-30 | G37: Implementado | H37: Orden | I37: 2 | J37: 1 | L37: =INDEX(Matriz!$C$7:$E$9,I37,J37) -> 100 | M37: =IF(ISNUMBER(SEARCH("Seguridad",H37)),Matriz!$C$20,0) -> 0 | N37: =IF(O37="Sí",L37+MIN(M37,Matriz!$C$24),0) -> 100 | O37: Sí | P37: [CARGADO, marcado amarillo en Evaluación] Sin firmas; sin cifras
A38: N34 | B38: Yadira González | C38: P1 Ensamble | D38: Ayuda visual de corte homologado de tela | E38: Marco Arellano / Carlos Palacios | F38: 2026-09-29 | G38: Implementado | H38: Scrap | I38: 3 | J38: 1 | L38: =INDEX(Matriz!$C$7:$E$9,I38,J38) -> 150 | M38: =IF(ISNUMBER(SEARCH("Seguridad",H38)),Matriz!$C$20,0) -> 0 | N38: =IF(O38="Sí",L38+MIN(M38,Matriz!$C$24),0) -> 150 | O38: Sí | P38: [CARGADO al Excel y dashboard] No agregado a ODS aún
A39: N35 | B39: Alfonso Rosales | C39: Materiales | D39: Racks por frecuencia de uso | E39: Oswaldo Casillas / Christian Bravo | F39: 2026-09-21 | G39: Implementado | H39: 5S | I39: 1 | J39: 2 | L39: =INDEX(Matriz!$C$7:$E$9,I39,J39) -> 100 | M39: =IF(ISNUMBER(SEARCH("Seguridad",H39)),Matriz!$C$20,0) -> 0 | N39: =IF(O39="Sí",L39+MIN(M39,Matriz!$C$24),0) -> 100 | O39: Sí | P39: [CARGADO, marcado amarillo en Evaluación] Sin cifras
A40: N36 | B40: Adrián Rodríguez | C40: P7 PIP/Foam | D40: Eliminación de nube de cera (extractores) | E40: Manuel Lara (implementó) / Víctor de la Torre (sup.) | F40: 2026-09-30 | G40: Implementado | H40: Seguridad | I40: 3 | J40: 1 | K40: 100000 | L40: =INDEX(Matriz!$C$7:$E$9,I40,J40) -> 150 | M40: =IF(ISNUMBER(SEARCH("Seguridad",H40)),Matriz!$C$20,0) -> 100 | N40: =IF(O40="Sí",L40+MIN(M40,Matriz!$C$24),0) -> 250 | O40: Sí | P40: [CARGADO al Excel y dashboard] B 72-200 mil (rango), costo 100,000, ahorro '100,00' mal capturado; actividades fechadas en enero
D42: Total provisional (solo Sí) | N42: =SUM(N5:N40) -> 4400
D43: Registros Sí / Dudoso / No | N43: =COUNTIF(O5:O40,"Sí")&" / "&COUNTIF(O5:O40,"Dudoso")&" / "&COUNTIF(O5:O40,"No") -> 23 / 10 / 3

Sheet Revisar
A1: REGISTROS QUE NECESITAN TU DECISIÓN
A2: No los evalué a ciegas. Decide y ajusta impacto/alcance en la hoja Evaluación.
A4: ID | B4: Persona | C4: Planta | D4: Qué encontré | E4: Acción sugerida | F4: Problema | G4: Mejora
A5: 1 | B5: Genet Campos | C5: Planta 1 | D5: Registro de prueba del administrador (texto 'df','sd') | E5: EXCLUIR | F5: sd | G5: df
A6: 2 | B6: Karina Guadalupe Flores Gonzalez | C6: Parras | D6: Descripción de la mejora vacía ('.') | E6: Pedir descripción | F6: Negociación en costo por recoleccion | G6: .
A7: 3 | B7: Idalia Recio | C7: Planta 3/4 | D7: Indicador dice 'Medio Ambiente' pero la mejora es de método/eficiencia | E7: Corregir indicador | F7: Auditores de LPAs realizan su auditoria de proceso con un formato incorrecto. El cual se les rechaza, ya que no cumple con el programa a auditar correcto y nivel o capa correcto y se tiene que volver a realizar en el formato correcto. | G7: Incluir en el correo de comunicación de LPAs el link del formato correcto a utilizar para descargarlo con un solo clic
A8: 21 | B8: Arsenio Vazquez | C8: Planta 1 | D8: Contenido inválido: problema='Mexico', mejora=correo electrónico | E8: EXCLUIR o recapturar | F8: Mexico | G8: evazquez@daimayus.com
A9: 25 | B9: Jose Gerardo Gudiño Ruiz | C9: Planta 1 | D9: La descripción trae un correo pegado antes del texto | E9: Limpiar texto | F9: No se tenia espejo concavo en DQMC Moldeo | G9: jgudino@daimayus.comNo se tenia visibilidad efectiva en el área, y se opto por colocar un espejo concavo para mejorar la visibiidad del transito y eliminar el riesgo de accidentes por equipo motorizado
A10: 28 | B10: Luis Gustavo Garcia Fuentes | C10: Planta 1 | D10: Descripción muy pobre para justificar puntos ('Ahorro en cambio de proveedor') | E10: Pedir detalle + monto | F10: Compra de material directo | G10: Ahorro en cambio de proveedor
A11: 39 | B11: Alejandro Lopez Lopez | C11: Planta 3/4 | D11: Descripción circular ('Se digitaliza el reporte' = el problema) | E11: Pedir detalle | F11: Se digitaliza proceso de reporte de transporte | G11: Se digitaliza el reporte de transporte
A12: 46 | B12: Berenice Esquivel Delgadillo | C12: Planta 6/7 | D12: Parece contención/recuperación, no mejora permanente | E12: Validar si es Kaizen | F12: Recuperacion de componentes por daño de maquina | G12: Se realiza el desensamble de la pieza para recuperar componentes
A13: 51 | B13: Fernanda Monserrath Vielma Zavala | C13: Parras | D13: Redactado como 'Evaluar el cambio' — ¿ya se implementó? | E13: Confirmar implementación | F13: material de 1mm se identifica OM para la alineacion durante el cerrado y la costura de alrededor | G13: Evaluar el cambio de material laminado de 1mm a 5mm
A14: 52 | B14: Teresita Gallegos | C14: Planta 3/4 | D14: Redactado como 'Se propone' — ¿ya se implementó? | E14: Confirmar implementación | F14: Actualmente cada prensa tiene un tiempo ciclo de 157.1 segundos por disparo generando la inyeccion de 8 piezas en cada disparo. | G14: Se propone disminuir la distacia de cierre de platinas de 700 mm a 600 mm, para disminuir el tiempo de ciclo.
A15: 77 | B15: Fernando Rodriguez Garcia | C15: Planta 1 | D15: Indicador 'Medio Ambiente' pero el beneficio principal es método/eficiencia | E15: Corregir indicador | F15: La inspección de escaleras en papel causaba pérdida de información, complicaba el seguimiento de hallazgos y generaba altos costos de impresión y almacenamiento | G15: Se implementó un código QR vinculado a una plataforma digital para registrar las inspecciones de escaleras de forma electrónica y Reduce el consumo de papel e impresión, disminuyendo costos y apoyando el cuidado del medio ambiente.
A16: 83 | B16: Citlalli Ozuna | C16: Planta 3/4 | D16: Alcance dudoso: rack de termos, beneficio de servicio más que de proceso | E16: Validar alcance | F16: Rack de termos | G16: Rack para colocar termos de personal operativo
